Workbook

Sheet Painel
A2: Controle jurídico
A3: Escolha uma opção abaixo ou use os filtros em amarelo para acompanhar a carteira.
A4: =IFERROR(HYPERLINK("#'Painel'!A1","Painel"),"Painel") -> Painel | D4: =IFERROR(HYPERLINK("#'Ficha'!C6","Ficha do processo"),"Ficha do processo") -> Ficha do processo | G4: =IFERROR(HYPERLINK("#'Central IA'!C6","Central IA"),"Central IA") -> Central IA | J4: =IFERROR(HYPERLINK("#'Críticos'!A1","Críticos"),"Críticos") -> Críticos | M4: =IFERROR(HYPERLINK("#'Escritórios'!A1","Escritórios"),"Escritórios") -> Escritórios | P4: =IFERROR(HYPERLINK("#'Configurar'!A1","Configurar"),"Configurar") -> Configurar
A5: =IFERROR(HYPERLINK("#'Processos'!A9","Cadastrar ou editar"),"Cadastrar ou editar") -> Cadastrar ou editar | G5: =IFERROR(HYPERLINK("#'Valores'!A9","Informar valores"),"Informar valores") -> Informar valores | M5: =IFERROR(HYPERLINK("#'Andamentos'!A9","Consultar histórico"),"Consultar histórico") -> Consultar histórico
A6: ESCRITÓRIO | C6: Todos | J6: EMPRESA | L6: Todas
A8: CONSÓRCIO | C8: Todos | J8: TEMA | L8: Todos
A10: BUSCA | N10: Digite o número ou o nome de uma parte.
A12: =A15&" registros / "&SUM(Processos!$BC$10:$BC$509)&" números principais no filtro. Use a Ficha para consultar." -> 148 registros / 138 números principais no filtro. Use a Ficha para consultar.
A14: REGISTROS | K14: CRÍTICOS
A15: =COUNTIFS(Processos!$X$10:$X$509,1) -> 148 | K15: =COUNTIFS(Processos!$X$10:$X$509,1,Processos!$Y$10:$Y$509,1) -> 7
A17: linhas de acompanhamento no filtro | K17: prioridade ou restrição vigente
A19: ="Cobrar atualização: "&COUNTIFS(Processos!$X$10:$X$509,1,Processos!$AD$10:$AD$509,1)&" processos" -> Cobrar atualização: 87 processos
A20: ="Ativos: "&COUNTIFS(Processos!$X$10:$X$509,1,Processos!$C$10:$C$509,"Ativo")&" Suspensos: "&COUNTIFS(Processos!$X$10:$X$509,1,Processos!$C$10:$C$509,"Suspenso") -> Ativos: 74 Suspensos: 17 | K20: ="Encerrados: "&COUNTIFS(Processos!$X$10:$X$509,1,Processos!$C$10:$C$509,"Encerrado")&" Arquivados: "&COUNTIFS(Processos!$X$10:$X$509,1,Processos!$C$10:$C$509,"Arquivado") -> Encerrados: 15 Arquivados: 40
A22: ="Conferir preenchimento (carteira inteira): "&SUMPRODUCT(--(Processos!$AI$10:$AI$509<>""))&" cadastros, "&SUMPRODUCT(--(Valores!$N$10:$N$509<>""))&" valores e "&SUMPRODUCT(--(Andamentos!$I$10:$I$2009<>""))&" andamentos." -> Conferir preenchimento (carteira inteira): 148 cadastros, 119 valores e 55 andamentos.
A23: =IFERROR(HYPERLINK("#'Processos'!AI9","REVISAR CADASTROS"),"REVISAR CADASTROS") -> REVISAR CADASTROS | K23: =IFERROR(HYPERLINK("#'Valores'!N9","REVISAR VALORES"),"REVISAR VALORES") -> REVISAR VALORES | P23: =IFERROR(HYPERLINK("#'Andamentos'!I9","REVISAR HISTÓRICO"),"REVISAR HISTÓRICO") -> REVISAR HISTÓRICO
A24: VALORES INFORMADOS | K24: PROCESSOS POR TEMA
A26: Depósitos judiciais | F26: =IF(COUNTIFS(Valores!$M$10:$M$509,1,Valores!$D$10:$D$509,">0")+COUNTIFS(Valores!$M$10:$M$509,1,Valores!$D$10:$D$509,"=0",Valores!$D$10:$D$509,"<>")=0,"Não informado",SUMIFS(Valores!$D$10:$D$509,Valores!$M$10:$M$509,1)) -> 137749.46
A27: Bloqueios em dinheiro (saldo) | F27: =IF(COUNTIFS(Valores!$M$10:$M$509,1,Valores!$E$10:$E$509,">0")+COUNTIFS(Valores!$M$10:$M$509,1,Valores!$E$10:$E$509,"=0",Valores!$E$10:$E$509,"<>")=0,"Não informado",SUMIFS(Valores!$E$10:$E$509,Valores!$M$10:$M$509,1)) -> Não informado
A28: Benefício econômico estimado | F28: =IF(COUNTIFS(Valores!$M$10:$M$509,1,Valores!$G$10:$G$509,">0")+COUNTIFS(Valores!$M$10:$M$509,1,Valores!$G$10:$G$509,"=0",Valores!$G$10:$G$509,"<>")=0,"Não informado",SUMIFS(Valores!$G$10:$G$509,Valores!$M$10:$M$509,1)) -> Não informado
A32: Totais parciais: registros com número repetido ficam fora até a revisão na coluna T de Valores. Sem rateio de consórcio.
A45: =IFERROR(HYPERLINK("#'Processos'!A"&Configurar!$U$13,"CADASTRAR PROCESSO"),"CADASTRAR PROCESSO") -> CADASTRAR PROCESSO | M45: =IFERROR(HYPERLINK("#'Andamentos'!A9","REGISTRAR ANDAMENTO"),"REGISTRAR ANDAMENTO") -> REGISTRAR ANDAMENTO
A48: EMPRESAS | K48: CONSÓRCIOS
A50: =IF(OR(Configurar!B10="",COUNTIFS(Configurar!$B$10:B10,Configurar!B10)>1),"",Configurar!B10) -> Alta Engenharia de Infraestrutura LTDA | G50: =IF(A50="","",COUNTIFS(Processos!$X$10:$X$509,1,Processos!$E$10:$E$509,A50)) -> 0 | K50: =IF(OR(Configurar!C10="",COUNTIFS(Configurar!$C$10:C10,Configurar!C10)>1),"",Configurar!C10) -> Sem consórcio | Q50: =IF(K50="","",COUNTIFS(Processos!$X$10:$X$509,1,Processos!$F$10:$F$509,K50)) -> 0
A51: =IF(OR(Configurar!B11="",COUNTIFS(Configurar!$B$10:B11,Configurar!B11)>1),"",Configurar!B11) -> Cava Engenharia de Infraestrutura LTDA | G51: =IF(A51="","",COUNTIFS(Processos!$X$10:$X$509,1,Processos!$E$10:$E$509,A51)) -> 0 | K51: =IF(OR(Configurar!C11="",COUNTIFS(Configurar!$C$10:C11,Configurar!C11)>1),"",Configurar!C11) -> Consórcio Trail-Spavias-Alta | Q51: =IF(K51="","",COUNTIFS(Processos!$X$10:$X$509,1,Processos!$F$10:$F$509,K51)) -> 14
A52: =IF(OR(Configurar!B12="",COUNTIFS(Configurar!$B$10:B12,Configurar!B12)>1),"",Configurar!B12) -> Planep | G52: =IF(A52="","",COUNTIFS(Processos!$X$10:$X$509,1,Processos!$E$10:$E$509,A52)) -> 0 | K52: =IF(OR(Configurar!C12="",COUNTIFS(Configurar!$C$10:C12,Configurar!C12)>1),"",Configurar!C12) -> Consórcio Integral Spavias Trail Alta | Q52: =IF(K52="","",COUNTIFS(Processos!$X$10:$X$509,1,Processos!$F$10:$F$509,K52)) -> 48
A53: =IF(OR(Configurar!B13="",COUNTIFS(Configurar!$B$10:B13,Configurar!B13)>1),"",Configurar!B13) -> Strata Engenharia | G53: =IF(A53="","",COUNTIFS(Processos!$X$10:$X$509,1,Processos!$E$10:$E$509,A53)) -> 0 | K53: =IF(OR(Configurar!C13="",COUNTIFS(Configurar!$C$10:C13,Configurar!C13)>1),"",Configurar!C13) -> Consórcio Spavias Cava | Q53: =IF(K53="","",COUNTIFS(Processos!$X$10:$X$509,1,Processos!$F$10:$F$509,K53)) -> 7
A54: =IF(OR(Configurar!B14="",COUNTIFS(Configurar!$B$10:B14,Configurar!B14)>1),"",Configurar!B14) -> Alltech | G54: =IF(A54="","",COUNTIFS(Processos!$X$10:$X$509,1,Processos!$E$10:$E$509,A54)) -> 0 | K54: =IF(OR(Configurar!C14="",COUNTIFS(Configurar!$C$10:C14,Configurar!C14)>1),"",Configurar!C14) -> Consórcio Spavias Serne Spavias Trail Alta | Q54: =IF(K54="","",COUNTIFS(Processos!$X$10:$X$509,1,Processos!$F$10:$F$509,K54)) -> 2
A55: =IF(OR(Configurar!B15="",COUNTIFS(Configurar!$B$10:B15,Configurar!B15)>1),"",Configurar!B15) -> Altabio Eucalipto | G55: =IF(A55="","",COUNTIFS(Processos!$X$10:$X$509,1,Processos!$E$10:$E$509,A55)) -> 0 | K55: =IF(OR(Configurar!C15="",COUNTIFS(Configurar!$C$10:C15,Configurar!C15)>1),"",Configurar!C15) -> Consórcio Loctec Pavienge Cava Alta Setorsul | Q55: =IF(K55="","",COUNTIFS(Processos!$X$10:$X$509,1,Processos!$F$10:$F$509,K55)) -> 10
A56: =IF(OR(Configurar!B16="",COUNTIFS(Configurar!$B$10:B16,Configurar!B16)>1),"",Configurar!B16) -> Altabio Pecuária | G56: =IF(A56="","",COUNTIFS(Processos!$X$10:$X$509,1,Processos!$E$10:$E$509,A56)) -> 0 | K56: =IF(OR(Configurar!C16="",COUNTIFS(Configurar!$C$10:C16,Configurar!C16)>1),"",Configurar!C16) -> Consórcio Spavias Alta | Q56: =IF(K56="","",COUNTIFS(Processos!$X$10:$X$509,1,Processos!$F$10:$F$509,K56)) -> 7
A57: =IF(OR(Configurar!B17="",COUNTIFS(Configurar!$B$10:B17,Configurar!B17)>1),"",Configurar!B17) -> CPC - Consultoria e Participações | G57: =IF(A57="","",COUNTIFS(Processos!$X$10:$X$509,1,Processos!$E$10:$E$509,A57)) -> 0 | K57: =IF(OR(Configurar!C17="",COUNTIFS(Configurar!$C$10:C17,Configurar!C17)>1),"",Configurar!C17) -> Consórcio GA 060 | Q57: =IF(K57="","",COUNTIFS(Processos!$X$10:$X$509,1,Processos!$F$10:$F$509,K57)) -> 1
A58: =IF(OR(Configurar!B18="",COUNTIFS(Configurar!$B$10:B18,Configurar!B18)>1),"",Configurar!B18) -> Camilo de Léllis Nogueira (PF) | G58: =IF(A58="","",COUNTIFS(Processos!$X$10:$X$509,1,Processos!$E$10:$E$509,A58)) -> 0 | K58: =IF(OR(Configurar!C18="",COUNTIFS(Configurar!$C$10:C18,Configurar!C18)>1),"",Configurar!C18) -> Consórcio Alta-ECP | Q58: =IF(K58="","",COUNTIFS(Processos!$X$10:$X$509,1,Processos!$F$10:$F$509,K58)) -> 3
K59: =IF(OR(Configurar!C19="",COUNTIFS(Configurar!$C$10:C19,Configurar!C19)>1),"",Configurar!C19) -> Consórcio JEA (JM/EHL/Alta) | Q59: =IF(K59="","",COUNTIFS(Processos!$X$10:$X$509,1,Processos!$F$10:$F$509,K59)) -> 3
A60: Empresa não informada / fora da lista | G60: =COUNTIFS(Processos!$X$10:$X$509,1)-SUM(G50:G58) -> 148 | K60: Demais / sem classificação | Q60: =COUNTIFS(Processos!$X$10:$X$509,1)-SUM(Q50:Q59) -> 53

Sheet Ficha
A2: Ficha do processo
A3: Escolha o processo no campo amarelo. Use os atalhos abaixo para editar o cadastro, informar valores ou abrir o tribunal.
A4: =IFERROR(HYPERLINK("#'Painel'!A1","Painel"),"Painel") -> Painel | D4: =IFERROR(HYPERLINK("#'Ficha'!C6","Ficha do processo"),"Ficha do processo") -> Ficha do processo | G4: =IFERROR(HYPERLINK("#'Central IA'!C6","Central IA"),"Central IA") -> Central IA | J4: =IFERROR(HYPERLINK("#'Críticos'!A1","Críticos"),"Críticos") -> Críticos | M4: =IFERROR(HYPERLINK("#'Escritórios'!A1","Escritórios"),"Escritórios") -> Escritórios | P4: =IFERROR(HYPERLINK("#'Configurar'!A1","Configurar"),"Configurar") -> Configurar
A5: =IFERROR(HYPERLINK("#'Processos'!A9","Cadastrar ou editar"),"Cadastrar ou editar") -> Cadastrar ou editar | G5: =IFERROR(HYPERLINK("#'Valores'!A9","Informar valores"),"Informar valores") -> Informar valores | M5: =IFERROR(HYPERLINK("#'Andamentos'!A9","Consultar histórico"),"Consultar histórico") -> Consultar histórico
A6: PROCESSO | C6: 0016196-95.2018.5.16.0017 | N6: =IF(C6="","Selecione um processo",IF(Configurar!$U$10=0,"Número não encontrado ou duplicado",INDEX(Processos!$C$10:$C$509,Configurar!$U$10))) -> Ativo
A9: =IFERROR(HYPERLINK("#'Processos'!A"&IF(Configurar!$U$10=0,9,Configurar!$U$10+9),"EDITAR CADASTRO"),"EDITAR CADASTRO") -> EDITAR CADASTRO | H9: =IFERROR(HYPERLINK("#'Valores'!A"&IF(Configurar!$U$11=0,9,Configurar!$U$11+9),"ATUALIZAR VALORES"),"ATUALIZAR VALORES") -> ATUALIZAR VALORES | N9: =IFERROR(IF(Configurar!$U$10=0,"CONSULTAR TRIBUNAL",IF(OR(IFERROR(INDEX(Critérios!$K$10:$K$32,MATCH(INDEX(Processos!$K$10:$K$509,Configurar!$U$10),Critérios!$J$10:$J$32,0)),"")="",IFERROR(INDEX(Critérios!$K$10:$K$32,MATCH(INDEX(Processos!$K$10:$K$509,Configurar!$U$10),Critérios!$J$10:$J$32,0)),"")=0),"IDENTIFICAR ÓRGÃO",HYPERLINK(IFERROR(INDEX(Critérios!$K$10:$K$32,MATCH(INDEX(Processos!$K$10:$K$509,Configurar!$U$10),Critérios!$J$10:$J$32,0)),""),"CONSULTAR TRIBUNAL"))),"CONSULTAR TRIBUNAL") -> CONSULTAR TRIBUNAL
A11: EMPRESA | H11: CONSÓRCIO | N11: ESCRITÓRIO
A12: =IF(Configurar!$U$10=0,"",IF(INDEX(Processos!$E$10:$E$509,Configurar!$U$10)="","Não informado",INDEX(Processos!$E$10:$E$509,Configurar!$U$10))) -> Não informado | H12: =IF(Configurar!$U$10=0,"",IF(INDEX(Processos!$F$10:$F$509,Configurar!$U$10)="","Não informado",INDEX(Processos!$F$10:$F$509,Configurar!$U$10))) -> Consórcio Integral Spavias Trail Alta | N12: =IF(Configurar!$U$10=0,"",IF(INDEX(Processos!$D$10:$D$509,Configurar!$U$10)="","Não informado",INDEX(Processos!$D$10:$D$509,Configurar!$U$10))) -> BMM Advogados
A15: PARTE AUTORA | K15: PARTE RÉ
A16: =IF(LEN(IF(Configurar!$U$10=0,"",IF(INDEX(Processos!$H$10:$H$509,Configurar!$U$10)="","Não informado",INDEX(Processos!$H$10:$H$509,Configurar!$U$10))))>450,LEFT(SUBSTITUTE(SUBSTITUTE(IF(Configurar!$U$10=0,"",IF(INDEX(Processos!$H$10:$H$509,Configurar!$U$10)="","Não informado",INDEX(Processos!$H$10:$H$509,Configurar!$U$10))),CHAR(10)," "),CHAR(13)," "),450)&" [...] Consulte o cadastro completo.",SUBSTITUTE(SUBSTITUTE(IF(Configurar!$U$10=0,"",IF(INDEX(Processos!$H$10:$H$509,Configurar!$U$10)="","Não informado",INDEX(Processos!$H$10:$H$509,Configurar!$U$10))),CHAR(10)," "),CHAR(13)," ")) -> RAIMUNDO DIAS DA SILVA | K16: =IF(LEN(IF(Configurar!$U$10=0,"",IF(INDEX(Processos!$I$10:$I$509,Configurar!$U$10)="","Não informado",INDEX(Processos!$I$10:$I$509,Configurar!$U$10))))>450,LEFT(SUBSTITUTE(SUBSTITUTE(IF(Configurar!$U$10=0,"",IF(INDEX(Processos!$I$10:$I$509,Configurar!$U$10)="","Não informado",INDEX(Processos!$I$10:$I$509,Configurar!$U$10))),CHAR(10)," "),CHAR(13)," "),450)&" [...] Consulte o cadastro completo.",SUBSTITUTE(SUBSTITUTE(IF(Configurar!$U$10=0,"",IF(INDEX(Processos!$I$10:$I$509,Configurar!$U$10)="","Não informado",INDEX(Processos!$I$10:$I$509,Configurar!$U$10))),CHAR(10)," "),CHAR(13)," ")) -> CONSÓRCIO INTEGRAL SPAVIAS TRAIL ALTA
A20: TEMA / NATUREZA | H20: COMARCA / TRIBUNAL | N20: CRITICIDADE DE ORIGEM
A21: =IF(Configurar!$U$10=0,"",INDEX(Processos!$G$10:$G$509,Configurar!$U$10)&" / "&INDEX(Processos!$B$10:$B$509,Configurar!$U$10)) -> Trabalhista / Judicial | H21: =IF(Configurar!$U$10=0,"",INDEX(Processos!$J$10:$J$509,Configurar!$U$10)&" / "&INDEX(Processos!$K$10:$K$509,Configurar!$U$10)) -> VT de Estreito/MA / TRT 16ª Região (MA) | N21: =IF($C$6="","",IFERROR(IF(OR(INDEX(Origem!$AB$10:$AB$509,MATCH($C$6,Origem!$A$10:$A$509,0))="",INDEX(Origem!$AB$10:$AB$509,MATCH($C$6,Origem!$A$10:$A$509,0))="—"),"Sem classificação",INDEX(Origem!$AB$10:$AB$509,MATCH($C$6,Origem!$A$10:$A$509,0))&CHAR(10)&IF(INDEX(Origem!$AC$10:$AC$509,MATCH($C$6,Origem!$A$10:$A$509,0))="","Sem pontuação",INDEX(Origem!$AC$10:$AC$509,MATCH($C$6,Origem!$A$10:$A$509,0))&" pontos")),"Sem classificação")) -> 🔴 CRÍTICO 70 pontos
A24: FATOS E MOTIVOS
A25: =IF(LEN(IF(Configurar!$U$10=0,"",IF(INDEX(Processos!$M$10:$M$509,Configurar!$U$10)="","Não informado",INDEX(Processos!$M$10:$M$509,Configurar!$U$10))))>620,LEFT(IF(Configurar!$U$10=0,"",IF(INDEX(Processos!$M$10:$M$509,Configurar!$U$10)="","Não informado",INDEX(Processos!$M$10:$M$509,Configurar!$U$10))),620)&" [...] Consulte o texto integral na base.",IF(Configurar!$U$10=0,"",IF(INDEX(Processos!$M$10:$M$509,Configurar!$U$10)="","Não informado",INDEX(Processos!$M$10:$M$509,Configurar!$U$10)))) -> Trata-se de um processo trabalhista em que o reclamante alega ter laborado em jornada extraordinária habitual, sem o devido pagamento das horas extras.
A29: INSTAURAÇÃO | H29: PREVISÃO DE ENCERRAMENTO | N29: PRIORIDADE / RESTRIÇÕES
A30: =IF(Configurar!$U$10=0,"",IF(INDEX(Processos!$L$10:$L$509,Configurar!$U$10)="","Não informado",INDEX(Processos!$L$10:$L$509,Configurar!$U$10))) -> Não informado | H30: =IF(Configurar!$U$10=0,"",IF(INDEX(Processos!$S$10:$S$509,Configurar!$U$10)="","Não informado",INDEX(Processos!$S$10:$S$509,Configurar!$U$10))) -> Não informado | N30: =IF(Configurar!$U$10=0,"",IF(INDEX(Processos!$N$10:$N$509,Configurar!$U$10)="","Prioridade não informada",INDEX(Processos!$N$10:$N$509,Configurar!$U$10))&CHAR(10)&"Bloqueio: "&IF(INDEX(Processos!$O$10:$O$509,Configurar!$U$10)="","não informado",INDEX(Processos!$O$10:$O$509,Configurar!$U$10))&" / Penhora: "&IF(INDEX(Processos!$P$10:$P$509,Configurar!$U$10)="","não informada",INDEX(Processos!$P$10:$P$509,Configurar!$U$10))) -> Crítica Bloqueio: não informado / Penhora: não informada
A33: ANDAMENTO
A35: ÚLTIMO ANDAMENTO REGISTRADO
A36: =IF(LEN(IF(Configurar!$U$10=0,"",IF(INDEX(Processos!$AC$10:$AC$509,Configurar!$U$10)="","Não informado",INDEX(Processos!$AC$10:$AC$509,Configurar!$U$10))))>650,LEFT(IF(Configurar!$U$10=0,"",IF(INDEX(Processos!$AC$10:$AC$509,Configurar!$U$10)="","Não informado",INDEX(Processos!$AC$10:$AC$509,Configurar!$U$10))),650)&" [...] Consulte o texto integral na base.",IF(Configurar!$U$10=0,"",IF(INDEX(Processos!$AC$10:$AC$509,Configurar!$U$10)="","Não informado",INDEX(Processos!$AC$10:$AC$509,Configurar!$U$10)))) -> 07/0/2023 - Remetido os autos para TST para processar recurso. [...] histórico completo em Observações
A40: DATA DO ANDAMENTO | H40: REGISTRADO / ATUALIZADO
A41: =IF(Configurar!$U$10=0,"",IF(INDEX(Processos!$AP$10:$AP$509,Configurar!$U$10)="","Não informado",INDEX(Processos!$AP$10:$AP$509,Configurar!$U$10))) -> Não informado | H41: =IF(Configurar!$U$10=0,"",IF(INDEX(Processos!$Z$10:$Z$509,Configurar!$U$10)="","Não informado",INDEX(Processos!$Z$10:$Z$509,Configurar!$U$10))) -> 46055
A49: FINANCEIRO E AVALIAÇÃO DO ESCRITÓRIO
A51: VALOR DA CAUSA | H51: CONDENAÇÃO / EXECUÇÃO | N51: ÊXITO ESTIMADO
A52: =IF(Configurar!$U$10=0,"",IF(Configurar!$U$11=0,"Não informado",IF(INDEX(Valores!$B$10:$B$509,Configurar!$U$11)="","Não informado",INDEX(Valores!$B$10:$B$509,Configurar!$U$11)))) -> 119383.18 | H52: =IF(Configurar!$U$10=0,"",IF(Configurar!$U$11=0,"Não informado",IF(INDEX(Valores!$C$10:$C$509,Configurar!$U$11)="","Não informado",INDEX(Valores!$C$10:$C$509,Configurar!$U$11)))) -> 108062.21 | N52: =IF(Configurar!$U$10=0,"",IF(Configurar!$U$11=0,"Não informado",IF(INDEX(Valores!$H$10:$H$509,Configurar!$U$11)="","Não informado",INDEX(Valores!$H$10:$H$509,Configurar!$U$11)))) -> Não informado
A55: DEPÓSITOS JUDICIAIS | H55: BLOQUEIOS (SALDO)
A56: =IF(Configurar!$U$10=0,"",IF(Configurar!$U$11=0,"Não informado",IF(INDEX(Valores!$D$10:$D$509,Configurar!$U$11)="","Não informado",INDEX(Valores!$D$10:$D$509,Configurar!$U$11)))) -> Não informado | H56: =IF(Configurar!$U$10=0,"",IF(Configurar!$U$11=0,"Não informado",IF(INDEX(Valores!$E$10:$E$509,Configurar!$U$11)="","Não informado",INDEX(Valores!$E$10:$E$509,Configurar!$U$11)))) -> Não informado
A59: BENEFÍCIO ESTIMADO | H59: REVISADO EM | N59: COBRAR ATUALIZAÇÃO
A60: =IF(Configurar!$U$10=0,"",IF(Configurar!$U$11=0,"Não informado",IF(INDEX(Valores!$G$10:$G$509,Configurar!$U$11)="","Não informado",INDEX(Valores!$G$10:$G$509,Configurar!$U$11)))) -> Não informado | H60: =IF(Configurar!$U$10=0,"",IF(Configurar!$U$11=0,"Não informado",IF(INDEX(Valores!$J$10:$J$509,Configurar!$U$11)="","Não informado",INDEX(Valores!$J$10:$J$509,Configurar!$U$11)))) -> Não informado | N60: =IF(Configurar!$U$10=0,"",IF(INDEX(Processos!$AD$10:$AD$509,Configurar!$U$10)=1,"Sim","Não")) -> Sim
A68: OBSERVAÇÕES
A69: =IF(LEN(IF(Configurar!$U$10=0,"",IF(INDEX(Processos!$U$10:$U$509,Configurar!$U$10)="","Sem observações adicionais",INDEX(Processos!$U$10:$U$509,Configurar!$U$10))))>900,LEFT(IF(Configurar!$U$10=0,"",IF(INDEX(Processos!$U$10:$U$509,Configurar!$U$10)="","Sem observações adicionais",INDEX(Processos!$U$10:$U$509,Configurar!$U$10))),900)&" [...] Consulte o texto integral na base.",IF(Configurar!$U$10=0,"",IF(INDEX(Processos!$U$10:$U$509,Configurar!$U$10)="","Sem observações adicionais",INDEX(Processos!$U$10:$U$509,Configurar!$U$10)))) -> Origem: BMM!54 | ID BMM-050 | Situação original: Ativo | Fase: Execução | Probabilidade de perda original: Provável | Avaliação original: PROVÁVEL INCLUSÃO POR IDPJ | Contrato: RDC 6 | Última atualização informada: 2026-02-02
A73: Atualize Processos, Valores e Andamentos. Classificação e pontuação de origem são históricas; critérios detalhados na aba Critérios.
A76: =IF(Configurar!$U$10=0,"DOCUMENTOS",IF(INDEX(Processos!$T$10:$T$509,Configurar!$U$10)="","Sem link de documentos",IFERROR(HYPERLINK(INDEX(Processos!$T$10:$T$509,Configurar!$U$10),"ABRIR DOCUMENTOS"),"ABRIR DOCUMENTOS"))) -> Sem link de documentos | K76: =IFERROR(HYPERLINK("#'Andamentos'!A9","VER HISTÓRICO COMPLETO"),"VER HISTÓRICO COMPLETO") -> VER HISTÓRICO COMPLETO
A79: DETALHES FINANCEIROS E REGISTRO ORIGINAL
A81: Valor atualizado da causa | H81: =IF(Configurar!$U$11=0,"Não informado",IF(INDEX(Valores!$U$10:$U$509,Configurar!$U$11)="","Não informado",INDEX(Valores!$U$10:$U$509,Configurar!$U$11))) -> Não informado
A86: Perda classificada na origem | H86: =IF(Configurar!$U$11=0,"Não informado",IF(INDEX(Valores!$Z$10:$Z$509,Configurar!$U$11)="","Não informado",INDEX(Valores!$Z$10:$Z$509,Configurar!$U$11))) -> Provável
A87: Duração estimada | H87: =IF(Configurar!$U$11=0,"Não informado",IF(INDEX(Valores!$AA$10:$AA$509,Configurar!$U$11)="","Não informado",INDEX(Valores!$AA$10:$AA$509,Configurar!$U$11))) -> Não informado
A89: Benefício econômico descrito | H89: =IF(Configurar!$U$11=0,"Não informado",IF(INDEX(Valores!$Y$10:$Y$509,Configurar!$U$11)="","Não informado",INDEX(Valores!$Y$10:$Y$509,Configurar!$U$11))) -> Não informado
A97: Incluir nos totais financeiros? | H97: =IF(Configurar!$U$11=0,"Não informado",IF(INDEX(Valores!$T$10:$T$509,Configurar!$U$11)="","Não informado",INDEX(Valores!$T$10:$T$509,Configurar!$U$11))) -> Sim
A100: =IFERROR(IF(COUNTIFS(Origem!$A$10:$A$157,C6)=1,HYPERLINK("#'Origem'!A"&(MATCH(C6,Origem!$A$10:$A$157,0)+9),"ABRIR REGISTRO ORIGINAL COMPLETO"),"Processo cadastrado após a migração"),"ABRIR REGISTRO ORIGINAL COMPLETO") -> ABRIR REGISTRO ORIGINAL COMPLETO
A101: Classificações e datas importadas retratam a planilha recebida; não indicam uma nova consulta aos autos.

Sheet Central IA
A2: Central IA
A3: 1. Cole o texto recebido. 2. Escolha Analisar texto. 3. Confira a prévia e aplique os itens aprovados.
A4: =IFERROR(HYPERLINK("#'Painel'!A1","Painel"),"Painel") -> Painel | D4: =IFERROR(HYPERLINK("#'Ficha'!C6","Ficha do processo"),"Ficha do processo") -> Ficha do processo | G4: =IFERROR(HYPERLINK("#'Configurar'!G64","Como conectar a IA"),"Como conectar a IA") -> Como conectar a IA
A6: 2. ESCOLHA A AÇÃO | G6: Conectado
A8: PROCESSO, SE SOUBER | C8: 0010752-95.2020.5.18.0101 | G8: FONTE DO TEXTO
A10: ESCRITÓRIO PADRÃO | C10: Frois | G10: EMPRESA PADRÃO
A12: CONSÓRCIO PADRÃO | C12: Consórcio Integral Spavias Trail Alta
A14: COMO SALVAR | C14: Revisar tudo | G14: ÚLTIMA EXECUÇÃO | H14: 21/10/2026 19:42
A16: 1. COLE O TEXTO ABAIXO. Clique na área amarela, pressione F2 e cole.
A17: Processo movido via forum
A24: Cadastro salvo. O processo já está disponível para consulta e atualização.
A27: 3. CONFIRA A PRÉVIA. Marque Sim no que deseja salvar e escolha Aplicar aprovados na ação acima.
A28: Aplicar? | B28: Processo | C28: Destino | D28: Campo / operação | E28: Atual | F28: Proposto | G28: Trecho da fonte | H28: Observação | I28: ID | J28: Aplicado em

Sheet Críticos
A2: Processos críticos
A3: Ativos ou suspensos com prioridade Crítica, bloqueio ou penhora vigente. As cores indicam a classificação de origem.
A4: =IFERROR(HYPERLINK("#'Painel'!A1","Painel"),"Painel") -> Painel | D4: =IFERROR(HYPERLINK("#'Ficha'!C6","Ficha do processo"),"Ficha do processo") -> Ficha do processo | G4: =IFERROR(HYPERLINK("#'Central IA'!C6","Atualizar com IA"),"Atualizar com IA") -> Atualizar com IA
A5: As listas seguem os filtros escolhidos no Painel.
A6: =COUNTIFS(Processos!$X$10:$X$509,1,Processos!$Y$10:$Y$509,1)&" processos críticos na seleção do Painel" -> 7 processos críticos na seleção do Painel
A7: Para consultar um caso, copie o número e selecione-o na Ficha. Cada página mostra até 50 registros.
C8: Página | D8: 1 | E8: =IFERROR(HYPERLINK("#'Critérios'!A6","VER CORES E CRITÉRIOS"),"VER CORES E CRITÉRIOS") -> VER CORES E CRITÉRIOS | I8: =MAX(1,ROUNDUP(COUNTIFS(Processos!$X$10:$X$509,1,Processos!$Y$10:$Y$509,1)/50,0)) -> 1 | J8: =MAX(1,MIN(IFERROR(INT(D8),1),I8)) -> 1
A9: Processo | B9: Escritório | C9: Autor × réu | D9: Fatos e motivos | E9: Por que é crítico | F9: Valor da causa | G9: Consultar
A10: =IF((ROW()-9+($J$8-1)*50)>COUNTIFS(Processos!$X$10:$X$509,1,Processos!$Y$10:$Y$509,1),"",IF(INDEX(Processos!$A$10:$A$509,MATCH((ROW()-9+($J$8-1)*50),Processos!$AJ$10:$AJ$509,0))="","",INDEX(Processos!$A$10:$A$509,MATCH((ROW()-9+($J$8-1)*50),Processos!$AJ$10:$AJ$509,0)))) -> 0016196-95.2018.5.16.0017 | B10: =IF((ROW()-9+($J$8-1)*50)>COUNTIFS(Processos!$X$10:$X$509,1,Processos!$Y$10:$Y$509,1),"",IF(INDEX(Processos!$D$10:$D$509,MATCH((ROW()-9+($J$8-1)*50),Processos!$AJ$10:$AJ$509,0))="","",INDEX(Processos!$D$10:$D$509,MATCH((ROW()-9+($J$8-1)*50),Processos!$AJ$10:$AJ$509,0)))) -> BMM Advogados | C10: =IF(LEN(SUBSTITUTE(SUBSTITUTE(IF(LEN(IF((ROW()-9+($J$8-1)*50)>COUNTIFS(Processos!$X$10:$X$509,1,Processos!$Y$10:$Y$509,1),"",IF(INDEX(Processos!$H$10:$H$509,MATCH((ROW()-9+($J$8-1)*50),Processos!$AJ$10:$AJ$509,0))&" × "&INDEX(Processos!$I$10:$I$509,MATCH((ROW()-9+($J$8-1)*50),Processos!$AJ$10:$AJ$509,0))="","",INDEX(Processos!$H$10:$H$509,MATCH((ROW()-9+($J$8-1)*50),Processos!$AJ$10:$AJ$509,0))&" × "&INDEX(Processos!$I$10:$I$509,MATCH((ROW()-9+($J$8-1)*50),Processos!$AJ$10:$AJ$509,0)))))>190,LEFT(IF((ROW()-9+($J$8-1)*50)>COUNTIFS(Processos!$X$10:$X$509,1,Processos!$Y$10:$Y$509,1),"",IF(INDEX(Processos!$H$10:$H$509,MATCH((ROW()-9+($J$8-1)*50),Processos!$AJ$10:$AJ$509,0))&" × "&INDEX(Processos!$I$10:$I$509,MATCH((ROW()-9+($J$8-1)*50),Processos!$AJ$10:$AJ$509,0))="","",INDEX(Processos!$H$10:$H$509,MATCH((ROW()-9+($J$8-1)*50),Processos!$AJ$10:$AJ$509,0))&" × "&INDEX(Processos!$I$10:$I$509,MATCH((ROW()-9+($J$8-1)*50),Processos!$AJ$10:$AJ$509,0)))),190)&" [...]",IF((ROW()-9+($J$8-1)*50)>COUNTIFS(Processos!$X$10:$X$509,1,Processos!$Y$10:$Y$509,1),"",IF(INDEX(Processos!$H$10:$H$509,MATCH((ROW()-9+($J$8-1)*50),Processos!$AJ$10:$AJ$509,0))&" × "&INDEX(Processos!$I$10:$I$509,MATCH((ROW()-9+($J$8-1)*50),Processos!$AJ$10:$AJ$509,0))="","",INDEX(Processos!$H$10:$H$509,MATCH((ROW()-9+($J$8-1)*50),Processos!$AJ$10:$AJ$509,0))&" × "&INDEX(Processos!$I$10:$I$509,MATCH((ROW()-9+($J$8-1)*50),Processos!$AJ$10:$AJ$509,0))))),CHAR(10)," "),CHAR(13)," "))>150,LEFT(SUBSTITUTE(SUBSTITUTE(IF(LEN(IF((ROW()-9+($J$8-1)*50)>COUNTIFS(Processos!$X$10:$X$509,1,Processos!$Y$10:$Y$509,1),"",IF(INDEX(Processos!$H$10:$H$509,MATCH((ROW()-9+($J$8-1)*50),Processos!$AJ$10:$AJ$509,0))&" × "&INDEX(Processos!$I$10:$I$509,MATCH((ROW()-9+($J$8-1)*50),Processos!$AJ$10:$AJ$509,0))="","",INDEX(Processos!$H$10:$H$509,MATCH((ROW()-9+($J$8-1)*50),Processos!$AJ$10:$AJ$509,0))&" × "&INDEX(Processos!$I$10:$I$509,MATCH((ROW()-9+($J$8-1)*50),Processos!$AJ$10:$AJ$509,0)))))>190,LEFT(IF((ROW()-9+($J$8-1)*50)>COUNTIFS(Processos!$X$10:$X$509,1,Processos!$Y$10:$Y$509,1),"",IF(INDEX(Processos!$H$10:$H$509,MATCH((ROW()-9+($J$8-1)*50),Processos!$AJ$10:$AJ$509,0))&" × "&INDEX(Processos!$I$10:$I$509,MATCH((ROW()-9+($J$8-1)*50),Processos!$AJ$10:$AJ$509,0))="","",INDEX(Processos!$H$10:$H$509,MATCH((ROW()-9+($J$8-1)*50),Processos!$AJ$10:$AJ$509,0))&" × "&INDEX(Processos!$I$10:$I$509,MATCH((ROW()-9+($J$8-1)*50),Processos!$AJ$10:$AJ$509,0)))),190)&" [...]",IF((ROW()-9+($J$8-1)*50)>COUNTIFS(Processos!$X$10:$X$509,1,Processos!$Y$10:$Y$509,1),"",IF(INDEX(Processos!$H$10:$H$509,MATCH((ROW()-9+($J$8-1)*50),Processos!$AJ$10:$AJ$509,0))&" × "&INDEX(Processos!$I$10:$I$509,MATCH((ROW()-9+($J$8-1)*50),Processos!$AJ$10:$AJ$509,0))="","",INDEX(Processos!$H$10:$H$509,MATCH((ROW()-9+($J$8-1)*50),Processos!$AJ$10:$AJ$509,0))&" × "&INDEX(Processos!$I$10:$I$509,MATCH((ROW()-9+($J$8-1)*50),Processos!$AJ$10:$AJ$509,0))))),CHAR(10)," "),CHAR(13)," "),150)&" [...]",SUBSTITUTE(SUBSTITUTE(IF(LEN(IF((ROW()-9+($J$8-1)*50)>COUNTIFS(Processos!$X$10:$X$509,1,Processos!$Y$10:$Y$509,1),"",IF(INDEX(Processos!$H$10:$H$509,MATCH((ROW()-9+($J$8-1)*50),Processos!$AJ$10:$AJ$509,0))&" × "&INDEX(Processos!$I$10:$I$509,MATCH((ROW()-9+($J$8-1)*50),Processos!$AJ$10:$AJ$509,0))="","",INDEX(Processos!$H$10:$H$509,MATCH((ROW()-9+($J$8-1)*50),Processos!$AJ$10:$AJ$509,0))&" × "&INDEX(Processos!$I$10:$I$509,MATCH((ROW()-9+($J$8-1)*50),Processos!$AJ$10:$AJ$509,0)))))>190,LEFT(IF((ROW()-9+($J$8-1)*50)>COUNTIFS(Processos!$X$10:$X$509,1,Processos!$Y$10:$Y$509,1),"",IF(INDEX(Processos!$H$10:$H$509,MATCH((ROW()-9+($J$8-1)*50),Processos!$AJ$10:$AJ$509,0))&" × "&INDEX(Processos!$I$10:$I$509,MATCH((ROW()-9+($J$8-1)*50),Processos!$AJ$10:$AJ$509,0))="","",INDEX(Processos!$H$10:$H$509,MATCH((ROW()-9+($J$8-1)*50),Processos!$AJ$10:$AJ$509,0))&" × "&INDEX(Processos!$I$10:$I$509,MATCH((ROW()-9+($J$8-1)*50),Processos!$AJ$10:$AJ$509,0)))),190)&" [...]",IF((ROW()-9+($J$8-1)*50)>COUNTIFS(Processos!$X$10:$X$509,1,Processos!$Y$10:$Y$509,1),"",IF(INDEX(Processos!$H$10:$H$509,MATCH((ROW()-9+($J$8-1)*50),Processos!$AJ$10:$AJ$509,0))&" × "&INDEX(Processos!$I$10:$I$509,MATCH((ROW()-9+($J$8-1)*50),Processos!$AJ$10:$AJ$509,0))="","",INDEX(Processos!$H$10:$H$509,MATCH((ROW()-9+($J$8-1)*50),Processos!$AJ$10:$AJ$509,0))&" × "&INDEX(Processos!$I$10:$I$509,MATCH((ROW()-9+($J$8-1)*50),Processos!$AJ$10:$AJ$509,0))))),CHAR(10)," "),CHAR(13)," ")) -> RAIMUNDO DIAS DA SILVA × CONSÓRCIO INTEGRAL SPAVIAS TRAIL ALTA | D10: =SUBSTITUTE(SUBSTITUTE(IF(LEN(IF((ROW()-9+($J$8-1)*50)>COUNTIFS(Processos!$X$10:$X$509,1,Processos!$Y$10:$Y$509,1),"",IF(INDEX(Processos!$M$10:$M$509,MATCH((ROW()-9+($J$8-1)*50),Processos!$AJ$10:$AJ$509,0))="","",INDEX(Processos!$M$10:$M$509,MATCH((ROW()-9+($J$8-1)*50),Processos!$AJ$10:$AJ$509,0)))))>190,LEFT(IF((ROW()-9+($J$8-1)*50)>COUNTIFS(Processos!$X$10:$X$509,1,Processos!$Y$10:$Y$509,1),"",IF(INDEX(Processos!$M$10:$M$509,MATCH((ROW()-9+($J$8-1)*50),Processos!$AJ$10:$AJ$509,0))="","",INDEX(Processos!$M$10:$M$509,MATCH((ROW()-9+($J$8-1)*50),Processos!$AJ$10:$AJ$509,0)))),190)&" [...]",IF((ROW()-9+($J$8-1)*50)>COUNTIFS(Processos!$X$10:$X$509,1,Processos!$Y$10:$Y$509,1),"",IF(INDEX(Processos!$M$10:$M$509,MATCH((ROW()-9+($J$8-1)*50),Processos!$AJ$10:$AJ$509,0))="","",INDEX(Processos!$M$10:$M$509,MATCH((ROW()-9+($J$8-1)*50),Processos!$AJ$10:$AJ$509,0))))),CHAR(10)," "),CHAR(13)," ") -> Trata-se de um processo trabalhista em que o reclamante alega ter laborado em jornada extraordinária habitual, sem o devido pagamento das horas extras. | E10: =IF($A10="","",IFERROR(INDEX(Processos!$AR$10:$AR$509,MATCH($A10,Processos!$A$10:$A$509,0)),"")&CHAR(10)&IFERROR(IF(OR(INDEX(Origem!$AB$10:$AB$509,MATCH($A10,Origem!$A$10:$A$509,0))="",INDEX(Origem!$AB$10:$AB$509,MATCH($A10,Origem!$A$10:$A$509,0))="—"),"Origem: sem classificação","Origem: "&INDEX(Origem!$AB$10:$AB$509,MATCH($A10,Origem!$A$10:$A$509,0))&IF(INDEX(Origem!$AC$10:$AC$509,MATCH($A10,Origem!$A$10:$A$509,0))=""," (sem pontuação)"," • "&INDEX(Origem!$AC$10:$AC$509,MATCH($A10,Origem!$A$10:$A$509,0))&" pontos")),"Origem: sem classificação")) -> Prioridade crítica. Criticidade herdada da planilha de origem; validar. Não confirma bloqueio/penhora vigente. Origem: 🔴 CRÍTICO • 70 pontos | F10: =IF((ROW()-9+($J$8-1)*50)>COUNTIFS(Processos!$X$10:$X$509,1,Processos!$Y$10:$Y$509,1),"",IF(INDEX(Processos!$AQ$10:$AQ$509,MATCH((ROW()-9+($J$8-1)*50),Processos!$AJ$10:$AJ$509,0))="","",INDEX(Processos!$AQ$10:$AQ$509,MATCH((ROW()-9+($J$8-1)*50),Processos!$AJ$10:$AJ$509,0)))) -> 119383.18 | G10: =IF((ROW()-9+($J$8-1)*50)>COUNTIFS(Processos!$X$10:$X$509,1,Processos!$Y$10:$Y$509,1),"",IFERROR(HYPERLINK("#'Ficha'!C6","Selecionar na Ficha"),"Selecionar na Ficha")) -> Selecionar na Ficha
A11: =IF((ROW()-9+($J$8-1)*50)>COUNTIFS(Processos!$X$10:$X$509,1,Processos!$Y$10:$Y$509,1),"",IF(INDEX(Processos!$A$10:$A$509,MATCH((ROW()-9+($J$8-1)*50),Processos!$AJ$10:$AJ$509,0))="","",INDEX(Processos!$A$10:$A$509,MATCH((ROW()-9+($J$8-1)*50),Processos!$AJ$10:$AJ$509,0)))) -> 0010552-28.2019.5.03.0138 | B11: =IF((ROW()-9+($J$8-1)*50)>COUNTIFS(Processos!$X$10:$X$509,1,Processos!$Y$10:$Y$509,1),"",IF(INDEX(Processos!$D$10:$D$509,MATCH((ROW()-9+($J$8-1)*50),Processos!$AJ$10:$AJ$509,0))="","",INDEX(Processos!$D$10:$D$509,MATCH((ROW()-9+($J$8-1)*50),Processos!$AJ$10:$AJ$509,0)))) -> BMM Advogados | C11: =IF(LEN(SUBSTITUTE(SUBSTITUTE(IF(LEN(IF((ROW()-9+($J$8-1)*50)>COUNTIFS(Processos!$X$10:$X$509,1,Processos!$Y$10:$Y$509,1),"",IF(INDEX(Processos!$H$10:$H$509,MATCH((ROW()-9+($J$8-1)*50),Processos!$AJ$10:$AJ$509,0))&" × "&INDEX(Processos!$I$10:$I$509,MATCH((ROW()-9+($J$8-1)*50),Processos!$AJ$10:$AJ$509,0))="","",INDEX(Processos!$H$10:$H$509,MATCH((ROW()-9+($J$8-1)*50),Processos!$AJ$10:$AJ$509,0))&" × "&INDEX(Processos!$I$10:$I$509,MATCH((ROW()-9+($J$8-1)*50),Processos!$AJ$10:$AJ$509,0)))))>190,LEFT(IF((ROW()-9+($J$8-1)*50)>COUNTIFS(Processos!$X$10:$X$509,1,Processos!$Y$10:$Y$509,1),"",IF(INDEX(Processos!$H$10:$H$509,MATCH((ROW()-9+($J$8-1)*50),Processos!$AJ$10:$AJ$509,0))&" × "&INDEX(Processos!$I$10:$I$509,MATCH((ROW()-9+($J$8-1)*50),Processos!$AJ$10:$AJ$509,0))="","",INDEX(Processos!$H$10:$H$509,MATCH((ROW()-9+($J$8-1)*50),Processos!$AJ$10:$AJ$509,0))&" × "&INDEX(Processos!$I$10:$I$509,MATCH((ROW()-9+($J$8-1)*50),Processos!$AJ$10:$AJ$509,0)))),190)&" [...]",IF((ROW()-9+($J$8-1)*50)>COUNTIFS(Processos!$X$10:$X$509,1,Processos!$Y$10:$Y$509,1),"",IF(INDEX(Processos!$H$10:$H$509,MATCH((ROW()-9+($J$8-1)*50),Processos!$AJ$10:$AJ$509,0))&" × "&INDEX(Processos!$I$10:$I$509,MATCH((ROW()-9+($J$8-1)*50),Processos!$AJ$10:$AJ$509,0))="","",INDEX(Processos!$H$10:$H$509,MATCH((ROW()-9+($J$8-1)*50),Processos!$AJ$10:$AJ$509,0))&" × "&INDEX(Processos!$I$10:$I$509,MATCH((ROW()-9+($J$8-1)*50),Processos!$AJ$10:$AJ$509,0))))),CHAR(10)," "),CHAR(13)," "))>150,LEFT(SUBSTITUTE(SUBSTITUTE(IF(LEN(IF((ROW()-9+($J$8-1)*50)>COUNTIFS(Processos!$X$10:$X$509,1,Processos!$Y$10:$Y$509,1),"",IF(INDEX(Processos!$H$10:$H$509,MATCH((ROW()-9+($J$8-1)*50),Processos!$AJ$10:$AJ$509,0))&" × "&INDEX(Processos!$I$10:$I$509,MATCH((ROW()-9+($J$8-1)*50),Processos!$AJ$10:$AJ$509,0))="","",INDEX(Processos!$H$10:$H$509,MATCH((ROW()-9+($J$8-1)*50),Processos!$AJ$10:$AJ$509,0))&" × "&INDEX(Processos!$I$10:$I$509,MATCH((ROW()-9+($J$8-1)*50),Processos!$AJ$10:$AJ$509,0)))))>190,LEFT(IF((ROW()-9+($J$8-1)*50)>COUNTIFS(Processos!$X$10:$X$509,1,Processos!$Y$10:$Y$509,1),"",IF(INDEX(Processos!$H$10:$H$509,MATCH((ROW()-9+($J$8-1)*50),Processos!$AJ$10:$AJ$509,0))&" × "&INDEX(Processos!$I$10:$I$509,MATCH((ROW()-9+($J$8-1)*50),Processos!$AJ$10:$AJ$509,0))="","",INDEX(Processos!$H$10:$H$509,MATCH((ROW()-9+($J$8-1)*50),Processos!$AJ$10:$AJ$509,0))&" × "&INDEX(Processos!$I$10:$I$509,MATCH((ROW()-9+($J$8-1)*50),Processos!$AJ$10:$AJ$509,0)))),190)&" [...]",IF((ROW()-9+($J$8-1)*50)>COUNTIFS(Processos!$X$10:$X$509,1,Processos!$Y$10:$Y$509,1),"",IF(INDEX(Processos!$H$10:$H$509,MATCH((ROW()-9+($J$8-1)*50),Processos!$AJ$10:$AJ$509,0))&" × "&INDEX(Processos!$I$10:$I$509,MATCH((ROW()-9+($J$8-1)*50),Processos!$AJ$10:$AJ$509,0))="","",INDEX(Processos!$H$10:$H$509,MATCH((ROW()-9+($J$8-1)*50),Processos!$AJ$10:$AJ$509,0))&" × "&INDEX(Processos!$I$10:$I$509,MATCH((ROW()-9+($J$8-1)*50),Processos!$AJ$10:$AJ$509,0))))),CHAR(10)," "),CHAR(13)," "),150)&" [...]",SUBSTITUTE(SUBSTITUTE(IF(LEN(IF((ROW()-9+($J$8-1)*50)>COUNTIFS(Processos!$X$10:$X$509,1,Processos!$Y$10:$Y$509,1),"",IF(INDEX(Processos!$H$10:$H$509,MATCH((ROW()-9+($J$8-1)*50),Processos!$AJ$10:$AJ$509,0))&" × "&INDEX(Processos!$I$10:$I$509,MATCH((ROW()-9+($J$8-1)*50),Processos!$AJ$10:$AJ$509,0))="","",INDEX(Processos!$H$10:$H$509,MATCH((ROW()-9+($J$8-1)*50),Processos!$AJ$10:$AJ$509,0))&" × "&INDEX(Processos!$I$10:$I$509,MATCH((ROW()-9+($J$8-1)*50),Processos!$AJ$10:$AJ$509,0)))))>190,LEFT(IF((ROW()-9+($J$8-1)*50)>COUNTIFS(Processos!$X$10:$X$509,1,Processos!$Y$10:$Y$509,1),"",IF(INDEX(Processos!$H$10:$H$509,MATCH((ROW()-9+($J$8-1)*50),Processos!$AJ$10:$AJ$509,0))&" × "&INDEX(Processos!$I$10:$I$509,MATCH((ROW()-9+($J$8-1)*50),Processos!$AJ$10:$AJ$509,0))="","",INDEX(Processos!$H$10:$H$509,MATCH((ROW()-9+($J$8-1)*50),Processos!$AJ$10:$AJ$509,0))&" × "&INDEX(Processos!$I$10:$I$509,MATCH((ROW()-9+($J$8-1)*50),Processos!$AJ$10:$AJ$509,0)))),190)&" [...]",IF((ROW()-9+($J$8-1)*50)>COUNTIFS(Processos!$X$10:$X$509,1,Processos!$Y$10:$Y$509,1),"",IF(INDEX(Processos!$H$10:$H$509,MATCH((ROW()-9+($J$8-1)*50),Processos!$AJ$10:$AJ$509,0))&" × "&INDEX(Processos!$I$10:$I$509,MATCH((ROW()-9+($J$8-1)*50),Processos!$AJ$10:$AJ$509,0))="","",INDEX(Processos!$H$10:$H$509,MATCH((ROW()-9+($J$8-1)*50),Processos!$AJ$10:$AJ$509,0))&" × "&INDEX(Processos!$I$10:$I$509,MATCH((ROW()-9+($J$8-1)*50),Processos!$AJ$10:$AJ$509,0))))),CHAR(10)," "),CHAR(13)," ")) -> GUILHERME SANTOS MOREIRA × 1 - Consórcio Spavias - Alta 2 - Spavias Engenharia LTDA 3 - Alta Engenharia 4 - Cava Engenharia | D11: =SUBSTITUTE(SUBSTITUTE(IF(LEN(IF((ROW()-9+($J$8-1)*50)>COUNTIFS(Processos!$X$10:$X$509,1,Processos!$Y$10:$Y$509,1),"",IF(INDEX(Processos!$M$10:$M$509,MATCH((ROW()-9+($J$8-1)*50),Processos!$AJ$10:$AJ$509,0))="","",INDEX(Processos!$M$10:$M$509,MATCH((ROW()-9+($J$8-1)*50),Processos!$AJ$10:$AJ$509,0)))))>190,LEFT(IF((ROW()-9+($J$8-1)*50)>COUNTIFS(Processos!$X$10:$X$509,1,Processos!$Y$10:$Y$509,1),"",IF(INDEX(Processos!$M$10:$M$509,MATCH((ROW()-9+($J$8-1)*50),Processos!$AJ$10:$AJ$509,0))="","",INDEX(Processos!$M$10:$M$509,MATCH((ROW()-9+($J$8-1)*50),Processos!$AJ$10:$AJ$509,0)))),190)&" [...]",IF((ROW()-9+($J$8-1)*50)>COUNTIFS(Processos!$X$10:$X$509,1,Processos!$Y$10:$Y$509,1),"",IF(INDEX(Processos!$M$10:$M$509,MATCH((ROW()-9+($J$8-1)*50),Processos!$AJ$10:$AJ$509,0))="","",INDEX(Processos!$M$10:$M$509,MATCH((ROW()-9+($J$8-1)*50),Processos!$AJ$10:$AJ$509,0))))),CHAR(10)," "),CHAR(13)," ") -> O trabalhador ajuizou ação contra o Consórcio Spavias Cava alegando que trabalhou de 2015 a 2019 como encarregado de departamento pessoal, com salário de R$ 4.076,43. Afirma que não recebeu [...] | E11: =IF($A11="","",IFERROR(INDEX(Processos!$AR$10:$AR$509,MATCH($A11,Processos!$A$10:$A$509,0)),"")&CHAR(10)&IFERROR(IF(OR(INDEX(Origem!$AB$10:$AB$509,MATCH($A11,Origem!$A$10:$A$509,0))="",INDEX(Origem!$AB$10:$AB$509,MATCH($A11,Origem!$A$10:$A$509,0))="—"),"Origem: sem classificação","Origem: "&INDEX(Origem!$AB$10:$AB$509,MATCH($A11,Origem!$A$10:$A$509,0))&IF(INDEX(Origem!$AC$10:$AC$509,MATCH($A11,Origem!$A$10:$A$509,0))=""," (sem pontuação)"," • "&INDEX(Origem!$AC$10:$AC$509,MATCH($A11,Origem!$A$10:$A$509,0))&" pontos")),"Origem: sem classificação")) -> Prioridade crítica. Criticidade herdada da planilha de origem; validar. Não confirma bloqueio/penhora vigente. Origem: 🔴 CRÍTICO • 70 pontos | F11: =IF((ROW()-9+($J$8-1)*50)>COUNTIFS(Processos!$X$10:$X$509,1,Processos!$Y$10:$Y$509,1),"",IF(INDEX(Processos!$AQ$10:$AQ$509,MATCH((ROW()-9+($J$8-1)*50),Processos!$AJ$10:$AJ$509,0))="","",INDEX(Processos!$AQ$10:$AQ$509,MATCH((ROW()-9+($J$8-1)*50),Processos!$AJ$10:$AJ$509,0)))) -> 80298.47 | G11: =IF((ROW()-9+($J$8-1)*50)>COUNTIFS(Processos!$X$10:$X$509,1,Processos!$Y$10:$Y$509,1),"",IFERROR(HYPERLINK("#'Ficha'!C6","Selecionar na Ficha"),"Selecionar na Ficha")) -> Selecionar na Ficha
A12: =IF((ROW()-9+($J$8-1)*50)>COUNTIFS(Processos!$X$10:$X$509,1,Processos!$Y$10:$Y$509,1),"",IF(INDEX(Processos!$A$10:$A$509,MATCH((ROW()-9+($J$8-1)*50),Processos!$AJ$10:$AJ$509,0))="","",INDEX(Processos!$A$10:$A$509,MATCH((ROW()-9+($J$8-1)*50),Processos!$AJ$10:$AJ$509,0)))) -> 0010471-11.2021.5.03.0138 | B12: =IF((ROW()-9+($J$8-1)*50)>COUNTIFS(Processos!$X$10:$X$509,1,Processos!$Y$10:$Y$509,1),"",IF(INDEX(Processos!$D$10:$D$509,MATCH((ROW()-9+($J$8-1)*50),Processos!$AJ$10:$AJ$509,0))="","",INDEX(Processos!$D$10:$D$509,MATCH((ROW()-9+($J$8-1)*50),Processos!$AJ$10:$AJ$509,0)))) -> BMM Advogados | C12: =IF(LEN(SUBSTITUTE(SUBSTITUTE(IF(LEN(IF((ROW()-9+($J$8-1)*50)>COUNTIFS(Processos!$X$10:$X$509,1,Processos!$Y$10:$Y$509,1),"",IF(INDEX(Processos!$H$10:$H$509,MATCH((ROW()-9+($J$8-1)*50),Processos!$AJ$10:$AJ$509,0))&" × "&INDEX(Processos!$I$10:$I$509,MATCH((ROW()-9+($J$8-1)*50),Processos!$AJ$10:$AJ$509,0))="","",INDEX(Processos!$H$10:$H$509,MATCH((ROW()-9+($J$8-1)*50),Processos!$AJ$10:$AJ$509,0))&" × "&INDEX(Processos!$I$10:$I$509,MATCH((ROW()-9+($J$8-1)*50),Processos!$AJ$10:$AJ$509,0)))))>190,LEFT(IF((ROW()-9+($J$8-1)*50)>COUNTIFS(Processos!$X$10:$X$509,1,Processos!$Y$10:$Y$509,1),"",IF(INDEX(Processos!$H$10:$H$509,MATCH((ROW()-9+($J$8-1)*50),Processos!$AJ$10:$AJ$509,0))&" × "&INDEX(Processos!$I$10:$I$509,MATCH((ROW()-9+($J$8-1)*50),Processos!$AJ$10:$AJ$509,0))="","",INDEX(Processos!$H$10:$H$509,MATCH((ROW()-9+($J$8-1)*50),Processos!$AJ$10:$AJ$509,0))&" × "&INDEX(Processos!$I$10:$I$509,MATCH((ROW()-9+($J$8-1)*50),Processos!$AJ$10:$AJ$509,0)))),190)&" [...]",IF((ROW()-9+($J$8-1)*50)>COUNTIFS(Processos!$X$10:$X$509,1,Processos!$Y$10:$Y$509,1),"",IF(INDEX(Processos!$H$10:$H$509,MATCH((ROW()-9+($J$8-1)*50),Processos!$AJ$10:$AJ$509,0))&" × "&INDEX(Processos!$I$10:$I$509,MATCH((ROW()-9+($J$8-1)*50),Processos!$AJ$10:$AJ$509,0))="","",INDEX(Processos!$H$10:$H$509,MATCH((ROW()-9+($J$8-1)*50),Processos!$AJ$10:$AJ$509,0))&" × "&INDEX(Processos!$I$10:$I$509,MATCH((ROW()-9+($J$8-1)*50),Processos!$AJ$10:$AJ$509,0))))),CHAR(10)," "),CHAR(13)," "))>150,LEFT(SUBSTITUTE(SUBSTITUTE(IF(LEN(IF((ROW()-9+($J$8-1)*50)>COUNTIFS(Processos!$X$10:$X$509,1,Processos!$Y$10:$Y$509,1),"",IF(INDEX(Processos!$H$10:$H$509,MATCH((ROW()-9+($J$8-1)*50),Processos!$AJ$10:$AJ$509,0))&" × "&INDEX(Processos!$I$10:$I$509,MATCH((ROW()-9+($J$8-1)*50),Processos!$AJ$10:$AJ$509,0))="","",INDEX(Processos!$H$10:$H$509,MATCH((ROW()-9+($J$8-1)*50),Processos!$AJ$10:$AJ$509,0))&" × "&INDEX(Processos!$I$10:$I$509,MATCH((ROW()-9+($J$8-1)*50),Processos!$AJ$10:$AJ$509,0)))))>190,LEFT(IF((ROW()-9+($J$8-1)*50)>COUNTIFS(Processos!$X$10:$X$509,1,Processos!$Y$10:$Y$509,1),"",IF(INDEX(Processos!$H$10:$H$509,MATCH((ROW()-9+($J$8-1)*50),Processos!$AJ$10:$AJ$509,0))&" × "&INDEX(Processos!$I$10:$I$509,MATCH((ROW()-9+($J$8-1)*50),Processos!$AJ$10:$AJ$509,0))="","",INDEX(Processos!$H$10:$H$509,MATCH((ROW()-9+($J$8-1)*50),Processos!$AJ$10:$AJ$509,0))&" × "&INDEX(Processos!$I$10:$I$509,MATCH((ROW()-9+($J$8-1)*50),Processos!$AJ$10:$AJ$509,0)))),190)&" [...]",IF((ROW()-9+($J$8-1)*50)>COUNTIFS(Processos!$X$10:$X$509,1,Processos!$Y$10:$Y$509,1),"",IF(INDEX(Processos!$H$10:$H$509,MATCH((ROW()-9+($J$8-1)*50),Processos!$AJ$10:$AJ$509,0))&" × "&INDEX(Processos!$I$10:$I$509,MATCH((ROW()-9+($J$8-1)*50),Processos!$AJ$10:$AJ$509,0))="","",INDEX(Processos!$H$10:$H$509,MATCH((ROW()-9+($J$8-1)*50),Processos!$AJ$10:$AJ$509,0))&" × "&INDEX(Processos!$I$10:$I$509,MATCH((ROW()-9+($J$8-1)*50),Processos!$AJ$10:$AJ$509,0))))),CHAR(10)," "),CHAR(13)," "),150)&" [...]",SUBSTITUTE(SUBSTITUTE(IF(LEN(IF((ROW()-9+($J$8-1)*50)>COUNTIFS(Processos!$X$10:$X$509,1,Processos!$Y$10:$Y$509,1),"",IF(INDEX(Processos!$H$10:$H$509,MATCH((ROW()-9+($J$8-1)*50),Processos!$AJ$10:$AJ$509,0))&" × "&INDEX(Processos!$I$10:$I$509,MATCH((ROW()-9+($J$8-1)*50),Processos!$AJ$10:$AJ$509,0))="","",INDEX(Processos!$H$10:$H$509,MATCH((ROW()-9+($J$8-1)*50),Processos!$AJ$10:$AJ$509,0))&" × "&INDEX(Processos!$I$10:$I$509,MATCH((ROW()-9+($J$8-1)*50),Processos!$AJ$10:$AJ$509,0)))))>190,LEFT(IF((ROW()-9+($J$8-1)*50)>COUNTIFS(Processos!$X$10:$X$509,1,Processos!$Y$10:$Y$509,1),"",IF(INDEX(Processos!$H$10:$H$509,MATCH((ROW()-9+($J$8-1)*50),Processos!$AJ$10:$AJ$509,0))&" × "&INDEX(Processos!$I$10:$I$509,MATCH((ROW()-9+($J$8-1)*50),Processos!$AJ$10:$AJ$509,0))="","",INDEX(Processos!$H$10:$H$509,MATCH((ROW()-9+($J$8-1)*50),Processos!$AJ$10:$AJ$509,0))&" × "&INDEX(Processos!$I$10:$I$509,MATCH((ROW()-9+($J$8-1)*50),Processos!$AJ$10:$AJ$509,0)))),190)&" [...]",IF((ROW()-9+($J$8-1)*50)>COUNTIFS(Processos!$X$10:$X$509,1,Processos!$Y$10:$Y$509,1),"",IF(INDEX(Processos!$H$10:$H$509,MATCH((ROW()-9+($J$8-1)*50),Processos!$AJ$10:$AJ$509,0))&" × "&INDEX(Processos!$I$10:$I$509,MATCH((ROW()-9+($J$8-1)*50),Processos!$AJ$10:$AJ$509,0))="","",INDEX(Processos!$H$10:$H$509,MATCH((ROW()-9+($J$8-1)*50),Processos!$AJ$10:$AJ$509,0))&" × "&INDEX(Processos!$I$10:$I$509,MATCH((ROW()-9+($J$8-1)*50),Processos!$AJ$10:$AJ$509,0))))),CHAR(10)," "),CHAR(13)," ")) -> GUILHERME SANTOS MOREIRA × 1 - Consórcio Spavias - Alta Spavias Engenharia LTDA 2 - Alta Engenharia 3 - Cava Engenharia | D12: =SUBSTITUTE(SUBSTITUTE(IF(LEN(IF((ROW()-9+($J$8-1)*50)>COUNTIFS(Processos!$X$10:$X$509,1,Processos!$Y$10:$Y$509,1),"",IF(INDEX(Processos!$M$10:$M$509,MATCH((ROW()-9+($J$8-1)*50),Processos!$AJ$10:$AJ$509,0))="","",INDEX(Processos!$M$10:$M$509,MATCH((ROW()-9+($J$8-1)*50),Processos!$AJ$10:$AJ$509,0)))))>190,LEFT(IF((ROW()-9+($J$8-1)*50)>COUNTIFS(Processos!$X$10:$X$509,1,Processos!$Y$10:$Y$509,1),"",IF(INDEX(Processos!$M$10:$M$509,MATCH((ROW()-9+($J$8-1)*50),Processos!$AJ$10:$AJ$509,0))="","",INDEX(Processos!$M$10:$M$509,MATCH((ROW()-9+($J$8-1)*50),Processos!$AJ$10:$AJ$509,0)))),190)&" [...]",IF((ROW()-9+($J$8-1)*50)>COUNTIFS(Processos!$X$10:$X$509,1,Processos!$Y$10:$Y$509,1),"",IF(INDEX(Processos!$M$10:$M$509,MATCH((ROW()-9+($J$8-1)*50),Processos!$AJ$10:$AJ$509,0))="","",INDEX(Processos!$M$10:$M$509,MATCH((ROW()-9+($J$8-1)*50),Processos!$AJ$10:$AJ$509,0))))),CHAR(10)," "),CHAR(13)," ") -> O trabalhador pede execução provisória da sentença porque a empresa não cumpriu acordo trabalhista de R$ 50.000. Após decisões favoráveis na Justiça e vários recursos das empresas, ele reque [...] | E12: =IF($A12="","",IFERROR(INDEX(Processos!$AR$10:$AR$509,MATCH($A12,Processos!$A$10:$A$509,0)),"")&CHAR(10)&IFERROR(IF(OR(INDEX(Origem!$AB$10:$AB$509,MATCH($A12,Origem!$A$10:$A$509,0))="",INDEX(Origem!$AB$10:$AB$509,MATCH($A12,Origem!$A$10:$A$509,0))="—"),"Origem: sem classificação","Origem: "&INDEX(Origem!$AB$10:$AB$509,MATCH($A12,Origem!$A$10:$A$509,0))&IF(INDEX(Origem!$AC$10:$AC$509,MATCH($A12,Origem!$A$10:$A$509,0))=""," (sem pontuação)"," • "&INDEX(Origem!$AC$10:$AC$509,MATCH($A12,Origem!$A$10:$A$509,0))&" pontos")),"Origem: sem classificação")) -> Prioridade crítica. Criticidade herdada da planilha de origem; validar. Não confirma bloqueio/penhora vigente. Origem: 🔴 CRÍTICO • 70 pontos | F12: =IF((ROW()-9+($J$8-1)*50)>COUNTIFS(Processos!$X$10:$X$509,1,Processos!$Y$10:$Y$509,1),"",IF(INDEX(Processos!$AQ$10:$AQ$509,MATCH((ROW()-9+($J$8-1)*50),Processos!$AJ$10:$AJ$509,0))="","",INDEX(Processos!$AQ$10:$AQ$509,MATCH((ROW()-9+($J$8-1)*50),Processos!$AJ$10:$AJ$509,0)))) -> 58038.42 | G12: =IF((ROW()-9+($J$8-1)*50)>COUNTIFS(Processos!$X$10:$X$509,1,Processos!$Y$10:$Y$509,1),"",IFERROR(HYPERLINK("#'Ficha'!C6","Selecionar na Ficha"),"Selecionar na Ficha")) -> Selecionar na Ficha
A13: =IF((ROW()-9+($J$8-1)*50)>COUNTIFS(Processos!$X$10:$X$509,1,Processos!$Y$10:$Y$509,1),"",IF(INDEX(Processos!$A$10:$A$509,MATCH((ROW()-9+($J$8-1)*50),Processos!$AJ$10:$AJ$509,0))="","",INDEX(Processos!$A$10:$A$509,MATCH((ROW()-9+($J$8-1)*50),Processos!$AJ$10:$AJ$509,0)))) -> 0001532-68.2015.5.10.0005 | B13: =IF((ROW()-9+($J$8-1)*50)>COUNTIFS(Processos!$X$10:$X$509,1,Processos!$Y$10:$Y$509,1),"",IF(INDEX(Processos!$D$10:$D$509,MATCH((ROW()-9+($J$8-1)*50),Processos!$AJ$10:$AJ$509,0))="","",INDEX(Processos!$D$10:$D$509,MATCH((ROW()-9+($J$8-1)*50),Processos!$AJ$10:$AJ$509,0)))) -> BMM Advogados | C13: =IF(LEN(SUBSTITUTE(SUBSTITUTE(IF(LEN(IF((ROW()-9+($J$8-1)*50)>COUNTIFS(Processos!$X$10:$X$509,1,Processos!$Y$10:$Y$509,1),"",IF(INDEX(Processos!$H$10:$H$509,MATCH((ROW()-9+($J$8-1)*50),Processos!$AJ$10:$AJ$509,0))&" × "&INDEX(Processos!$I$10:$I$509,MATCH((ROW()-9+($J$8-1)*50),Processos!$AJ$10:$AJ$509,0))="","",INDEX(Processos!$H$10:$H$509,MATCH((ROW()-9+($J$8-1)*50),Processos!$AJ$10:$AJ$509,0))&" × "&INDEX(Processos!$I$10:$I$509,MATCH((ROW()-9+($J$8-1)*50),Processos!$AJ$10:$AJ$509,0)))))>190,LEFT(IF((ROW()-9+($J$8-1)*50)>COUNTIFS(Processos!$X$10:$X$509,1,Processos!$Y$10:$Y$509,1),"",IF(INDEX(Processos!$H$10:$H$509,MATCH((ROW()-9+($J$8-1)*50),Processos!$AJ$10:$AJ$509,0))&" × "&INDEX(Processos!$I$10:$I$509,MATCH((ROW()-9+($J$8-1)*50),Processos!$AJ$10:$AJ$509,0))="","",INDEX(Processos!$H$10:$H$509,MATCH((ROW()-9+($J$8-1)*50),Processos!$AJ$10:$AJ$509,0))&" × "&INDEX(Processos!$I$10:$I$509,MATCH((ROW()-9+($J$8-1)*50),Processos!$AJ$10:$AJ$509,0)))),190)&" [...]",IF((ROW()-9+($J$8-1)*50)>COUNTIFS(Processos!$X$10:$X$509,1,Processos!$Y$10:$Y$509,1),"",IF(INDEX(Processos!$H$10:$H$509,MATCH((ROW()-9+($J$8-1)*50),Processos!$AJ$10:$AJ$509,0))&" × "&INDEX(Processos!$I$10:$I$509,MATCH((ROW()-9+($J$8-1)*50),Processos!$AJ$10:$AJ$509,0))="","",INDEX(Processos!$H$10:$H$509,MATCH((ROW()-9+($J$8-1)*50),Processos!$AJ$10:$AJ$509,0))&" × "&INDEX(Processos!$I$10:$I$509,MATCH((ROW()-9+($J$8-1)*50),Processos!$AJ$10:$AJ$509,0))))),CHAR(10)," "),CHAR(13)," "))>150,LEFT(SUBSTITUTE(SUBSTITUTE(IF(LEN(IF((ROW()-9+($J$8-1)*50)>COUNTIFS(Processos!$X$10:$X$509,1,Processos!$Y$10:$Y$509,1),"",IF(INDEX(Processos!$H$10:$H$509,MATCH((ROW()-9+($J$8-1)*50),Processos!$AJ$10:$AJ$509,0))&" × "&INDEX(Processos!$I$10:$I$509,MATCH((ROW()-9+($J$8-1)*50),Processos!$AJ$10:$AJ$509,0))="","",INDEX(Processos!$H$10:$H$509,MATCH((ROW()-9+($J$8-1)*50),Processos!$AJ$10:$AJ$509,0))&" × "&INDEX(Processos!$I$10:$I$509,MATCH((ROW()-9+($J$8-1)*50),Processos!$AJ$10:$AJ$509,0)))))>190,LEFT(IF((ROW()-9+($J$8-1)*50)>COUNTIFS(Processos!$X$10:$X$509,1,Processos!$Y$10:$Y$509,1),"",IF(INDEX(Processos!$H$10:$H$509,MATCH((ROW()-9+($J$8-1)*50),Processos!$AJ$10:$AJ$509,0))&" × "&INDEX(Processos!$I$10:$I$509,MATCH((ROW()-9+($J$8-1)*50),Processos!$AJ$10:$AJ$509,0))="","",INDEX(Processos!$H$10:$H$509,MATCH((ROW()-9+($J$8-1)*50),Processos!$AJ$10:$AJ$509,0))&" × "&INDEX(Processos!$I$10:$I$509,MATCH((ROW()-9+($J$8-1)*50),Processos!$AJ$10:$AJ$509,0)))),190)&" [...]",IF((ROW()-9+($J$8-1)*50)>COUNTIFS(Processos!$X$10:$X$509,1,Processos!$Y$10:$Y$509,1),"",IF(INDEX(Processos!$H$10:$H$509,MATCH((ROW()-9+($J$8-1)*50),Processos!$AJ$10:$AJ$509,0))&" × "&INDEX(Processos!$I$10:$I$509,MATCH((ROW()-9+($J$8-1)*50),Processos!$AJ$10:$AJ$509,0))="","",INDEX(Processos!$H$10:$H$509,MATCH((ROW()-9+($J$8-1)*50),Processos!$AJ$10:$AJ$509,0))&" × "&INDEX(Processos!$I$10:$I$509,MATCH((ROW()-9+($J$8-1)*50),Processos!$AJ$10:$AJ$509,0))))),CHAR(10)," "),CHAR(13)," "),150)&" [...]",SUBSTITUTE(SUBSTITUTE(IF(LEN(IF((ROW()-9+($J$8-1)*50)>COUNTIFS(Processos!$X$10:$X$509,1,Processos!$Y$10:$Y$509,1),"",IF(INDEX(Processos!$H$10:$H$509,MATCH((ROW()-9+($J$8-1)*50),Processos!$AJ$10:$AJ$509,0))&" × "&INDEX(Processos!$I$10:$I$509,MATCH((ROW()-9+($J$8-1)*50),Processos!$AJ$10:$AJ$509,0))="","",INDEX(Processos!$H$10:$H$509,MATCH((ROW()-9+($J$8-1)*50),Processos!$AJ$10:$AJ$509,0))&" × "&INDEX(Processos!$I$10:$I$509,MATCH((ROW()-9+($J$8-1)*50),Processos!$AJ$10:$AJ$509,0)))))>190,LEFT(IF((ROW()-9+($J$8-1)*50)>COUNTIFS(Processos!$X$10:$X$509,1,Processos!$Y$10:$Y$509,1),"",IF(INDEX(Processos!$H$10:$H$509,MATCH((ROW()-9+($J$8-1)*50),Processos!$AJ$10:$AJ$509,0))&" × "&INDEX(Processos!$I$10:$I$509,MATCH((ROW()-9+($J$8-1)*50),Processos!$AJ$10:$AJ$509,0))="","",INDEX(Processos!$H$10:$H$509,MATCH((ROW()-9+($J$8-1)*50),Processos!$AJ$10:$AJ$509,0))&" × "&INDEX(Processos!$I$10:$I$509,MATCH((ROW()-9+($J$8-1)*50),Processos!$AJ$10:$AJ$509,0)))),190)&" [...]",IF((ROW()-9+($J$8-1)*50)>COUNTIFS(Processos!$X$10:$X$509,1,Processos!$Y$10:$Y$509,1),"",IF(INDEX(Processos!$H$10:$H$509,MATCH((ROW()-9+($J$8-1)*50),Processos!$AJ$10:$AJ$509,0))&" × "&INDEX(Processos!$I$10:$I$509,MATCH((ROW()-9+($J$8-1)*50),Processos!$AJ$10:$AJ$509,0))="","",INDEX(Processos!$H$10:$H$509,MATCH((ROW()-9+($J$8-1)*50),Processos!$AJ$10:$AJ$509,0))&" × "&INDEX(Processos!$I$10:$I$509,MATCH((ROW()-9+($J$8-1)*50),Processos!$AJ$10:$AJ$509,0))))),CHAR(10)," "),CHAR(13)," ")) -> 1 - MARIA TERESA SOARES MOREIRA 2 - JOSÉ FONSECA FILHO × 1 - Cesar Transportes, Guindastes e Equipamentos LTDA 2 - União - Ministérios dos Transportes [...] | D13: =SUBSTITUTE(SUBSTITUTE(IF(LEN(IF((ROW()-9+($J$8-1)*50)>COUNTIFS(Processos!$X$10:$X$509,1,Processos!$Y$10:$Y$509,1),"",IF(INDEX(Processos!$M$10:$M$509,MATCH((ROW()-9+($J$8-1)*50),Processos!$AJ$10:$AJ$509,0))="","",INDEX(Processos!$M$10:$M$509,MATCH((ROW()-9+($J$8-1)*50),Processos!$AJ$10:$AJ$509,0)))))>190,LEFT(IF((ROW()-9+($J$8-1)*50)>COUNTIFS(Processos!$X$10:$X$509,1,Processos!$Y$10:$Y$509,1),"",IF(INDEX(Processos!$M$10:$M$509,MATCH((ROW()-9+($J$8-1)*50),Processos!$AJ$10:$AJ$509,0))="","",INDEX(Processos!$M$10:$M$509,MATCH((ROW()-9+($J$8-1)*50),Processos!$AJ$10:$AJ$509,0)))),190)&" [...]",IF((ROW()-9+($J$8-1)*50)>COUNTIFS(Processos!$X$10:$X$509,1,Processos!$Y$10:$Y$509,1),"",IF(INDEX(Processos!$M$10:$M$509,MATCH((ROW()-9+($J$8-1)*50),Processos!$AJ$10:$AJ$509,0))="","",INDEX(Processos!$M$10:$M$509,MATCH((ROW()-9+($J$8-1)*50),Processos!$AJ$10:$AJ$509,0))))),CHAR(10)," "),CHAR(13)," ") -> Ação trabalhista de indenização proposta pelos pais de um trabalhador falecido (Juscelino Soares Fonseca) após acidente de trabalho em obra ferroviária. Eles alegam que o empregado morreu ao [...] | E13: =IF($A13="","",IFERROR(INDEX(Processos!$AR$10:$AR$509,MATCH($A13,Processos!$A$10:$A$509,0)),"")&CHAR(10)&IFERROR(IF(OR(INDEX(Origem!$AB$10:$AB$509,MATCH($A13,Origem!$A$10:$A$509,0))="",INDEX(Origem!$AB$10:$AB$509,MATCH($A13,Origem!$A$10:$A$509,0))="—"),"Origem: sem classificação","Origem: "&INDEX(Origem!$AB$10:$AB$509,MATCH($A13,Origem!$A$10:$A$509,0))&IF(INDEX(Origem!$AC$10:$AC$509,MATCH($A13,Origem!$A$10:$A$509,0))=""," (sem pontuação)"," • "&INDEX(Origem!$AC$10:$AC$509,MATCH($A13,Origem!$A$10:$A$509,0))&" pontos")),"Origem: sem classificação")) -> Prioridade crítica. Criticidade herdada da planilha de origem; validar. Não confirma bloqueio/penhora vigente. Origem: 🔴 CRÍTICO • 70 pontos | F13: =IF((ROW()-9+($J$8-1)*50)>COUNTIFS(Processos!$X$10:$X$509,1,Processos!$Y$10:$Y$509,1),"",IF(INDEX(Processos!$AQ$10:$AQ$509,MATCH((ROW()-9+($J$8-1)*50),Processos!$AJ$10:$AJ$509,0))="","",INDEX(Processos!$AQ$10:$AQ$509,MATCH((ROW()-9+($J$8-1)*50),Processos!$AJ$10:$AJ$509,0)))) -> 3000000 | G13: =IF((ROW()-9+($J$8-1)*50)>COUNTIFS(Processos!$X$10:$X$509,1,Processos!$Y$10:$Y$509,1),"",IFERROR(HYPERLINK("#'Ficha'!C6","Selecionar na Ficha"),"Selecionar na Ficha")) -> Selecionar na Ficha
A14: =IF((ROW()-9+($J$8-1)*50)>COUNTIFS(Processos!$X$10:$X$509,1,Processos!$Y$10:$Y$509,1),"",IF(INDEX(Processos!$A$10:$A$509,MATCH((ROW()-9+($J$8-1)*50),Processos!$AJ$10:$AJ$509,0))="","",INDEX(Processos!$A$10:$A$509,MATCH((ROW()-9+($J$8-1)*50),Processos!$AJ$10:$AJ$509,0)))) -> 0010993-94.2019.5.18.0104 | B14: =IF((ROW()-9+($J$8-1)*50)>COUNTIFS(Processos!$X$10:$X$509,1,Processos!$Y$10:$Y$509,1),"",IF(INDEX(Processos!$D$10:$D$509,MATCH((ROW()-9+($J$8-1)*50),Processos!$AJ$10:$AJ$509,0))="","",INDEX(Processos!$D$10:$D$509,MATCH((ROW()-9+($J$8-1)*50),Processos!$AJ$10:$AJ$509,0)))) -> BMM Advogados | C14: =IF(LEN(SUBSTITUTE(SUBSTITUTE(IF(LEN(IF((ROW()-9+($J$8-1)*50)>COUNTIFS(Processos!$X$10:$X$509,1,Processos!$Y$10:$Y$509,1),"",IF(INDEX(Processos!$H$10:$H$509,MATCH((ROW()-9+($J$8-1)*50),Processos!$AJ$10:$AJ$509,0))&" × "&INDEX(Processos!$I$10:$I$509,MATCH((ROW()-9+($J$8-1)*50),Processos!$AJ$10:$AJ$509,0))="","",INDEX(Processos!$H$10:$H$509,MATCH((ROW()-9+($J$8-1)*50),Processos!$AJ$10:$AJ$509,0))&" × "&INDEX(Processos!$I$10:$I$509,MATCH((ROW()-9+($J$8-1)*50),Processos!$AJ$10:$AJ$509,0)))))>190,LEFT(IF((ROW()-9+($J$8-1)*50)>COUNTIFS(Processos!$X$10:$X$509,1,Processos!$Y$10:$Y$509,1),"",IF(INDEX(Processos!$H$10:$H$509,MATCH((ROW()-9+($J$8-1)*50),Processos!$AJ$10:$AJ$509,0))&" × "&INDEX(Processos!$I$10:$I$509,MATCH((ROW()-9+($J$8-1)*50),Processos!$AJ$10:$AJ$509,0))="","",INDEX(Processos!$H$10:$H$509,MATCH((ROW()-9+($J$8-1)*50),Processos!$AJ$10:$AJ$509,0))&" × "&INDEX(Processos!$I$10:$I$509,MATCH((ROW()-9+($J$8-1)*50),Processos!$AJ$10:$AJ$509,0)))),190)&" [...]",IF((ROW()-9+($J$8-1)*50)>COUNTIFS(Processos!$X$10:$X$509,1,Processos!$Y$10:$Y$509,1),"",IF(INDEX(Processos!$H$10:$H$509,MATCH((ROW()-9+($J$8-1)*50),Processos!$AJ$10:$AJ$509,0))&" × "&INDEX(Processos!$I$10:$I$509,MATCH((ROW()-9+($J$8-1)*50),Processos!$AJ$10:$AJ$509,0))="","",INDEX(Processos!$H$10:$H$509,MATCH((ROW()-9+($J$8-1)*50),Processos!$AJ$10:$AJ$509,0))&" × "&INDEX(Processos!$I$10:$I$509,MATCH((ROW()-9+($J$8-1)*50),Processos!$AJ$10:$AJ$509,0))))),CHAR(10)," "),CHAR(13)," "))>150,LEFT(SUBSTITUTE(SUBSTITUTE(IF(LEN(IF((ROW()-9+($J$8-1)*50)>COUNTIFS(Processos!$X$10:$X$509,1,Processos!$Y$10:$Y$509,1),"",IF(INDEX(Processos!$H$10:$H$509,MATCH((ROW()-9+($J$8-1)*50),Processos!$AJ$10:$AJ$509,0))&" × "&INDEX(Processos!$I$10:$I$509,MATCH((ROW()-9+($J$8-1)*50),Processos!$AJ$10:$AJ$509,0))="","",INDEX(Processos!$H$10:$H$509,MATCH((ROW()-9+($J$8-1)*50),Processos!$AJ$10:$AJ$509,0))&" × "&INDEX(Processos!$I$10:$I$509,MATCH((ROW()-9+($J$8-1)*50),Processos!$AJ$10:$AJ$509,0)))))>190,LEFT(IF((ROW()-9+($J$8-1)*50)>COUNTIFS(Processos!$X$10:$X$509,1,Processos!$Y$10:$Y$509,1),"",IF(INDEX(Processos!$H$10:$H$509,MATCH((ROW()-9+($J$8-1)*50),Processos!$AJ$10:$AJ$509,0))&" × "&INDEX(Processos!$I$10:$I$509,MATCH((ROW()-9+($J$8-1)*50),Processos!$AJ$10:$AJ$509,0))="","",INDEX(Processos!$H$10:$H$509,MATCH((ROW()-9+($J$8-1)*50),Processos!$AJ$10:$AJ$509,0))&" × "&INDEX(Processos!$I$10:$I$509,MATCH((ROW()-9+($J$8-1)*50),Processos!$AJ$10:$AJ$509,0)))),190)&" [...]",IF((ROW()-9+($J$8-1)*50)>COUNTIFS(Processos!$X$10:$X$509,1,Processos!$Y$10:$Y$509,1),"",IF(INDEX(Processos!$H$10:$H$509,MATCH((ROW()-9+($J$8-1)*50),Processos!$AJ$10:$AJ$509,0))&" × "&INDEX(Processos!$I$10:$I$509,MATCH((ROW()-9+($J$8-1)*50),Processos!$AJ$10:$AJ$509,0))="","",INDEX(Processos!$H$10:$H$509,MATCH((ROW()-9+($J$8-1)*50),Processos!$AJ$10:$AJ$509,0))&" × "&INDEX(Processos!$I$10:$I$509,MATCH((ROW()-9+($J$8-1)*50),Processos!$AJ$10:$AJ$509,0))))),CHAR(10)," "),CHAR(13)," "),150)&" [...]",SUBSTITUTE(SUBSTITUTE(IF(LEN(IF((ROW()-9+($J$8-1)*50)>COUNTIFS(Processos!$X$10:$X$509,1,Processos!$Y$10:$Y$509,1),"",IF(INDEX(Processos!$H$10:$H$509,MATCH((ROW()-9+($J$8-1)*50),Processos!$AJ$10:$AJ$509,0))&" × "&INDEX(Processos!$I$10:$I$509,MATCH((ROW()-9+($J$8-1)*50),Processos!$AJ$10:$AJ$509,0))="","",INDEX(Processos!$H$10:$H$509,MATCH((ROW()-9+($J$8-1)*50),Processos!$AJ$10:$AJ$509,0))&" × "&INDEX(Processos!$I$10:$I$509,MATCH((ROW()-9+($J$8-1)*50),Processos!$AJ$10:$AJ$509,0)))))>190,LEFT(IF((ROW()-9+($J$8-1)*50)>COUNTIFS(Processos!$X$10:$X$509,1,Processos!$Y$10:$Y$509,1),"",IF(INDEX(Processos!$H$10:$H$509,MATCH((ROW()-9+($J$8-1)*50),Processos!$AJ$10:$AJ$509,0))&" × "&INDEX(Processos!$I$10:$I$509,MATCH((ROW()-9+($J$8-1)*50),Processos!$AJ$10:$AJ$509,0))="","",INDEX(Processos!$H$10:$H$509,MATCH((ROW()-9+($J$8-1)*50),Processos!$AJ$10:$AJ$509,0))&" × "&INDEX(Processos!$I$10:$I$509,MATCH((ROW()-9+($J$8-1)*50),Processos!$AJ$10:$AJ$509,0)))),190)&" [...]",IF((ROW()-9+($J$8-1)*50)>COUNTIFS(Processos!$X$10:$X$509,1,Processos!$Y$10:$Y$509,1),"",IF(INDEX(Processos!$H$10:$H$509,MATCH((ROW()-9+($J$8-1)*50),Processos!$AJ$10:$AJ$509,0))&" × "&INDEX(Processos!$I$10:$I$509,MATCH((ROW()-9+($J$8-1)*50),Processos!$AJ$10:$AJ$509,0))="","",INDEX(Processos!$H$10:$H$509,MATCH((ROW()-9+($J$8-1)*50),Processos!$AJ$10:$AJ$509,0))&" × "&INDEX(Processos!$I$10:$I$509,MATCH((ROW()-9+($J$8-1)*50),Processos!$AJ$10:$AJ$509,0))))),CHAR(10)," "),CHAR(13)," ")) -> Sindicato Dos Trabalhadores Nas Industrias Da Construcao × 1 - Consórcio Integral Spavias Trail Alta 2 - SPA Engenharia Indústria e Comércio LTDA 3 - [...] | D14: =SUBSTITUTE(SUBSTITUTE(IF(LEN(IF((ROW()-9+($J$8-1)*50)>COUNTIFS(Processos!$X$10:$X$509,1,Processos!$Y$10:$Y$509,1),"",IF(INDEX(Processos!$M$10:$M$509,MATCH((ROW()-9+($J$8-1)*50),Processos!$AJ$10:$AJ$509,0))="","",INDEX(Processos!$M$10:$M$509,MATCH((ROW()-9+($J$8-1)*50),Processos!$AJ$10:$AJ$509,0)))))>190,LEFT(IF((ROW()-9+($J$8-1)*50)>COUNTIFS(Processos!$X$10:$X$509,1,Processos!$Y$10:$Y$509,1),"",IF(INDEX(Processos!$M$10:$M$509,MATCH((ROW()-9+($J$8-1)*50),Processos!$AJ$10:$AJ$509,0))="","",INDEX(Processos!$M$10:$M$509,MATCH((ROW()-9+($J$8-1)*50),Processos!$AJ$10:$AJ$509,0)))),190)&" [...]",IF((ROW()-9+($J$8-1)*50)>COUNTIFS(Processos!$X$10:$X$509,1,Processos!$Y$10:$Y$509,1),"",IF(INDEX(Processos!$M$10:$M$509,MATCH((ROW()-9+($J$8-1)*50),Processos!$AJ$10:$AJ$509,0))="","",INDEX(Processos!$M$10:$M$509,MATCH((ROW()-9+($J$8-1)*50),Processos!$AJ$10:$AJ$509,0))))),CHAR(10)," "),CHAR(13)," ") -> O recurso do Sindicato foi provido para condenar a Alta até o período que ela particilou do processo, porém, em sustenação oral feita pelo BMM, o Relator pediu vista do processo. Estamos agu [...] | E14: =IF($A14="","",IFERROR(INDEX(Processos!$AR$10:$AR$509,MATCH($A14,Processos!$A$10:$A$509,0)),"")&CHAR(10)&IFERROR(IF(OR(INDEX(Origem!$AB$10:$AB$509,MATCH($A14,Origem!$A$10:$A$509,0))="",INDEX(Origem!$AB$10:$AB$509,MATCH($A14,Origem!$A$10:$A$509,0))="—"),"Origem: sem classificação","Origem: "&INDEX(Origem!$AB$10:$AB$509,MATCH($A14,Origem!$A$10:$A$509,0))&IF(INDEX(Origem!$AC$10:$AC$509,MATCH($A14,Origem!$A$10:$A$509,0))=""," (sem pontuação)"," • "&INDEX(Origem!$AC$10:$AC$509,MATCH($A14,Origem!$A$10:$A$509,0))&" pontos")),"Origem: sem classificação")) -> Prioridade crítica. Criticidade herdada da planilha de origem; validar. Não confirma bloqueio/penhora vigente. Origem: 🔴 CRÍTICO • 65 pontos | F14: =IF((ROW()-9+($J$8-1)*50)>COUNTIFS(Processos!$X$10:$X$509,1,Processos!$Y$10:$Y$509,1),"",IF(INDEX(Processos!$AQ$10:$AQ$509,MATCH((ROW()-9+($J$8-1)*50),Processos!$AJ$10:$AJ$509,0))="","",INDEX(Processos!$AQ$10:$AQ$509,MATCH((ROW()-9+($J$8-1)*50),Processos!$AJ$10:$AJ$509,0)))) -> 2018074.8 | G14: =IF((ROW()-9+($J$8-1)*50)>COUNTIFS(Processos!$X$10:$X$509,1,Processos!$Y$10:$Y$509,1),"",IFERROR(HYPERLINK("#'Ficha'!C6","Selecionar na Ficha"),"Selecionar na Ficha")) -> Selecionar na Ficha
A15: =IF((ROW()-9+($J$8-1)*50)>COUNTIFS(Processos!$X$10:$X$509,1,Processos!$Y$10:$Y$509,1),"",IF(INDEX(Processos!$A$10:$A$509,MATCH((ROW()-9+($J$8-1)*50),Processos!$AJ$10:$AJ$509,0))="","",INDEX(Processos!$A$10:$A$509,MATCH((ROW()-9+($J$8-1)*50),Processos!$AJ$10:$AJ$509,0)))) -> 0010723-70.2019.5.18.0104 | B15: =IF((ROW()-9+($J$8-1)*50)>COUNTIFS(Processos!$X$10:$X$509,1,Processos!$Y$10:$Y$509,1),"",IF(INDEX(Processos!$D$10:$D$509,MATCH((ROW()-9+($J$8-1)*50),Processos!$AJ$10:$AJ$509,0))="","",INDEX(Processos!$D$10:$D$509,MATCH((ROW()-9+($J$8-1)*50),Processos!$AJ$10:$AJ$509,0)))) -> BMM Advogados | C15: =IF(LEN(SUBSTITUTE(SUBSTITUTE(IF(LEN(IF((ROW()-9+($J$8-1)*50)>COUNTIFS(Processos!$X$10:$X$509,1,Processos!$Y$10:$Y$509,1),"",IF(INDEX(Processos!$H$10:$H$509,MATCH((ROW()-9+($J$8-1)*50),Processos!$AJ$10:$AJ$509,0))&" × "&INDEX(Processos!$I$10:$I$509,MATCH((ROW()-9+($J$8-1)*50),Processos!$AJ$10:$AJ$509,0))="","",INDEX(Processos!$H$10:$H$509,MATCH((ROW()-9+($J$8-1)*50),Processos!$AJ$10:$AJ$509,0))&" × "&INDEX(Processos!$I$10:$I$509,MATCH((ROW()-9+($J$8-1)*50),Processos!$AJ$10:$AJ$509,0)))))>190,LEFT(IF((ROW()-9+($J$8-1)*50)>COUNTIFS(Processos!$X$10:$X$509,1,Processos!$Y$10:$Y$509,1),"",IF(INDEX(Processos!$H$10:$H$509,MATCH((ROW()-9+($J$8-1)*50),Processos!$AJ$10:$AJ$509,0))&" × "&INDEX(Processos!$I$10:$I$509,MATCH((ROW()-9+($J$8-1)*50),Processos!$AJ$10:$AJ$509,0))="","",INDEX(Processos!$H$10:$H$509,MATCH((ROW()-9+($J$8-1)*50),Processos!$AJ$10:$AJ$509,0))&" × "&INDEX(Processos!$I$10:$I$509,MATCH((ROW()-9+($J$8-1)*50),Processos!$AJ$10:$AJ$509,0)))),190)&" [...]",IF((ROW()-9+($J$8-1)*50)>COUNTIFS(Processos!$X$10:$X$509,1,Processos!$Y$10:$Y$509,1),"",IF(INDEX(Processos!$H$10:$H$509,MATCH((ROW()-9+($J$8-1)*50),Processos!$AJ$10:$AJ$509,0))&" × "&INDEX(Processos!$I$10:$I$509,MATCH((ROW()-9+($J$8-1)*50),Processos!$AJ$10:$AJ$509,0))="","",INDEX(Processos!$H$10:$H$509,MATCH((ROW()-9+($J$8-1)*50),Processos!$AJ$10:$AJ$509,0))&" × "&INDEX(Processos!$I$10:$I$509,MATCH((ROW()-9+($J$8-1)*50),Processos!$AJ$10:$AJ$509,0))))),CHAR(10)," "),CHAR(13)," "))>150,LEFT(SUBSTITUTE(SUBSTITUTE(IF(LEN(IF((ROW()-9+($J$8-1)*50)>COUNTIFS(Processos!$X$10:$X$509,1,Processos!$Y$10:$Y$509,1),"",IF(INDEX(Processos!$H$10:$H$509,MATCH((ROW()-9+($J$8-1)*50),Processos!$AJ$10:$AJ$509,0))&" × "&INDEX(Processos!$I$10:$I$509,MATCH((ROW()-9+($J$8-1)*50),Processos!$AJ$10:$AJ$509,0))="","",INDEX(Processos!$H$10:$H$509,MATCH((ROW()-9+($J$8-1)*50),Processos!$AJ$10:$AJ$509,0))&" × "&INDEX(Processos!$I$10:$I$509,MATCH((ROW()-9+($J$8-1)*50),Processos!$AJ$10:$AJ$509,0)))))>190,LEFT(IF((ROW()-9+($J$8-1)*50)>COUNTIFS(Processos!$X$10:$X$509,1,Processos!$Y$10:$Y$509,1),"",IF(INDEX(Processos!$H$10:$H$509,MATCH((ROW()-9+($J$8-1)*50),Processos!$AJ$10:$AJ$509,0))&" × "&INDEX(Processos!$I$10:$I$509,MATCH((ROW()-9+($J$8-1)*50),Processos!$AJ$10:$AJ$509,0))="","",INDEX(Processos!$H$10:$H$509,MATCH((ROW()-9+($J$8-1)*50),Processos!$AJ$10:$AJ$509,0))&" × "&INDEX(Processos!$I$10:$I$509,MATCH((ROW()-9+($J$8-1)*50),Processos!$AJ$10:$AJ$509,0)))),190)&" [...]",IF((ROW()-9+($J$8-1)*50)>COUNTIFS(Processos!$X$10:$X$509,1,Processos!$Y$10:$Y$509,1),"",IF(INDEX(Processos!$H$10:$H$509,MATCH((ROW()-9+($J$8-1)*50),Processos!$AJ$10:$AJ$509,0))&" × "&INDEX(Processos!$I$10:$I$509,MATCH((ROW()-9+($J$8-1)*50),Processos!$AJ$10:$AJ$509,0))="","",INDEX(Processos!$H$10:$H$509,MATCH((ROW()-9+($J$8-1)*50),Processos!$AJ$10:$AJ$509,0))&" × "&INDEX(Processos!$I$10:$I$509,MATCH((ROW()-9+($J$8-1)*50),Processos!$AJ$10:$AJ$509,0))))),CHAR(10)," "),CHAR(13)," "),150)&" [...]",SUBSTITUTE(SUBSTITUTE(IF(LEN(IF((ROW()-9+($J$8-1)*50)>COUNTIFS(Processos!$X$10:$X$509,1,Processos!$Y$10:$Y$509,1),"",IF(INDEX(Processos!$H$10:$H$509,MATCH((ROW()-9+($J$8-1)*50),Processos!$AJ$10:$AJ$509,0))&" × "&INDEX(Processos!$I$10:$I$509,MATCH((ROW()-9+($J$8-1)*50),Processos!$AJ$10:$AJ$509,0))="","",INDEX(Processos!$H$10:$H$509,MATCH((ROW()-9+($J$8-1)*50),Processos!$AJ$10:$AJ$509,0))&" × "&INDEX(Processos!$I$10:$I$509,MATCH((ROW()-9+($J$8-1)*50),Processos!$AJ$10:$AJ$509,0)))))>190,LEFT(IF((ROW()-9+($J$8-1)*50)>COUNTIFS(Processos!$X$10:$X$509,1,Processos!$Y$10:$Y$509,1),"",IF(INDEX(Processos!$H$10:$H$509,MATCH((ROW()-9+($J$8-1)*50),Processos!$AJ$10:$AJ$509,0))&" × "&INDEX(Processos!$I$10:$I$509,MATCH((ROW()-9+($J$8-1)*50),Processos!$AJ$10:$AJ$509,0))="","",INDEX(Processos!$H$10:$H$509,MATCH((ROW()-9+($J$8-1)*50),Processos!$AJ$10:$AJ$509,0))&" × "&INDEX(Processos!$I$10:$I$509,MATCH((ROW()-9+($J$8-1)*50),Processos!$AJ$10:$AJ$509,0)))),190)&" [...]",IF((ROW()-9+($J$8-1)*50)>COUNTIFS(Processos!$X$10:$X$509,1,Processos!$Y$10:$Y$509,1),"",IF(INDEX(Processos!$H$10:$H$509,MATCH((ROW()-9+($J$8-1)*50),Processos!$AJ$10:$AJ$509,0))&" × "&INDEX(Processos!$I$10:$I$509,MATCH((ROW()-9+($J$8-1)*50),Processos!$AJ$10:$AJ$509,0))="","",INDEX(Processos!$H$10:$H$509,MATCH((ROW()-9+($J$8-1)*50),Processos!$AJ$10:$AJ$509,0))&" × "&INDEX(Processos!$I$10:$I$509,MATCH((ROW()-9+($J$8-1)*50),Processos!$AJ$10:$AJ$509,0))))),CHAR(10)," "),CHAR(13)," ")) -> Sindicato Dos Trabalhadores Nas Industrias Da Construcao × 1 - Consórcio Integral Spavias Trail Alta 2 - SPA Engenharia Indústria e Comércio LTDA 3 - [...] | D15: =SUBSTITUTE(SUBSTITUTE(IF(LEN(IF((ROW()-9+($J$8-1)*50)>COUNTIFS(Processos!$X$10:$X$509,1,Processos!$Y$10:$Y$509,1),"",IF(INDEX(Processos!$M$10:$M$509,MATCH((ROW()-9+($J$8-1)*50),Processos!$AJ$10:$AJ$509,0))="","",INDEX(Processos!$M$10:$M$509,MATCH((ROW()-9+($J$8-1)*50),Processos!$AJ$10:$AJ$509,0)))))>190,LEFT(IF((ROW()-9+($J$8-1)*50)>COUNTIFS(Processos!$X$10:$X$509,1,Processos!$Y$10:$Y$509,1),"",IF(INDEX(Processos!$M$10:$M$509,MATCH((ROW()-9+($J$8-1)*50),Processos!$AJ$10:$AJ$509,0))="","",INDEX(Processos!$M$10:$M$509,MATCH((ROW()-9+($J$8-1)*50),Processos!$AJ$10:$AJ$509,0)))),190)&" [...]",IF((ROW()-9+($J$8-1)*50)>COUNTIFS(Processos!$X$10:$X$509,1,Processos!$Y$10:$Y$509,1),"",IF(INDEX(Processos!$M$10:$M$509,MATCH((ROW()-9+($J$8-1)*50),Processos!$AJ$10:$AJ$509,0))="","",INDEX(Processos!$M$10:$M$509,MATCH((ROW()-9+($J$8-1)*50),Processos!$AJ$10:$AJ$509,0))))),CHAR(10)," "),CHAR(13)," ") -> Trata-se de um processo em que o Sindicato dos Trabalhadores nas Indústrias da Construção Pesada no Estado de Goiás (STICEP) ajuizou ação de obrigação de fazer em face de diversas empresas e [...] | E15: =IF($A15="","",IFERROR(INDEX(Processos!$AR$10:$AR$509,MATCH($A15,Processos!$A$10:$A$509,0)),"")&CHAR(10)&IFERROR(IF(OR(INDEX(Origem!$AB$10:$AB$509,MATCH($A15,Origem!$A$10:$A$509,0))="",INDEX(Origem!$AB$10:$AB$509,MATCH($A15,Origem!$A$10:$A$509,0))="—"),"Origem: sem classificação","Origem: "&INDEX(Origem!$AB$10:$AB$509,MATCH($A15,Origem!$A$10:$A$509,0))&IF(INDEX(Origem!$AC$10:$AC$509,MATCH($A15,Origem!$A$10:$A$509,0))=""," (sem pontuação)"," • "&INDEX(Origem!$AC$10:$AC$509,MATCH($A15,Origem!$A$10:$A$509,0))&" pontos")),"Origem: sem classificação")) -> Prioridade crítica. Criticidade herdada da planilha de origem; validar. Não confirma bloqueio/penhora vigente. Origem: 🔴 CRÍTICO • 80 pontos | F15: =IF((ROW()-9+($J$8-1)*50)>COUNTIFS(Processos!$X$10:$X$509,1,Processos!$Y$10:$Y$509,1),"",IF(INDEX(Processos!$AQ$10:$AQ$509,MATCH((ROW()-9+($J$8-1)*50),Processos!$AJ$10:$AJ$509,0))="","",INDEX(Processos!$AQ$10:$AQ$509,MATCH((ROW()-9+($J$8-1)*50),Processos!$AJ$10:$AJ$509,0)))) -> 2681428.5 | G15: =IF((ROW()-9+($J$8-1)*50)>COUNTIFS(Processos!$X$10:$X$509,1,Processos!$Y$10:$Y$509,1),"",IFERROR(HYPERLINK("#'Ficha'!C6","Selecionar na Ficha"),"Selecionar na Ficha")) -> Selecionar na Ficha
A16: =IF((ROW()-9+($J$8-1)*50)>COUNTIFS(Processos!$X$10:$X$509,1,Processos!$Y$10:$Y$509,1),"",IF(INDEX(Processos!$A$10:$A$509,MATCH((ROW()-9+($J$8-1)*50),Processos!$AJ$10:$AJ$509,0))="","",INDEX(Processos!$A$10:$A$509,MATCH((ROW()-9+($J$8-1)*50),Processos!$AJ$10:$AJ$509,0)))) -> 5225553-65.2023.8.13.0024 | B16: =IF((ROW()-9+($J$8-1)*50)>COUNTIFS(Processos!$X$10:$X$509,1,Processos!$Y$10:$Y$509,1),"",IF(INDEX(Processos!$D$10:$D$509,MATCH((ROW()-9+($J$8-1)*50),Processos!$AJ$10:$AJ$509,0))="","",INDEX(Processos!$D$10:$D$509,MATCH((ROW()-9+($J$8-1)*50),Processos!$AJ$10:$AJ$509,0)))) -> Sacha Calmon | C16: =IF(LEN(SUBSTITUTE(SUBSTITUTE(IF(LEN(IF((ROW()-9+($J$8-1)*50)>COUNTIFS(Processos!$X$10:$X$509,1,Processos!$Y$10:$Y$509,1),"",IF(INDEX(Processos!$H$10:$H$509,MATCH((ROW()-9+($J$8-1)*50),Processos!$AJ$10:$AJ$509,0))&" × "&INDEX(Processos!$I$10:$I$509,MATCH((ROW()-9+($J$8-1)*50),Processos!$AJ$10:$AJ$509,0))="","",INDEX(Processos!$H$10:$H$509,MATCH((ROW()-9+($J$8-1)*50),Processos!$AJ$10:$AJ$509,0))&" × "&INDEX(Processos!$I$10:$I$509,MATCH((ROW()-9+($J$8-1)*50),Processos!$AJ$10:$AJ$509,0)))))>190,LEFT(IF((ROW()-9+($J$8-1)*50)>COUNTIFS(Processos!$X$10:$X$509,1,Processos!$Y$10:$Y$509,1),"",IF(INDEX(Processos!$H$10:$H$509,MATCH((ROW()-9+($J$8-1)*50),Processos!$AJ$10:$AJ$509,0))&" × "&INDEX(Processos!$I$10:$I$509,MATCH((ROW()-9+($J$8-1)*50),Processos!$AJ$10:$AJ$509,0))="","",INDEX(Processos!$H$10:$H$509,MATCH((ROW()-9+($J$8-1)*50),Processos!$AJ$10:$AJ$509,0))&" × "&INDEX(Processos!$I$10:$I$509,MATCH((ROW()-9+($J$8-1)*50),Processos!$AJ$10:$AJ$509,0)))),190)&" [...]",IF((ROW()-9+($J$8-1)*50)>COUNTIFS(Processos!$X$10:$X$509,1,Processos!$Y$10:$Y$509,1),"",IF(INDEX(Processos!$H$10:$H$509,MATCH((ROW()-9+($J$8-1)*50),Processos!$AJ$10:$AJ$509,0))&" × "&INDEX(Processos!$I$10:$I$509,MATCH((ROW()-9+($J$8-1)*50),Processos!$AJ$10:$AJ$509,0))="","",INDEX(Processos!$H$10:$H$509,MATCH((ROW()-9+($J$8-1)*50),Processos!$AJ$10:$AJ$509,0))&" × "&INDEX(Processos!$I$10:$I$509,MATCH((ROW()-9+($J$8-1)*50),Processos!$AJ$10:$AJ$509,0))))),CHAR(10)," "),CHAR(13)," "))>150,LEFT(SUBSTITUTE(SUBSTITUTE(IF(LEN(IF((ROW()-9+($J$8-1)*50)>COUNTIFS(Processos!$X$10:$X$509,1,Processos!$Y$10:$Y$509,1),"",IF(INDEX(Processos!$H$10:$H$509,MATCH((ROW()-9+($J$8-1)*50),Processos!$AJ$10:$AJ$509,0))&" × "&INDEX(Processos!$I$10:$I$509,MATCH((ROW()-9+($J$8-1)*50),Processos!$AJ$10:$AJ$509,0))="","",INDEX(Processos!$H$10:$H$509,MATCH((ROW()-9+($J$8-1)*50),Processos!$AJ$10:$AJ$509,0))&" × "&INDEX(Processos!$I$10:$I$509,MATCH((ROW()-9+($J$8-1)*50),Processos!$AJ$10:$AJ$509,0)))))>190,LEFT(IF((ROW()-9+($J$8-1)*50)>COUNTIFS(Processos!$X$10:$X$509,1,Processos!$Y$10:$Y$509,1),"",IF(INDEX(Processos!$H$10:$H$509,MATCH((ROW()-9+($J$8-1)*50),Processos!$AJ$10:$AJ$509,0))&" × "&INDEX(Processos!$I$10:$I$509,MATCH((ROW()-9+($J$8-1)*50),Processos!$AJ$10:$AJ$509,0))="","",INDEX(Processos!$H$10:$H$509,MATCH((ROW()-9+($J$8-1)*50),Processos!$AJ$10:$AJ$509,0))&" × "&INDEX(Processos!$I$10:$I$509,MATCH((ROW()-9+($J$8-1)*50),Processos!$AJ$10:$AJ$509,0)))),190)&" [...]",IF((ROW()-9+($J$8-1)*50)>COUNTIFS(Processos!$X$10:$X$509,1,Processos!$Y$10:$Y$509,1),"",IF(INDEX(Processos!$H$10:$H$509,MATCH((ROW()-9+($J$8-1)*50),Processos!$AJ$10:$AJ$509,0))&" × "&INDEX(Processos!$I$10:$I$509,MATCH((ROW()-9+($J$8-1)*50),Processos!$AJ$10:$AJ$509,0))="","",INDEX(Processos!$H$10:$H$509,MATCH((ROW()-9+($J$8-1)*50),Processos!$AJ$10:$AJ$509,0))&" × "&INDEX(Processos!$I$10:$I$509,MATCH((ROW()-9+($J$8-1)*50),Processos!$AJ$10:$AJ$509,0))))),CHAR(10)," "),CHAR(13)," "),150)&" [...]",SUBSTITUTE(SUBSTITUTE(IF(LEN(IF((ROW()-9+($J$8-1)*50)>COUNTIFS(Processos!$X$10:$X$509,1,Processos!$Y$10:$Y$509,1),"",IF(INDEX(Processos!$H$10:$H$509,MATCH((ROW()-9+($J$8-1)*50),Processos!$AJ$10:$AJ$509,0))&" × "&INDEX(Processos!$I$10:$I$509,MATCH((ROW()-9+($J$8-1)*50),Processos!$AJ$10:$AJ$509,0))="","",INDEX(Processos!$H$10:$H$509,MATCH((ROW()-9+($J$8-1)*50),Processos!$AJ$10:$AJ$509,0))&" × "&INDEX(Processos!$I$10:$I$509,MATCH((ROW()-9+($J$8-1)*50),Processos!$AJ$10:$AJ$509,0)))))>190,LEFT(IF((ROW()-9+($J$8-1)*50)>COUNTIFS(Processos!$X$10:$X$509,1,Processos!$Y$10:$Y$509,1),"",IF(INDEX(Processos!$H$10:$H$509,MATCH((ROW()-9+($J$8-1)*50),Processos!$AJ$10:$AJ$509,0))&" × "&INDEX(Processos!$I$10:$I$509,MATCH((ROW()-9+($J$8-1)*50),Processos!$AJ$10:$AJ$509,0))="","",INDEX(Processos!$H$10:$H$509,MATCH((ROW()-9+($J$8-1)*50),Processos!$AJ$10:$AJ$509,0))&" × "&INDEX(Processos!$I$10:$I$509,MATCH((ROW()-9+($J$8-1)*50),Processos!$AJ$10:$AJ$509,0)))),190)&" [...]",IF((ROW()-9+($J$8-1)*50)>COUNTIFS(Processos!$X$10:$X$509,1,Processos!$Y$10:$Y$509,1),"",IF(INDEX(Processos!$H$10:$H$509,MATCH((ROW()-9+($J$8-1)*50),Processos!$AJ$10:$AJ$509,0))&" × "&INDEX(Processos!$I$10:$I$509,MATCH((ROW()-9+($J$8-1)*50),Processos!$AJ$10:$AJ$509,0))="","",INDEX(Processos!$H$10:$H$509,MATCH((ROW()-9+($J$8-1)*50),Processos!$AJ$10:$AJ$509,0))&" × "&INDEX(Processos!$I$10:$I$509,MATCH((ROW()-9+($J$8-1)*50),Processos!$AJ$10:$AJ$509,0))))),CHAR(10)," "),CHAR(13)," ")) -> Município de Belo Horizonte × ALTA | D16: =SUBSTITUTE(SUBSTITUTE(IF(LEN(IF((ROW()-9+($J$8-1)*50)>COUNTIFS(Processos!$X$10:$X$509,1,Processos!$Y$10:$Y$509,1),"",IF(INDEX(Processos!$M$10:$M$509,MATCH((ROW()-9+($J$8-1)*50),Processos!$AJ$10:$AJ$509,0))="","",INDEX(Processos!$M$10:$M$509,MATCH((ROW()-9+($J$8-1)*50),Processos!$AJ$10:$AJ$509,0)))))>190,LEFT(IF((ROW()-9+($J$8-1)*50)>COUNTIFS(Processos!$X$10:$X$509,1,Processos!$Y$10:$Y$509,1),"",IF(INDEX(Processos!$M$10:$M$509,MATCH((ROW()-9+($J$8-1)*50),Processos!$AJ$10:$AJ$509,0))="","",INDEX(Processos!$M$10:$M$509,MATCH((ROW()-9+($J$8-1)*50),Processos!$AJ$10:$AJ$509,0)))),190)&" [...]",IF((ROW()-9+($J$8-1)*50)>COUNTIFS(Processos!$X$10:$X$509,1,Processos!$Y$10:$Y$509,1),"",IF(INDEX(Processos!$M$10:$M$509,MATCH((ROW()-9+($J$8-1)*50),Processos!$AJ$10:$AJ$509,0))="","",INDEX(Processos!$M$10:$M$509,MATCH((ROW()-9+($J$8-1)*50),Processos!$AJ$10:$AJ$509,0))))),CHAR(10)," "),CHAR(13)," ") -> ISS Cobrança de 3 débitos, sendo que um está em discussão na Anulatória (ALT-001) e dois foram quitados pela Alta. ----------- DÉBITO EM DISCUSSÃO NA AÇÃO ANULATÓRIA Nº 52873929120238130024 [...] | E16: =IF($A16="","",IFERROR(INDEX(Processos!$AR$10:$AR$509,MATCH($A16,Processos!$A$10:$A$509,0)),"")&CHAR(10)&IFERROR(IF(OR(INDEX(Origem!$AB$10:$AB$509,MATCH($A16,Origem!$A$10:$A$509,0))="",INDEX(Origem!$AB$10:$AB$509,MATCH($A16,Origem!$A$10:$A$509,0))="—"),"Origem: sem classificação","Origem: "&INDEX(Origem!$AB$10:$AB$509,MATCH($A16,Origem!$A$10:$A$509,0))&IF(INDEX(Origem!$AC$10:$AC$509,MATCH($A16,Origem!$A$10:$A$509,0))=""," (sem pontuação)"," • "&INDEX(Origem!$AC$10:$AC$509,MATCH($A16,Origem!$A$10:$A$509,0))&" pontos")),"Origem: sem classificação")) -> Prioridade crítica. Criticidade herdada da planilha de origem; validar. Não confirma bloqueio/penhora vigente. Origem: 🔴 CRÍTICO • 65 pontos | F16: =IF((ROW()-9+($J$8-1)*50)>COUNTIFS(Processos!$X$10:$X$509,1,Processos!$Y$10:$Y$509,1),"",IF(INDEX(Processos!$AQ$10:$AQ$509,MATCH((ROW()-9+($J$8-1)*50),Processos!$AJ$10:$AJ$509,0))="","",INDEX(Processos!$AQ$10:$AQ$509,MATCH((ROW()-9+($J$8-1)*50),Processos!$AJ$10:$AJ$509,0)))) -> 28362468 | G16: =IF((ROW()-9+($J$8-1)*50)>COUNTIFS(Processos!$X$10:$X$509,1,Processos!$Y$10:$Y$509,1),"",IFERROR(HYPERLINK("#'Ficha'!C6","Selecionar na Ficha"),"Selecionar na Ficha")) -> Selecionar na Ficha
A17: =IF((ROW()-9+($J$8-1)*50)>COUNTIFS(Processos!$X$10:$X$509,1,Processos!$Y$10:$Y$509,1),"",IF(INDEX(Processos!$A$10:$A$509,MATCH((ROW()-9+($J$8-1)*50),Processos!$AJ$10:$AJ$509,0))="","",INDEX(Processos!$A$10:$A$509,MATCH((ROW()-9+($J$8-1)*50),Processos!$AJ$10:$AJ$509,0)))) | B17: =IF((ROW()-9+($J$8-1)*50)>COUNTIFS(Processos!$X$10:$X$509,1,Processos!$Y$10:$Y$509,1),"",IF(INDEX(Processos!$D$10:$D$509,MATCH((ROW()-9+($J$8-1)*50),Processos!$AJ$10:$AJ$509,0))="","",INDEX(Processos!$D$10:$D$509,MATCH((ROW()-9+($J$8-1)*50),Processos!$AJ$10:$AJ$509,0)))) | C17: =IF(LEN(SUBSTITUTE(SUBSTITUTE(IF(LEN(IF((ROW()-9+($J$8-1)*50)>COUNTIFS(Processos!$X$10:$X$509,1,Processos!$Y$10:$Y$509,1),"",IF(INDEX(Processos!$H$10:$H$509,MATCH((ROW()-9+($J$8-1)*50),Processos!$AJ$10:$AJ$509,0))&" × "&INDEX(Processos!$I$10:$I$509,MATCH((ROW()-9+($J$8-1)*50),Processos!$AJ$10:$AJ$509,0))="","",INDEX(Processos!$H$10:$H$509,MATCH((ROW()-9+($J$8-1)*50),Processos!$AJ$10:$AJ$509,0))&" × "&INDEX(Processos!$I$10:$I$509,MATCH((ROW()-9+($J$8-1)*50),Processos!$AJ$10:$AJ$509,0)))))>190,LEFT(IF((ROW()-9+($J$8-1)*50)>COUNTIFS(Processos!$X$10:$X$509,1,Processos!$Y$10:$Y$509,1),"",IF(INDEX(Processos!$H$10:$H$509,MATCH((ROW()-9+($J$8-1)*50),Processos!$AJ$10:$AJ$509,0))&" × "&INDEX(Processos!$I$10:$I$509,MATCH((ROW()-9+($J$8-1)*50),Processos!$AJ$10:$AJ$509,0))="","",INDEX(Processos!$H$10:$H$509,MATCH((ROW()-9+($J$8-1)*50),Processos!$AJ$10:$AJ$509,0))&" × "&INDEX(Processos!$I$10:$I$509,MATCH((ROW()-9+($J$8-1)*50),Processos!$AJ$10:$AJ$509,0)))),190)&" [...]",IF((ROW()-9+($J$8-1)*50)>COUNTIFS(Processos!$X$10:$X$509,1,Processos!$Y$10:$Y$509,1),"",IF(INDEX(Processos!$H$10:$H$509,MATCH((ROW()-9+($J$8-1)*50),Processos!$AJ$10:$AJ$509,0))&" × "&INDEX(Processos!$I$10:$I$509,MATCH((ROW()-9+($J$8-1)*50),Processos!$AJ$10:$AJ$509,0))="","",INDEX(Processos!$H$10:$H$509,MATCH((ROW()-9+($J$8-1)*50),Processos!$AJ$10:$AJ$509,0))&" × "&INDEX(Processos!$I$10:$I$509,MATCH((ROW()-9+($J$8-1)*50),Processos!$AJ$10:$AJ$509,0))))),CHAR(10)," "),CHAR(13)," "))>150,LEFT(SUBSTITUTE(SUBSTITUTE(IF(LEN(IF((ROW()-9+($J$8-1)*50)>COUNTIFS(Processos!$X$10:$X$509,1,Processos!$Y$10:$Y$509,1),"",IF(INDEX(Processos!$H$10:$H$509,MATCH((ROW()-9+($J$8-1)*50),Processos!$AJ$10:$AJ$509,0))&" × "&INDEX(Processos!$I$10:$I$509,MATCH((ROW()-9+($J$8-1)*50),Processos!$AJ$10:$AJ$509,0))="","",INDEX(Processos!$H$10:$H$509,MATCH((ROW()-9+($J$8-1)*50),Processos!$AJ$10:$AJ$509,0))&" × "&INDEX(Processos!$I$10:$I$509,MATCH((ROW()-9+($J$8-1)*50),Processos!$AJ$10:$AJ$509,0)))))>190,LEFT(IF((ROW()-9+($J$8-1)*50)>COUNTIFS(Processos!$X$10:$X$509,1,Processos!$Y$10:$Y$509,1),"",IF(INDEX(Processos!$H$10:$H$509,MATCH((ROW()-9+($J$8-1)*50),Processos!$AJ$10:$AJ$509,0))&" × "&INDEX(Processos!$I$10:$I$509,MATCH((ROW()-9+($J$8-1)*50),Processos!$AJ$10:$AJ$509,0))="","",INDEX(Processos!$H$10:$H$509,MATCH((ROW()-9+($J$8-1)*50),Processos!$AJ$10:$AJ$509,0))&" × "&INDEX(Processos!$I$10:$I$509,MATCH((ROW()-9+($J$8-1)*50),Processos!$AJ$10:$AJ$509,0)))),190)&" [...]",IF((ROW()-9+($J$8-1)*50)>COUNTIFS(Processos!$X$10:$X$509,1,Processos!$Y$10:$Y$509,1),"",IF(INDEX(Processos!$H$10:$H$509,MATCH((ROW()-9+($J$8-1)*50),Processos!$AJ$10:$AJ$509,0))&" × "&INDEX(Processos!$I$10:$I$509,MATCH((ROW()-9+($J$8-1)*50),Processos!$AJ$10:$AJ$509,0))="","",INDEX(Processos!$H$10:$H$509,MATCH((ROW()-9+($J$8-1)*50),Processos!$AJ$10:$AJ$509,0))&" × "&INDEX(Processos!$I$10:$I$509,MATCH((ROW()-9+($J$8-1)*50),Processos!$AJ$10:$AJ$509,0))))),CHAR(10)," "),CHAR(13)," "),150)&" [...]",SUBSTITUTE(SUBSTITUTE(IF(LEN(IF((ROW()-9+($J$8-1)*50)>COUNTIFS(Processos!$X$10:$X$509,1,Processos!$Y$10:$Y$509,1),"",IF(INDEX(Processos!$H$10:$H$509,MATCH((ROW()-9+($J$8-1)*50),Processos!$AJ$10:$AJ$509,0))&" × "&INDEX(Processos!$I$10:$I$509,MATCH((ROW()-9+($J$8-1)*50),Processos!$AJ$10:$AJ$509,0))="","",INDEX(Processos!$H$10:$H$509,MATCH((ROW()-9+($J$8-1)*50),Processos!$AJ$10:$AJ$509,0))&" × "&INDEX(Processos!$I$10:$I$509,MATCH((ROW()-9+($J$8-1)*50),Processos!$AJ$10:$AJ$509,0)))))>190,LEFT(IF((ROW()-9+($J$8-1)*50)>COUNTIFS(Processos!$X$10:$X$509,1,Processos!$Y$10:$Y$509,1),"",IF(INDEX(Processos!$H$10:$H$509,MATCH((ROW()-9+($J$8-1)*50),Processos!$AJ$10:$AJ$509,0))&" × "&INDEX(Processos!$I$10:$I$509,MATCH((ROW()-9+($J$8-1)*50),Processos!$AJ$10:$AJ$509,0))="","",INDEX(Processos!$H$10:$H$509,MATCH((ROW()-9+($J$8-1)*50),Processos!$AJ$10:$AJ$509,0))&" × "&INDEX(Processos!$I$10:$I$509,MATCH((ROW()-9+($J$8-1)*50),Processos!$AJ$10:$AJ$509,0)))),190)&" [...]",IF((ROW()-9+($J$8-1)*50)>COUNTIFS(Processos!$X$10:$X$509,1,Processos!$Y$10:$Y$509,1),"",IF(INDEX(Processos!$H$10:$H$509,MATCH((ROW()-9+($J$8-1)*50),Processos!$AJ$10:$AJ$509,0))&" × "&INDEX(Processos!$I$10:$I$509,MATCH((ROW()-9+($J$8-1)*50),Processos!$AJ$10:$AJ$509,0))="","",INDEX(Processos!$H$10:$H$509,MATCH((ROW()-9+($J$8-1)*50),Processos!$AJ$10:$AJ$509,0))&" × "&INDEX(Processos!$I$10:$I$509,MATCH((ROW()-9+($J$8-1)*50),Processos!$AJ$10:$AJ$509,0))))),CHAR(10)," "),CHAR(13)," ")) | D17: =SUBSTITUTE(SUBSTITUTE(IF(LEN(IF((ROW()-9+($J$8-1)*50)>COUNTIFS(Processos!$X$10:$X$509,1,Processos!$Y$10:$Y$509,1),"",IF(INDEX(Processos!$M$10:$M$509,MATCH((ROW()-9+($J$8-1)*50),Processos!$AJ$10:$AJ$509,0))="","",INDEX(Processos!$M$10:$M$509,MATCH((ROW()-9+($J$8-1)*50),Processos!$AJ$10:$AJ$509,0)))))>190,LEFT(IF((ROW()-9+($J$8-1)*50)>COUNTIFS(Processos!$X$10:$X$509,1,Processos!$Y$10:$Y$509,1),"",IF(INDEX(Processos!$M$10:$M$509,MATCH((ROW()-9+($J$8-1)*50),Processos!$AJ$10:$AJ$509,0))="","",INDEX(Processos!$M$10:$M$509,MATCH((ROW()-9+($J$8-1)*50),Processos!$AJ$10:$AJ$509,0)))),190)&" [...]",IF((ROW()-9+($J$8-1)*50)>COUNTIFS(Processos!$X$10:$X$509,1,Processos!$Y$10:$Y$509,1),"",IF(INDEX(Processos!$M$10:$M$509,MATCH((ROW()-9+($J$8-1)*50),Processos!$AJ$10:$AJ$509,0))="","",INDEX(Processos!$M$10:$M$509,MATCH((ROW()-9+($J$8-1)*50),Processos!$AJ$10:$AJ$509,0))))),CHAR(10)," "),CHAR(13)," ") | E17: =IF($A17="","",IFERROR(INDEX(Processos!$AR$10:$AR$509,MATCH($A17,Processos!$A$10:$A$509,0)),"")&CHAR(10)&IFERROR(IF(OR(INDEX(Origem!$AB$10:$AB$509,MATCH($A17,Origem!$A$10:$A$509,0))="",INDEX(Origem!$AB$10:$AB$509,MATCH($A17,Origem!$A$10:$A$509,0))="—"),"Origem: sem classificação","Origem: "&INDEX(Origem!$AB$10:$AB$509,MATCH($A17,Origem!$A$10:$A$509,0))&IF(INDEX(Origem!$AC$10:$AC$509,MATCH($A17,Origem!$A$10:$A$509,0))=""," (sem pontuação)"," • "&INDEX(Origem!$AC$10:$AC$509,MATCH($A17,Origem!$A$10:$A$509,0))&" pontos")),"Origem: sem classificação")) | F17: =IF((ROW()-9+($J$8-1)*50)>COUNTIFS(Processos!$X$10:$X$509,1,Processos!$Y$10:$Y$509,1),"",IF(INDEX(Processos!$AQ$10:$AQ$509,MATCH((ROW()-9+($J$8-1)*50),Processos!$AJ$10:$AJ$509,0))="","",INDEX(Processos!$AQ$10:$AQ$509,MATCH((ROW()-9+($J$8-1)*50),Processos!$AJ$10:$AJ$509,0)))) | G17: =IF((ROW()-9+($J$8-1)*50)>COUNTIFS(Processos!$X$10:$X$509,1,Processos!$Y$10:$Y$509,1),"",IFERROR(HYPERLINK("#'Ficha'!C6","Selecionar na Ficha"),"Selecionar na Ficha"))
A18: =IF((ROW()-9+($J$8-1)*50)>COUNTIFS(Processos!$X$10:$X$509,1,Processos!$Y$10:$Y$509,1),"",IF(INDEX(Processos!$A$10:$A$509,MATCH((ROW()-9+($J$8-1)*50),Processos!$AJ$10:$AJ$509,0))="","",INDEX(Processos!$A$10:$A$509,MATCH((ROW()-9+($J$8-1)*50),Processos!$AJ$10:$AJ$509,0)))) | B18: =IF((ROW()-9+($J$8-1)*50)>COUNTIFS(Processos!$X$10:$X$509,1,Processos!$Y$10:$Y$509,1),"",IF(INDEX(Processos!$D$10:$D$509,MATCH((ROW()-9+($J$8-1)*50),Processos!$AJ$10:$AJ$509,0))="","",INDEX(Processos!$D$10:$D$509,MATCH((ROW()-9+($J$8-1)*50),Processos!$AJ$10:$AJ$509,0)))) | C18: =IF(LEN(SUBSTITUTE(SUBSTITUTE(IF(LEN(IF((ROW()-9+($J$8-1)*50)>COUNTIFS(Processos!$X$10:$X$509,1,Processos!$Y$10:$Y$509,1),"",IF(INDEX(Processos!$H$10:$H$509,MATCH((ROW()-9+($J$8-1)*50),Processos!$AJ$10:$AJ$509,0))&" × "&INDEX(Processos!$I$10:$I$509,MATCH((ROW()-9+($J$8-1)*50),Processos!$AJ$10:$AJ$509,0))="","",INDEX(Processos!$H$10:$H$509,MATCH((ROW()-9+($J$8-1)*50),Processos!$AJ$10:$AJ$509,0))&" × "&INDEX(Processos!$I$10:$I$509,MATCH((ROW()-9+($J$8-1)*50),Processos!$AJ$10:$AJ$509,0)))))>190,LEFT(IF((ROW()-9+($J$8-1)*50)>COUNTIFS(Processos!$X$10:$X$509,1,Processos!$Y$10:$Y$509,1),"",IF(INDEX(Processos!$H$10:$H$509,MATCH((ROW()-9+($J$8-1)*50),Processos!$AJ$10:$AJ$509,0))&" × "&INDEX(Processos!$I$10:$I$509,MATCH((ROW()-9+($J$8-1)*50),Processos!$AJ$10:$AJ$509,0))="","",INDEX(Processos!$H$10:$H$509,MATCH((ROW()-9+($J$8-1)*50),Processos!$AJ$10:$AJ$509,0))&" × "&INDEX(Processos!$I$10:$I$509,MATCH((ROW()-9+($J$8-1)*50),Processos!$AJ$10:$AJ$509,0)))),190)&" [...]",IF((ROW()-9+($J$8-1)*50)>COUNTIFS(Processos!$X$10:$X$509,1,Processos!$Y$10:$Y$509,1),"",IF(INDEX(Processos!$H$10:$H$509,MATCH((ROW()-9+($J$8-1)*50),Processos!$AJ$10:$AJ$509,0))&" × "&INDEX(Processos!$I$10:$I$509,MATCH((ROW()-9+($J$8-1)*50),Processos!$AJ$10:$AJ$509,0))="","",INDEX(Processos!$H$10:$H$509,MATCH((ROW()-9+($J$8-1)*50),Processos!$AJ$10:$AJ$509,0))&" × "&INDEX(Processos!$I$10:$I$509,MATCH((ROW()-9+($J$8-1)*50),Processos!$AJ$10:$AJ$509,0))))),CHAR(10)," "),CHAR(13)," "))>150,LEFT(SUBSTITUTE(SUBSTITUTE(IF(LEN(IF((ROW()-9+($J$8-1)*50)>COUNTIFS(Processos!$X$10:$X$509,1,Processos!$Y$10:$Y$509,1),"",IF(INDEX(Processos!$H$10:$H$509,MATCH((ROW()-9+($J$8-1)*50),Processos!$AJ$10:$AJ$509,0))&" × "&INDEX(Processos!$I$10:$I$509,MATCH((ROW()-9+($J$8-1)*50),Processos!$AJ$10:$AJ$509,0))="","",INDEX(Processos!$H$10:$H$509,MATCH((ROW()-9+($J$8-1)*50),Processos!$AJ$10:$AJ$509,0))&" × "&INDEX(Processos!$I$10:$I$509,MATCH((ROW()-9+($J$8-1)*50),Processos!$AJ$10:$AJ$509,0)))))>190,LEFT(IF((ROW()-9+($J$8-1)*50)>COUNTIFS(Processos!$X$10:$X$509,1,Processos!$Y$10:$Y$509,1),"",IF(INDEX(Processos!$H$10:$H$509,MATCH((ROW()-9+($J$8-1)*50),Processos!$AJ$10:$AJ$509,0))&" × "&INDEX(Processos!$I$10:$I$509,MATCH((ROW()-9+($J$8-1)*50),Processos!$AJ$10:$AJ$509,0))="","",INDEX(Processos!$H$10:$H$509,MATCH((ROW()-9+($J$8-1)*50),Processos!$AJ$10:$AJ$509,0))&" × "&INDEX(Processos!$I$10:$I$509,MATCH((ROW()-9+($J$8-1)*50),Processos!$AJ$10:$AJ$509,0)))),190)&" [...]",IF((ROW()-9+($J$8-1)*50)>COUNTIFS(Processos!$X$10:$X$509,1,Processos!$Y$10:$Y$509,1),"",IF(INDEX(Processos!$H$10:$H$509,MATCH((ROW()-9+($J$8-1)*50),Processos!$AJ$10:$AJ$509,0))&" × "&INDEX(Processos!$I$10:$I$509,MATCH((ROW()-9+($J$8-1)*50),Processos!$AJ$10:$AJ$509,0))="","",INDEX(Processos!$H$10:$H$509,MATCH((ROW()-9+($J$8-1)*50),Processos!$AJ$10:$AJ$509,0))&" × "&INDEX(Processos!$I$10:$I$509,MATCH((ROW()-9+($J$8-1)*50),Processos!$AJ$10:$AJ$509,0))))),CHAR(10)," "),CHAR(13)," "),150)&" [...]",SUBSTITUTE(SUBSTITUTE(IF(LEN(IF((ROW()-9+($J$8-1)*50)>COUNTIFS(Processos!$X$10:$X$509,1,Processos!$Y$10:$Y$509,1),"",IF(INDEX(Processos!$H$10:$H$509,MATCH((ROW()-9+($J$8-1)*50),Processos!$AJ$10:$AJ$509,0))&" × "&INDEX(Processos!$I$10:$I$509,MATCH((ROW()-9+($J$8-1)*50),Processos!$AJ$10:$AJ$509,0))="","",INDEX(Processos!$H$10:$H$509,MATCH((ROW()-9+($J$8-1)*50),Processos!$AJ$10:$AJ$509,0))&" × "&INDEX(Processos!$I$10:$I$509,MATCH((ROW()-9+($J$8-1)*50),Processos!$AJ$10:$AJ$509,0)))))>190,LEFT(IF((ROW()-9+($J$8-1)*50)>COUNTIFS(Processos!$X$10:$X$509,1,Processos!$Y$10:$Y$509,1),"",IF(INDEX(Processos!$H$10:$H$509,MATCH((ROW()-9+($J$8-1)*50),Processos!$AJ$10:$AJ$509,0))&" × "&INDEX(Processos!$I$10:$I$509,MATCH((ROW()-9+($J$8-1)*50),Processos!$AJ$10:$AJ$509,0))="","",INDEX(Processos!$H$10:$H$509,MATCH((ROW()-9+($J$8-1)*50),Processos!$AJ$10:$AJ$509,0))&" × "&INDEX(Processos!$I$10:$I$509,MATCH((ROW()-9+($J$8-1)*50),Processos!$AJ$10:$AJ$509,0)))),190)&" [...]",IF((ROW()-9+($J$8-1)*50)>COUNTIFS(Processos!$X$10:$X$509,1,Processos!$Y$10:$Y$509,1),"",IF(INDEX(Processos!$H$10:$H$509,MATCH((ROW()-9+($J$8-1)*50),Processos!$AJ$10:$AJ$509,0))&" × "&INDEX(Processos!$I$10:$I$509,MATCH((ROW()-9+($J$8-1)*50),Processos!$AJ$10:$AJ$509,0))="","",INDEX(Processos!$H$10:$H$509,MATCH((ROW()-9+($J$8-1)*50),Processos!$AJ$10:$AJ$509,0))&" × "&INDEX(Processos!$I$10:$I$509,MATCH((ROW()-9+($J$8-1)*50),Processos!$AJ$10:$AJ$509,0))))),CHAR(10)," "),CHAR(13)," ")) | D18: =SUBSTITUTE(SUBSTITUTE(IF(LEN(IF((ROW()-9+($J$8-1)*50)>COUNTIFS(Processos!$X$10:$X$509,1,Processos!$Y$10:$Y$509,1),"",IF(INDEX(Processos!$M$10:$M$509,MATCH((ROW()-9+($J$8-1)*50),Processos!$AJ$10:$AJ$509,0))="","",INDEX(Processos!$M$10:$M$509,MATCH((ROW()-9+($J$8-1)*50),Processos!$AJ$10:$AJ$509,0)))))>190,LEFT(IF((ROW()-9+($J$8-1)*50)>COUNTIFS(Processos!$X$10:$X$509,1,Processos!$Y$10:$Y$509,1),"",IF(INDEX(Processos!$M$10:$M$509,MATCH((ROW()-9+($J$8-1)*50),Processos!$AJ$10:$AJ$509,0))="","",INDEX(Processos!$M$10:$M$509,MATCH((ROW()-9+($J$8-1)*50),Processos!$AJ$10:$AJ$509,0)))),190)&" [...]",IF((ROW()-9+($J$8-1)*50)>COUNTIFS(Processos!$X$10:$X$509,1,Processos!$Y$10:$Y$509,1),"",IF(INDEX(Processos!$M$10:$M$509,MATCH((ROW()-9+($J$8-1)*50),Processos!$AJ$10:$AJ$509,0))="","",INDEX(Processos!$M$10:$M$509,MATCH((ROW()-9+($J$8-1)*50),Processos!$AJ$10:$AJ$509,0))))),CHAR(10)," "),CHAR(13)," ") | E18: =IF($A18="","",IFERROR(INDEX(Processos!$AR$10:$AR$509,MATCH($A18,Processos!$A$10:$A$509,0)),"")&CHAR(10)&IFERROR(IF(OR(INDEX(Origem!$AB$10:$AB$509,MATCH($A18,Origem!$A$10:$A$509,0))="",INDEX(Origem!$AB$10:$AB$509,MATCH($A18,Origem!$A$10:$A$509,0))="—"),"Origem: sem classificação","Origem: "&INDEX(Origem!$AB$10:$AB$509,MATCH($A18,Origem!$A$10:$A$509,0))&IF(INDEX(Origem!$AC$10:$AC$509,MATCH($A18,Origem!$A$10:$A$509,0))=""," (sem pontuação)"," • "&INDEX(Origem!$AC$10:$AC$509,MATCH($A18,Origem!$A$10:$A$509,0))&" pontos")),"Origem: sem classificação")) | F18: =IF((ROW()-9+($J$8-1)*50)>COUNTIFS(Processos!$X$10:$X$509,1,Processos!$Y$10:$Y$509,1),"",IF(INDEX(Processos!$AQ$10:$AQ$509,MATCH((ROW()-9+($J$8-1)*50),Processos!$AJ$10:$AJ$509,0))="","",INDEX(Processos!$AQ$10:$AQ$509,MATCH((ROW()-9+($J$8-1)*50),Processos!$AJ$10:$AJ$509,0)))) | G18: =IF((ROW()-9+($J$8-1)*50)>COUNTIFS(Processos!$X$10:$X$509,1,Processos!$Y$10:$Y$509,1),"",IFERROR(HYPERLINK("#'Ficha'!C6","Selecionar na Ficha"),"Selecionar na Ficha"))
A19: =IF((ROW()-9+($J$8-1)*50)>COUNTIFS(Processos!$X$10:$X$509,1,Processos!$Y$10:$Y$509,1),"",IF(INDEX(Processos!$A$10:$A$509,MATCH((ROW()-9+($J$8-1)*50),Processos!$AJ$10:$AJ$509,0))="","",INDEX(Processos!$A$10:$A$509,MATCH((ROW()-9+($J$8-1)*50),Processos!$AJ$10:$AJ$509,0)))) | B19: =IF((ROW()-9+($J$8-1)*50)>COUNTIFS(Processos!$X$10:$X$509,1,Processos!$Y$10:$Y$509,1),"",IF(INDEX(Processos!$D$10:$D$509,MATCH((ROW()-9+($J$8-1)*50),Processos!$AJ$10:$AJ$509,0))="","",INDEX(Processos!$D$10:$D$509,MATCH((ROW()-9+($J$8-1)*50),Processos!$AJ$10:$AJ$509,0)))) | C19: =IF(LEN(SUBSTITUTE(SUBSTITUTE(IF(LEN(IF((ROW()-9+($J$8-1)*50)>COUNTIFS(Processos!$X$10:$X$509,1,Processos!$Y$10:$Y$509,1),"",IF(INDEX(Processos!$H$10:$H$509,MATCH((ROW()-9+($J$8-1)*50),Processos!$AJ$10:$AJ$509,0))&" × "&INDEX(Processos!$I$10:$I$509,MATCH((ROW()-9+($J$8-1)*50),Processos!$AJ$10:$AJ$509,0))="","",INDEX(Processos!$H$10:$H$509,MATCH((ROW()-9+($J$8-1)*50),Processos!$AJ$10:$AJ$509,0))&" × "&INDEX(Processos!$I$10:$I$509,MATCH((ROW()-9+($J$8-1)*50),Processos!$AJ$10:$AJ$509,0)))))>190,LEFT(IF((ROW()-9+($J$8-1)*50)>COUNTIFS(Processos!$X$10:$X$509,1,Processos!$Y$10:$Y$509,1),"",IF(INDEX(Processos!$H$10:$H$509,MATCH((ROW()-9+($J$8-1)*50),Processos!$AJ$10:$AJ$509,0))&" × "&INDEX(Processos!$I$10:$I$509,MATCH((ROW()-9+($J$8-1)*50),Processos!$AJ$10:$AJ$509,0))="","",INDEX(Processos!$H$10:$H$509,MATCH((ROW()-9+($J$8-1)*50),Processos!$AJ$10:$AJ$509,0))&" × "&INDEX(Processos!$I$10:$I$509,MATCH((ROW()-9+($J$8-1)*50),Processos!$AJ$10:$AJ$509,0)))),190)&" [...]",IF((ROW()-9+($J$8-1)*50)>COUNTIFS(Processos!$X$10:$X$509,1,Processos!$Y$10:$Y$509,1),"",IF(INDEX(Processos!$H$10:$H$509,MATCH((ROW()-9+($J$8-1)*50),Processos!$AJ$10:$AJ$509,0))&" × "&INDEX(Processos!$I$10:$I$509,MATCH((ROW()-9+($J$8-1)*50),Processos!$AJ$10:$AJ$509,0))="","",INDEX(Processos!$H$10:$H$509,MATCH((ROW()-9+($J$8-1)*50),Processos!$AJ$10:$AJ$509,0))&" × "&INDEX(Processos!$I$10:$I$509,MATCH((ROW()-9+($J$8-1)*50),Processos!$AJ$10:$AJ$509,0))))),CHAR(10)," "),CHAR(13)," "))>150,LEFT(SUBSTITUTE(SUBSTITUTE(IF(LEN(IF((ROW()-9+($J$8-1)*50)>COUNTIFS(Processos!$X$10:$X$509,1,Processos!$Y$10:$Y$509,1),"",IF(INDEX(Processos!$H$10:$H$509,MATCH((ROW()-9+($J$8-1)*50),Processos!$AJ$10:$AJ$509,0))&" × "&INDEX(Processos!$I$10:$I$509,MATCH((ROW()-9+($J$8-1)*50),Processos!$AJ$10:$AJ$509,0))="","",INDEX(Processos!$H$10:$H$509,MATCH((ROW()-9+($J$8-1)*50),Processos!$AJ$10:$AJ$509,0))&" × "&INDEX(Processos!$I$10:$I$509,MATCH((ROW()-9+($J$8-1)*50),Processos!$AJ$10:$AJ$509,0)))))>190,LEFT(IF((ROW()-9+($J$8-1)*50)>COUNTIFS(Processos!$X$10:$X$509,1,Processos!$Y$10:$Y$509,1),"",IF(INDEX(Processos!$H$10:$H$509,MATCH((ROW()-9+($J$8-1)*50),Processos!$AJ$10:$AJ$509,0))&" × "&INDEX(Processos!$I$10:$I$509,MATCH((ROW()-9+($J$8-1)*50),Processos!$AJ$10:$AJ$509,0))="","",INDEX(Processos!$H$10:$H$509,MATCH((ROW()-9+($J$8-1)*50),Processos!$AJ$10:$AJ$509,0))&" × "&INDEX(Processos!$I$10:$I$509,MATCH((ROW()-9+($J$8-1)*50),Processos!$AJ$10:$AJ$509,0)))),190)&" [...]",IF((ROW()-9+($J$8-1)*50)>COUNTIFS(Processos!$X$10:$X$509,1,Processos!$Y$10:$Y$509,1),"",IF(INDEX(Processos!$H$10:$H$509,MATCH((ROW()-9+($J$8-1)*50),Processos!$AJ$10:$AJ$509,0))&" × "&INDEX(Processos!$I$10:$I$509,MATCH((ROW()-9+($J$8-1)*50),Processos!$AJ$10:$AJ$509,0))="","",INDEX(Processos!$H$10:$H$509,MATCH((ROW()-9+($J$8-1)*50),Processos!$AJ$10:$AJ$509,0))&" × "&INDEX(Processos!$I$10:$I$509,MATCH((ROW()-9+($J$8-1)*50),Processos!$AJ$10:$AJ$509,0))))),CHAR(10)," "),CHAR(13)," "),150)&" [...]",SUBSTITUTE(SUBSTITUTE(IF(LEN(IF((ROW()-9+($J$8-1)*50)>COUNTIFS(Processos!$X$10:$X$509,1,Processos!$Y$10:$Y$509,1),"",IF(INDEX(Processos!$H$10:$H$509,MATCH((ROW()-9+($J$8-1)*50),Processos!$AJ$10:$AJ$509,0))&" × "&INDEX(Processos!$I$10:$I$509,MATCH((ROW()-9+($J$8-1)*50),Processos!$AJ$10:$AJ$509,0))="","",INDEX(Processos!$H$10:$H$509,MATCH((ROW()-9+($J$8-1)*50),Processos!$AJ$10:$AJ$509,0))&" × "&INDEX(Processos!$I$10:$I$509,MATCH((ROW()-9+($J$8-1)*50),Processos!$AJ$10:$AJ$509,0)))))>190,LEFT(IF((ROW()-9+($J$8-1)*50)>COUNTIFS(Processos!$X$10:$X$509,1,Processos!$Y$10:$Y$509,1),"",IF(INDEX(Processos!$H$10:$H$509,MATCH((ROW()-9+($J$8-1)*50),Processos!$AJ$10:$AJ$509,0))&" × "&INDEX(Processos!$I$10:$I$509,MATCH((ROW()-9+($J$8-1)*50),Processos!$AJ$10:$AJ$509,0))="","",INDEX(Processos!$H$10:$H$509,MATCH((ROW()-9+($J$8-1)*50),Processos!$AJ$10:$AJ$509,0))&" × "&INDEX(Processos!$I$10:$I$509,MATCH((ROW()-9+($J$8-1)*50),Processos!$AJ$10:$AJ$509,0)))),190)&" [...]",IF((ROW()-9+($J$8-1)*50)>COUNTIFS(Processos!$X$10:$X$509,1,Processos!$Y$10:$Y$509,1),"",IF(INDEX(Processos!$H$10:$H$509,MATCH((ROW()-9+($J$8-1)*50),Processos!$AJ$10:$AJ$509,0))&" × "&INDEX(Processos!$I$10:$I$509,MATCH((ROW()-9+($J$8-1)*50),Processos!$AJ$10:$AJ$509,0))="","",INDEX(Processos!$H$10:$H$509,MATCH((ROW()-9+($J$8-1)*50),Processos!$AJ$10:$AJ$509,0))&" × "&INDEX(Processos!$I$10:$I$509,MATCH((ROW()-9+($J$8-1)*50),Processos!$AJ$10:$AJ$509,0))))),CHAR(10)," "),CHAR(13)," ")) | D19: =SUBSTITUTE(SUBSTITUTE(IF(LEN(IF((ROW()-9+($J$8-1)*50)>COUNTIFS(Processos!$X$10:$X$509,1,Processos!$Y$10:$Y$509,1),"",IF(INDEX(Processos!$M$10:$M$509,MATCH((ROW()-9+($J$8-1)*50),Processos!$AJ$10:$AJ$509,0))="","",INDEX(Processos!$M$10:$M$509,MATCH((ROW()-9+($J$8-1)*50),Processos!$AJ$10:$AJ$509,0)))))>190,LEFT(IF((ROW()-9+($J$8-1)*50)>COUNTIFS(Processos!$X$10:$X$509,1,Processos!$Y$10:$Y$509,1),"",IF(INDEX(Processos!$M$10:$M$509,MATCH((ROW()-9+($J$8-1)*50),Processos!$AJ$10:$AJ$509,0))="","",INDEX(Processos!$M$10:$M$509,MATCH((ROW()-9+($J$8-1)*50),Processos!$AJ$10:$AJ$509,0)))),190)&" [...]",IF((ROW()-9+($J$8-1)*50)>COUNTIFS(Processos!$X$10:$X$509,1,Processos!$Y$10:$Y$509,1),"",IF(INDEX(Processos!$M$10:$M$509,MATCH((ROW()-9+($J$8-1)*50),Processos!$AJ$10:$AJ$509,0))="","",INDEX(Processos!$M$10:$M$509,MATCH((ROW()-9+($J$8-1)*50),Processos!$AJ$10:$AJ$509,0))))),CHAR(10)," "),CHAR(13)," ") | E19: =IF($A19="","",IFERROR(INDEX(Processos!$AR$10:$AR$509,MATCH($A19,Processos!$A$10:$A$509,0)),"")&CHAR(10)&IFERROR(IF(OR(INDEX(Origem!$AB$10:$AB$509,MATCH($A19,Origem!$A$10:$A$509,0))="",INDEX(Origem!$AB$10:$AB$509,MATCH($A19,Origem!$A$10:$A$509,0))="—"),"Origem: sem classificação","Origem: "&INDEX(Origem!$AB$10:$AB$509,MATCH($A19,Origem!$A$10:$A$509,0))&IF(INDEX(Origem!$AC$10:$AC$509,MATCH($A19,Origem!$A$10:$A$509,0))=""," (sem pontuação)"," • "&INDEX(Origem!$AC$10:$AC$509,MATCH($A19,Origem!$A$10:$A$509,0))&" pontos")),"Origem: sem classificação")) | F19: =IF((ROW()-9+($J$8-1)*50)>COUNTIFS(Processos!$X$10:$X$509,1,Processos!$Y$10:$Y$509,1),"",IF(INDEX(Processos!$AQ$10:$AQ$509,MATCH((ROW()-9+($J$8-1)*50),Processos!$AJ$10:$AJ$509,0))="","",INDEX(Processos!$AQ$10:$AQ$509,MATCH((ROW()-9+($J$8-1)*50),Processos!$AJ$10:$AJ$509,0)))) | G19: =IF((ROW()-9+($J$8-1)*50)>COUNTIFS(Processos!$X$10:$X$509,1,Processos!$Y$10:$Y$509,1),"",IFERROR(HYPERLINK("#'Ficha'!C6","Selecionar na Ficha"),"Selecionar na Ficha"))
A20: =IF((ROW()-9+($J$8-1)*50)>COUNTIFS(Processos!$X$10:$X$509,1,Processos!$Y$10:$Y$509,1),"",IF(INDEX(Processos!$A$10:$A$509,MATCH((ROW()-9+($J$8-1)*50),Processos!$AJ$10:$AJ$509,0))="","",INDEX(Processos!$A$10:$A$509,MATCH((ROW()-9+($J$8-1)*50),Processos!$AJ$10:$AJ$509,0)))) | B20: =IF((ROW()-9+($J$8-1)*50)>COUNTIFS(Processos!$X$10:$X$509,1,Processos!$Y$10:$Y$509,1),"",IF(INDEX(Processos!$D$10:$D$509,MATCH((ROW()-9+($J$8-1)*50),Processos!$AJ$10:$AJ$509,0))="","",INDEX(Processos!$D$10:$D$509,MATCH((ROW()-9+($J$8-1)*50),Processos!$AJ$10:$AJ$509,0)))) | C20: =IF(LEN(SUBSTITUTE(SUBSTITUTE(IF(LEN(IF((ROW()-9+($J$8-1)*50)>COUNTIFS(Processos!$X$10:$X$509,1,Processos!$Y$10:$Y$509,1),"",IF(INDEX(Processos!$H$10:$H$509,MATCH((ROW()-9+($J$8-1)*50),Processos!$AJ$10:$AJ$509,0))&" × "&INDEX(Processos!$I$10:$I$509,MATCH((ROW()-9+($J$8-1)*50),Processos!$AJ$10:$AJ$509,0))="","",INDEX(Processos!$H$10:$H$509,MATCH((ROW()-9+($J$8-1)*50),Processos!$AJ$10:$AJ$509,0))&" × "&INDEX(Processos!$I$10:$I$509,MATCH((ROW()-9+($J$8-1)*50),Processos!$AJ$10:$AJ$509,0)))))>190,LEFT(IF((ROW()-9+($J$8-1)*50)>COUNTIFS(Processos!$X$10:$X$509,1,Processos!$Y$10:$Y$509,1),"",IF(INDEX(Processos!$H$10:$H$509,MATCH((ROW()-9+($J$8-1)*50),Processos!$AJ$10:$AJ$509,0))&" × "&INDEX(Processos!$I$10:$I$509,MATCH((ROW()-9+($J$8-1)*50),Processos!$AJ$10:$AJ$509,0))="","",INDEX(Processos!$H$10:$H$509,MATCH((ROW()-9+($J$8-1)*50),Processos!$AJ$10:$AJ$509,0))&" × "&INDEX(Processos!$I$10:$I$509,MATCH((ROW()-9+($J$8-1)*50),Processos!$AJ$10:$AJ$509,0)))),190)&" [...]",IF((ROW()-9+($J$8-1)*50)>COUNTIFS(Processos!$X$10:$X$509,1,Processos!$Y$10:$Y$509,1),"",IF(INDEX(Processos!$H$10:$H$509,MATCH((ROW()-9+($J$8-1)*50),Processos!$AJ$10:$AJ$509,0))&" × "&INDEX(Processos!$I$10:$I$509,MATCH((ROW()-9+($J$8-1)*50),Processos!$AJ$10:$AJ$509,0))="","",INDEX(Processos!$H$10:$H$509,MATCH((ROW()-9+($J$8-1)*50),Processos!$AJ$10:$AJ$509,0))&" × "&INDEX(Processos!$I$10:$I$509,MATCH((ROW()-9+($J$8-1)*50),Processos!$AJ$10:$AJ$509,0))))),CHAR(10)," "),CHAR(13)," "))>150,LEFT(SUBSTITUTE(SUBSTITUTE(IF(LEN(IF((ROW()-9+($J$8-1)*50)>COUNTIFS(Processos!$X$10:$X$509,1,Processos!$Y$10:$Y$509,1),"",IF(INDEX(Processos!$H$10:$H$509,MATCH((ROW()-9+($J$8-1)*50),Processos!$AJ$10:$AJ$509,0))&" × "&INDEX(Processos!$I$10:$I$509,MATCH((ROW()-9+($J$8-1)*50),Processos!$AJ$10:$AJ$509,0))="","",INDEX(Processos!$H$10:$H$509,MATCH((ROW()-9+($J$8-1)*50),Processos!$AJ$10:$AJ$509,0))&" × "&INDEX(Processos!$I$10:$I$509,MATCH((ROW()-9+($J$8-1)*50),Processos!$AJ$10:$AJ$509,0)))))>190,LEFT(IF((ROW()-9+($J$8-1)*50)>COUNTIFS(Processos!$X$10:$X$509,1,Processos!$Y$10:$Y$509,1),"",IF(INDEX(Processos!$H$10:$H$509,MATCH((ROW()-9+($J$8-1)*50),Processos!$AJ$10:$AJ$509,0))&" × "&INDEX(Processos!$I$10:$I$509,MATCH((ROW()-9+($J$8-1)*50),Processos!$AJ$10:$AJ$509,0))="","",INDEX(Processos!$H$10:$H$509,MATCH((ROW()-9+($J$8-1)*50),Processos!$AJ$10:$AJ$509,0))&" × "&INDEX(Processos!$I$10:$I$509,MATCH((ROW()-9+($J$8-1)*50),Processos!$AJ$10:$AJ$509,0)))),190)&" [...]",IF((ROW()-9+($J$8-1)*50)>COUNTIFS(Processos!$X$10:$X$509,1,Processos!$Y$10:$Y$509,1),"",IF(INDEX(Processos!$H$10:$H$509,MATCH((ROW()-9+($J$8-1)*50),Processos!$AJ$10:$AJ$509,0))&" × "&INDEX(Processos!$I$10:$I$509,MATCH((ROW()-9+($J$8-1)*50),Processos!$AJ$10:$AJ$509,0))="","",INDEX(Processos!$H$10:$H$509,MATCH((ROW()-9+($J$8-1)*50),Processos!$AJ$10:$AJ$509,0))&" × "&INDEX(Processos!$I$10:$I$509,MATCH((ROW()-9+($J$8-1)*50),Processos!$AJ$10:$AJ$509,0))))),CHAR(10)," "),CHAR(13)," "),150)&" [...]",SUBSTITUTE(SUBSTITUTE(IF(LEN(IF((ROW()-9+($J$8-1)*50)>COUNTIFS(Processos!$X$10:$X$509,1,Processos!$Y$10:$Y$509,1),"",IF(INDEX(Processos!$H$10:$H$509,MATCH((ROW()-9+($J$8-1)*50),Processos!$AJ$10:$AJ$509,0))&" × "&INDEX(Processos!$I$10:$I$509,MATCH((ROW()-9+($J$8-1)*50),Processos!$AJ$10:$AJ$509,0))="","",INDEX(Processos!$H$10:$H$509,MATCH((ROW()-9+($J$8-1)*50),Processos!$AJ$10:$AJ$509,0))&" × "&INDEX(Processos!$I$10:$I$509,MATCH((ROW()-9+($J$8-1)*50),Processos!$AJ$10:$AJ$509,0)))))>190,LEFT(IF((ROW()-9+($J$8-1)*50)>COUNTIFS(Processos!$X$10:$X$509,1,Processos!$Y$10:$Y$509,1),"",IF(INDEX(Processos!$H$10:$H$509,MATCH((ROW()-9+($J$8-1)*50),Processos!$AJ$10:$AJ$509,0))&" × "&INDEX(Processos!$I$10:$I$509,MATCH((ROW()-9+($J$8-1)*50),Processos!$AJ$10:$AJ$509,0))="","",INDEX(Processos!$H$10:$H$509,MATCH((ROW()-9+($J$8-1)*50),Processos!$AJ$10:$AJ$509,0))&" × "&INDEX(Processos!$I$10:$I$509,MATCH((ROW()-9+($J$8-1)*50),Processos!$AJ$10:$AJ$509,0)))),190)&" [...]",IF((ROW()-9+($J$8-1)*50)>COUNTIFS(Processos!$X$10:$X$509,1,Processos!$Y$10:$Y$509,1),"",IF(INDEX(Processos!$H$10:$H$509,MATCH((ROW()-9+($J$8-1)*50),Processos!$AJ$10:$AJ$509,0))&" × "&INDEX(Processos!$I$10:$I$509,MATCH((ROW()-9+($J$8-1)*50),Processos!$AJ$10:$AJ$509,0))="","",INDEX(Processos!$H$10:$H$509,MATCH((ROW()-9+($J$8-1)*50),Processos!$AJ$10:$AJ$509,0))&" × "&INDEX(Processos!$I$10:$I$509,MATCH((ROW()-9+($J$8-1)*50),Processos!$AJ$10:$AJ$509,0))))),CHAR(10)," "),CHAR(13)," ")) | D20: =SUBSTITUTE(SUBSTITUTE(IF(LEN(IF((ROW()-9+($J$8-1)*50)>COUNTIFS(Processos!$X$10:$X$509,1,Processos!$Y$10:$Y$509,1),"",IF(INDEX(Processos!$M$10:$M$509,MATCH((ROW()-9+($J$8-1)*50),Processos!$AJ$10:$AJ$509,0))="","",INDEX(Processos!$M$10:$M$509,MATCH((ROW()-9+($J$8-1)*50),Processos!$AJ$10:$AJ$509,0)))))>190,LEFT(IF((ROW()-9+($J$8-1)*50)>COUNTIFS(Processos!$X$10:$X$509,1,Processos!$Y$10:$Y$509,1),"",IF(INDEX(Processos!$M$10:$M$509,MATCH((ROW()-9+($J$8-1)*50),Processos!$AJ$10:$AJ$509,0))="","",INDEX(Processos!$M$10:$M$509,MATCH((ROW()-9+($J$8-1)*50),Processos!$AJ$10:$AJ$509,0)))),190)&" [...]",IF((ROW()-9+($J$8-1)*50)>COUNTIFS(Processos!$X$10:$X$509,1,Processos!$Y$10:$Y$509,1),"",IF(INDEX(Processos!$M$10:$M$509,MATCH((ROW()-9+($J$8-1)*50),Processos!$AJ$10:$AJ$509,0))="","",INDEX(Processos!$M$10:$M$509,MATCH((ROW()-9+($J$8-1)*50),Processos!$AJ$10:$AJ$509,0))))),CHAR(10)," "),CHAR(13)," ") | E20: =IF($A20="","",IFERROR(INDEX(Processos!$AR$10:$AR$509,MATCH($A20,Processos!$A$10:$A$509,0)),"")&CHAR(10)&IFERROR(IF(OR(INDEX(Origem!$AB$10:$AB$509,MATCH($A20,Origem!$A$10:$A$509,0))="",INDEX(Origem!$AB$10:$AB$509,MATCH($A20,Origem!$A$10:$A$509,0))="—"),"Origem: sem classificação","Origem: "&INDEX(Origem!$AB$10:$AB$509,MATCH($A20,Origem!$A$10:$A$509,0))&IF(INDEX(Origem!$AC$10:$AC$509,MATCH($A20,Origem!$A$10:$A$509,0))=""," (sem pontuação)"," • "&INDEX(Origem!$AC$10:$AC$509,MATCH($A20,Origem!$A$10:$A$509,0))&" pontos")),"Origem: sem classificação")) | F20: =IF((ROW()-9+($J$8-1)*50)>COUNTIFS(Processos!$X$10:$X$509,1,Processos!$Y$10:$Y$509,1),"",IF(INDEX(Processos!$AQ$10:$AQ$509,MATCH((ROW()-9+($J$8-1)*50),Processos!$AJ$10:$AJ$509,0))="","",INDEX(Processos!$AQ$10:$AQ$509,MATCH((ROW()-9+($J$8-1)*50),Processos!$AJ$10:$AJ$509,0)))) | G20: =IF((ROW()-9+($J$8-1)*50)>COUNTIFS(Processos!$X$10:$X$509,1,Processos!$Y$10:$Y$509,1),"",IFERROR(HYPERLINK("#'Ficha'!C6","Selecionar na Ficha"),"Selecionar na Ficha"))
A21: =IF((ROW()-9+($J$8-1)*50)>COUNTIFS(Processos!$X$10:$X$509,1,Processos!$Y$10:$Y$509,1),"",IF(INDEX(Processos!$A$10:$A$509,MATCH((ROW()-9+($J$8-1)*50),Processos!$AJ$10:$AJ$509,0))="","",INDEX(Processos!$A$10:$A$509,MATCH((ROW()-9+($J$8-1)*50),Processos!$AJ$10:$AJ$509,0)))) | B21: =IF((ROW()-9+($J$8-1)*50)>COUNTIFS(Processos!$X$10:$X$509,1,Processos!$Y$10:$Y$509,1),"",IF(INDEX(Processos!$D$10:$D$509,MATCH((ROW()-9+($J$8-1)*50),Processos!$AJ$10:$AJ$509,0))="","",INDEX(Processos!$D$10:$D$509,MATCH((ROW()-9+($J$8-1)*50),Processos!$AJ$10:$AJ$509,0)))) | C21: =IF(LEN(SUBSTITUTE(SUBSTITUTE(IF(LEN(IF((ROW()-9+($J$8-1)*50)>COUNTIFS(Processos!$X$10:$X$509,1,Processos!$Y$10:$Y$509,1),"",IF(INDEX(Processos!$H$10:$H$509,MATCH((ROW()-9+($J$8-1)*50),Processos!$AJ$10:$AJ$509,0))&" × "&INDEX(Processos!$I$10:$I$509,MATCH((ROW()-9+($J$8-1)*50),Processos!$AJ$10:$AJ$509,0))="","",INDEX(Processos!$H$10:$H$509,MATCH((ROW()-9+($J$8-1)*50),Processos!$AJ$10:$AJ$509,0))&" × "&INDEX(Processos!$I$10:$I$509,MATCH((ROW()-9+($J$8-1)*50),Processos!$AJ$10:$AJ$509,0)))))>190,LEFT(IF((ROW()-9+($J$8-1)*50)>COUNTIFS(Processos!$X$10:$X$509,1,Processos!$Y$10:$Y$509,1),"",IF(INDEX(Processos!$H$10:$H$509,MATCH((ROW()-9+($J$8-1)*50),Processos!$AJ$10:$AJ$509,0))&" × "&INDEX(Processos!$I$10:$I$509,MATCH((ROW()-9+($J$8-1)*50),Processos!$AJ$10:$AJ$509,0))="","",INDEX(Processos!$H$10:$H$509,MATCH((ROW()-9+($J$8-1)*50),Processos!$AJ$10:$AJ$509,0))&" × "&INDEX(Processos!$I$10:$I$509,MATCH((ROW()-9+($J$8-1)*50),Processos!$AJ$10:$AJ$509,0)))),190)&" [...]",IF((ROW()-9+($J$8-1)*50)>COUNTIFS(Processos!$X$10:$X$509,1,Processos!$Y$10:$Y$509,1),"",IF(INDEX(Processos!$H$10:$H$509,MATCH((ROW()-9+($J$8-1)*50),Processos!$AJ$10:$AJ$509,0))&" × "&INDEX(Processos!$I$10:$I$509,MATCH((ROW()-9+($J$8-1)*50),Processos!$AJ$10:$AJ$509,0))="","",INDEX(Processos!$H$10:$H$509,MATCH((ROW()-9+($J$8-1)*50),Processos!$AJ$10:$AJ$509,0))&" × "&INDEX(Processos!$I$10:$I$509,MATCH((ROW()-9+($J$8-1)*50),Processos!$AJ$10:$AJ$509,0))))),CHAR(10)," "),CHAR(13)," "))>150,LEFT(SUBSTITUTE(SUBSTITUTE(IF(LEN(IF((ROW()-9+($J$8-1)*50)>COUNTIFS(Processos!$X$10:$X$509,1,Processos!$Y$10:$Y$509,1),"",IF(INDEX(Processos!$H$10:$H$509,MATCH((ROW()-9+($J$8-1)*50),Processos!$AJ$10:$AJ$509,0))&" × "&INDEX(Processos!$I$10:$I$509,MATCH((ROW()-9+($J$8-1)*50),Processos!$AJ$10:$AJ$509,0))="","",INDEX(Processos!$H$10:$H$509,MATCH((ROW()-9+($J$8-1)*50),Processos!$AJ$10:$AJ$509,0))&" × "&INDEX(Processos!$I$10:$I$509,MATCH((ROW()-9+($J$8-1)*50),Processos!$AJ$10:$AJ$509,0)))))>190,LEFT(IF((ROW()-9+($J$8-1)*50)>COUNTIFS(Processos!$X$10:$X$509,1,Processos!$Y$10:$Y$509,1),"",IF(INDEX(Processos!$H$10:$H$509,MATCH((ROW()-9+($J$8-1)*50),Processos!$AJ$10:$AJ$509,0))&" × "&INDEX(Processos!$I$10:$I$509,MATCH((ROW()-9+($J$8-1)*50),Processos!$AJ$10:$AJ$509,0))="","",INDEX(Processos!$H$10:$H$509,MATCH((ROW()-9+($J$8-1)*50),Processos!$AJ$10:$AJ$509,0))&" × "&INDEX(Processos!$I$10:$I$509,MATCH((ROW()-9+($J$8-1)*50),Processos!$AJ$10:$AJ$509,0)))),190)&" [...]",IF((ROW()-9+($J$8-1)*50)>COUNTIFS(Processos!$X$10:$X$509,1,Processos!$Y$10:$Y$509,1),"",IF(INDEX(Processos!$H$10:$H$509,MATCH((ROW()-9+($J$8-1)*50),Processos!$AJ$10:$AJ$509,0))&" × "&INDEX(Processos!$I$10:$I$509,MATCH((ROW()-9+($J$8-1)*50),Processos!$AJ$10:$AJ$509,0))="","",INDEX(Processos!$H$10:$H$509,MATCH((ROW()-9+($J$8-1)*50),Processos!$AJ$10:$AJ$509,0))&" × "&INDEX(Processos!$I$10:$I$509,MATCH((ROW()-9+($J$8-1)*50),Processos!$AJ$10:$AJ$509,0))))),CHAR(10)," "),CHAR(13)," "),150)&" [...]",SUBSTITUTE(SUBSTITUTE(IF(LEN(IF((ROW()-9+($J$8-1)*50)>COUNTIFS(Processos!$X$10:$X$509,1,Processos!$Y$10:$Y$509,1),"",IF(INDEX(Processos!$H$10:$H$509,MATCH((ROW()-9+($J$8-1)*50),Processos!$AJ$10:$AJ$509,0))&" × "&INDEX(Processos!$I$10:$I$509,MATCH((ROW()-9+($J$8-1)*50),Processos!$AJ$10:$AJ$509,0))="","",INDEX(Processos!$H$10:$H$509,MATCH((ROW()-9+($J$8-1)*50),Processos!$AJ$10:$AJ$509,0))&" × "&INDEX(Processos!$I$10:$I$509,MATCH((ROW()-9+($J$8-1)*50),Processos!$AJ$10:$AJ$509,0)))))>190,LEFT(IF((ROW()-9+($J$8-1)*50)>COUNTIFS(Processos!$X$10:$X$509,1,Processos!$Y$10:$Y$509,1),"",IF(INDEX(Processos!$H$10:$H$509,MATCH((ROW()-9+($J$8-1)*50),Processos!$AJ$10:$AJ$509,0))&" × "&INDEX(Processos!$I$10:$I$509,MATCH((ROW()-9+($J$8-1)*50),Processos!$AJ$10:$AJ$509,0))="","",INDEX(Processos!$H$10:$H$509,MATCH((ROW()-9+($J$8-1)*50),Processos!$AJ$10:$AJ$509,0))&" × "&INDEX(Processos!$I$10:$I$509,MATCH((ROW()-9+($J$8-1)*50),Processos!$AJ$10:$AJ$509,0)))),190)&" [...]",IF((ROW()-9+($J$8-1)*50)>COUNTIFS(Processos!$X$10:$X$509,1,Processos!$Y$10:$Y$509,1),"",IF(INDEX(Processos!$H$10:$H$509,MATCH((ROW()-9+($J$8-1)*50),Processos!$AJ$10:$AJ$509,0))&" × "&INDEX(Processos!$I$10:$I$509,MATCH((ROW()-9+($J$8-1)*50),Processos!$AJ$10:$AJ$509,0))="","",INDEX(Processos!$H$10:$H$509,MATCH((ROW()-9+($J$8-1)*50),Processos!$AJ$10:$AJ$509,0))&" × "&INDEX(Processos!$I$10:$I$509,MATCH((ROW()-9+($J$8-1)*50),Processos!$AJ$10:$AJ$509,0))))),CHAR(10)," "),CHAR(13)," ")) | D21: =SUBSTITUTE(SUBSTITUTE(IF(LEN(IF((ROW()-9+($J$8-1)*50)>COUNTIFS(Processos!$X$10:$X$509,1,Processos!$Y$10:$Y$509,1),"",IF(INDEX(Processos!$M$10:$M$509,MATCH((ROW()-9+($J$8-1)*50),Processos!$AJ$10:$AJ$509,0))="","",INDEX(Processos!$M$10:$M$509,MATCH((ROW()-9+($J$8-1)*50),Processos!$AJ$10:$AJ$509,0)))))>190,LEFT(IF((ROW()-9+($J$8-1)*50)>COUNTIFS(Processos!$X$10:$X$509,1,Processos!$Y$10:$Y$509,1),"",IF(INDEX(Processos!$M$10:$M$509,MATCH((ROW()-9+($J$8-1)*50),Processos!$AJ$10:$AJ$509,0))="","",INDEX(Processos!$M$10:$M$509,MATCH((ROW()-9+($J$8-1)*50),Processos!$AJ$10:$AJ$509,0)))),190)&" [...]",IF((ROW()-9+($J$8-1)*50)>COUNTIFS(Processos!$X$10:$X$509,1,Processos!$Y$10:$Y$509,1),"",IF(INDEX(Processos!$M$10:$M$509,MATCH((ROW()-9+($J$8-1)*50),Processos!$AJ$10:$AJ$509,0))="","",INDEX(Processos!$M$10:$M$509,MATCH((ROW()-9+($J$8-1)*50),Processos!$AJ$10:$AJ$509,0))))),CHAR(10)," "),CHAR(13)," ") | E21: =IF($A21="","",IFERROR(INDEX(Processos!$AR$10:$AR$509,MATCH($A21,Processos!$A$10:$A$509,0)),"")&CHAR(10)&IFERROR(IF(OR(INDEX(Origem!$AB$10:$AB$509,MATCH($A21,Origem!$A$10:$A$509,0))="",INDEX(Origem!$AB$10:$AB$509,MATCH($A21,Origem!$A$10:$A$509,0))="—"),"Origem: sem classificação","Origem: "&INDEX(Origem!$AB$10:$AB$509,MATCH($A21,Origem!$A$10:$A$509,0))&IF(INDEX(Origem!$AC$10:$AC$509,MATCH($A21,Origem!$A$10:$A$509,0))=""," (sem pontuação)"," • "&INDEX(Origem!$AC$10:$AC$509,MATCH($A21,Origem!$A$10:$A$509,0))&" pontos")),"Origem: sem classificação")) | F21: =IF((ROW()-9+($J$8-1)*50)>COUNTIFS(Processos!$X$10:$X$509,1,Processos!$Y$10:$Y$509,1),"",IF(INDEX(Processos!$AQ$10:$AQ$509,MATCH((ROW()-9+($J$8-1)*50),Processos!$AJ$10:$AJ$509,0))="","",INDEX(Processos!$AQ$10:$AQ$509,MATCH((ROW()-9+($J$8-1)*50),Processos!$AJ$10:$AJ$509,0)))) | G21: =IF((ROW()-9+($J$8-1)*50)>COUNTIFS(Processos!$X$10:$X$509,1,Processos!$Y$10:$Y$509,1),"",IFERROR(HYPERLINK("#'Ficha'!C6","Selecionar na Ficha"),"Selecionar na Ficha"))
... A29: =IF((ROW()-9+($J$8-1)*50)>COUNTIFS(Processos!$X$10:$X$509,1,Processos!$Y$10:$Y$509,1),"",IF(INDEX(Processos!$A$10:$A$509,MATCH((ROW()-9+($J$8-1)*50),Processos!$AJ$10:$AJ$509,0))="","",INDEX(Processos!$A$10:$A$509,MATCH((ROW()-9+($J$8-1)*50),Processos!$AJ$10:$AJ$509,0)))) | B29: =IF((ROW()-9+($J$8-1)*50)>COUNTIFS(Processos!$X$10:$X$509,1,Processos!$Y$10:$Y$509,1),"",IF(INDEX(Processos!$D$10:$D$509,MATCH((ROW()-9+($J$8-1)*50),Processos!$AJ$10:$AJ$509,0))="","",INDEX(Processos!$D$10:$D$509,MATCH((ROW()-9+($J$8-1)*50),Processos!$AJ$10:$AJ$509,0)))) | C29: =IF(LEN(SUBSTITUTE(SUBSTITUTE(IF(LEN(IF((ROW()-9+($J$8-1)*50)>COUNTIFS(Processos!$X$10:$X$509,1,Processos!$Y$10:$Y$509,1),"",IF(INDEX(Processos!$H$10:$H$509,MATCH((ROW()-9+($J$8-1)*50),Processos!$AJ$10:$AJ$509,0))&" × "&INDEX(Processos!$I$10:$I$509,MATCH((ROW()-9+($J$8-1)*50),Processos!$AJ$10:$AJ$509,0))="","",INDEX(Processos!$H$10:$H$509,MATCH((ROW()-9+($J$8-1)*50),Processos!$AJ$10:$AJ$509,0))&" × "&INDEX(Processos!$I$10:$I$509,MATCH((ROW()-9+($J$8-1)*50),Processos!$AJ$10:$AJ$509,0)))))>190,LEFT(IF((ROW()-9+($J$8-1)*50)>COUNTIFS(Processos!$X$10:$X$509,1,Processos!$Y$10:$Y$509,1),"",IF(INDEX(Processos!$H$10:$H$509,MATCH((ROW()-9+($J$8-1)*50),Processos!$AJ$10:$AJ$509,0))&" × "&INDEX(Processos!$I$10:$I$509,MATCH((ROW()-9+($J$8-1)*50),Processos!$AJ$10:$AJ$509,0))="","",INDEX(Processos!$H$10:$H$509,MATCH((ROW()-9+($J$8-1)*50),Processos!$AJ$10:$AJ$509,0))&" × "&INDEX(Processos!$I$10:$I$509,MATCH((ROW()-9+($J$8-1)*50),Processos!$AJ$10:$AJ$509,0)))),190)&" [...]",IF((ROW()-9+($J$8-1)*50)>COUNTIFS(Processos!$X$10:$X$509,1,Processos!$Y$10:$Y$509,1),"",IF(INDEX(Processos!$H$10:$H$509,MATCH((ROW()-9+($J$8-1)*50),Processos!$AJ$10:$AJ$509,0))&" × "&INDEX(Processos!$I$10:$I$509,MATCH((ROW()-9+($J$8-1)*50),Processos!$AJ$10:$AJ$509,0))="","",INDEX(Processos!$H$10:$H$509,MATCH((ROW()-9+($J$8-1)*50),Processos!$AJ$10:$AJ$509,0))&" × "&INDEX(Processos!$I$10:$I$509,MATCH((ROW()-9+($J$8-1)*50),Processos!$AJ$10:$AJ$509,0))))),CHAR(10)," "),CHAR(13)," "))>150,LEFT(SUBSTITUTE(SUBSTITUTE(IF(LEN(IF((ROW()-9+($J$8-1)*50)>COUNTIFS(Processos!$X$10:$X$509,1,Processos!$Y$10:$Y$509,1),"",IF(INDEX(Processos!$H$10:$H$509,MATCH((ROW()-9+($J$8-1)*50),Processos!$AJ$10:$AJ$509,0))&" × "&INDEX(Processos!$I$10:$I$509,MATCH((ROW()-9+($J$8-1)*50),Processos!$AJ$10:$AJ$509,0))="","",INDEX(Processos!$H$10:$H$509,MATCH((ROW()-9+($J$8-1)*50),Processos!$AJ$10:$AJ$509,0))&" × "&INDEX(Processos!$I$10:$I$509,MATCH((ROW()-9+($J$8-1)*50),Processos!$AJ$10:$AJ$509,0)))))>190,LEFT(IF((ROW()-9+($J$8-1)*50)>COUNTIFS(Processos!$X$10:$X$509,1,Processos!$Y$10:$Y$509,1),"",IF(INDEX(Processos!$H$10:$H$509,MATCH((ROW()-9+($J$8-1)*50),Processos!$AJ$10:$AJ$509,0))&" × "&INDEX(Processos!$I$10:$I$509,MATCH((ROW()-9+($J$8-1)*50),Processos!$AJ$10:$AJ$509,0))="","",INDEX(Processos!$H$10:$H$509,MATCH((ROW()-9+($J$8-1)*50),Processos!$AJ$10:$AJ$509,0))&" × "&INDEX(Processos!$I$10:$I$509,MATCH((ROW()-9+($J$8-1)*50),Processos!$AJ$10:$AJ$509,0)))),190)&" [...]",IF((ROW()-9+($J$8-1)*50)>COUNTIFS(Processos!$X$10:$X$509,1,Processos!$Y$10:$Y$509,1),"",IF(INDEX(Processos!$H$10:$H$509,MATCH((ROW()-9+($J$8-1)*50),Processos!$AJ$10:$AJ$509,0))&" × "&INDEX(Processos!$I$10:$I$509,MATCH((ROW()-9+($J$8-1)*50),Processos!$AJ$10:$AJ$509,0))="","",INDEX(Processos!$H$10:$H$509,MATCH((ROW()-9+($J$8-1)*50),Processos!$AJ$10:$AJ$509,0))&" × "&INDEX(Processos!$I$10:$I$509,MATCH((ROW()-9+($J$8-1)*50),Processos!$AJ$10:$AJ$509,0))))),CHAR(10)," "),CHAR(13)," "),150)&" [...]",SUBSTITUTE(SUBSTITUTE(IF(LEN(IF((ROW()-9+($J$8-1)*50)>COUNTIFS(Processos!$X$10:$X$509,1,Processos!$Y$10:$Y$509,1),"",IF(INDEX(Processos!$H$10:$H$509,MATCH((ROW()-9+($J$8-1)*50),Processos!$AJ$10:$AJ$509,0))&" × "&INDEX(Processos!$I$10:$I$509,MATCH((ROW()-9+($J$8-1)*50),Processos!$AJ$10:$AJ$509,0))="","",INDEX(Processos!$H$10:$H$509,MATCH((ROW()-9+($J$8-1)*50),Processos!$AJ$10:$AJ$509,0))&" × "&INDEX(Processos!$I$10:$I$509,MATCH((ROW()-9+($J$8-1)*50),Processos!$AJ$10:$AJ$509,0)))))>190,LEFT(IF((ROW()-9+($J$8-1)*50)>COUNTIFS(Processos!$X$10:$X$509,1,Processos!$Y$10:$Y$509,1),"",IF(INDEX(Processos!$H$10:$H$509,MATCH((ROW()-9+($J$8-1)*50),Processos!$AJ$10:$AJ$509,0))&" × "&INDEX(Processos!$I$10:$I$509,MATCH((ROW()-9+($J$8-1)*50),Processos!$AJ$10:$AJ$509,0))="","",INDEX(Processos!$H$10:$H$509,MATCH((ROW()-9+($J$8-1)*50),Processos!$AJ$10:$AJ$509,0))&" × "&INDEX(Processos!$I$10:$I$509,MATCH((ROW()-9+($J$8-1)*50),Processos!$AJ$10:$AJ$509,0)))),190)&" [...]",IF((ROW()-9+($J$8-1)*50)>COUNTIFS(Processos!$X$10:$X$509,1,Processos!$Y$10:$Y$509,1),"",IF(INDEX(Processos!$H$10:$H$509,MATCH((ROW()-9+($J$8-1)*50),Processos!$AJ$10:$AJ$509,0))&" × "&INDEX(Processos!$I$10:$I$509,MATCH((ROW()-9+($J$8-1)*50),Processos!$AJ$10:$AJ$509,0))="","",INDEX(Processos!$H$10:$H$509,MATCH((ROW()-9+($J$8-1)*50),Processos!$AJ$10:$AJ$509,0))&" × "&INDEX(Processos!$I$10:$I$509,MATCH((ROW()-9+($J$8-1)*50),Processos!$AJ$10:$AJ$509,0))))),CHAR(10)," "),CHAR(13)," ")) | D29: =SUBSTITUTE(SUBSTITUTE(IF(LEN(IF((ROW()-9+($J$8-1)*50)>COUNTIFS(Processos!$X$10:$X$509,1,Processos!$Y$10:$Y$509,1),"",IF(INDEX(Processos!$M$10:$M$509,MATCH((ROW()-9+($J$8-1)*50),Processos!$AJ$10:$AJ$509,0))="","",INDEX(Processos!$M$10:$M$509,MATCH((ROW()-9+($J$8-1)*50),Processos!$AJ$10:$AJ$509,0)))))>190,LEFT(IF((ROW()-9+($J$8-1)*50)>COUNTIFS(Processos!$X$10:$X$509,1,Processos!$Y$10:$Y$509,1),"",IF(INDEX(Processos!$M$10:$M$509,MATCH((ROW()-9+($J$8-1)*50),Processos!$AJ$10:$AJ$509,0))="","",INDEX(Processos!$M$10:$M$509,MATCH((ROW()-9+($J$8-1)*50),Processos!$AJ$10:$AJ$509,0)))),190)&" [...]",IF((ROW()-9+($J$8-1)*50)>COUNTIFS(Processos!$X$10:$X$509,1,Processos!$Y$10:$Y$509,1),"",IF(INDEX(Processos!$M$10:$M$509,MATCH((ROW()-9+($J$8-1)*50),Processos!$AJ$10:$AJ$509,0))="","",INDEX(Processos!$M$10:$M$509,MATCH((ROW()-9+($J$8-1)*50),Processos!$AJ$10:$AJ$509,0))))),CHAR(10)," "),CHAR(13)," ") | E29: =IF($A29="","",IFERROR(INDEX(Processos!$AR$10:$AR$509,MATCH($A29,Processos!$A$10:$A$509,0)),"")&CHAR(10)&IFERROR(IF(OR(INDEX(Origem!$AB$10:$AB$509,MATCH($A29,Origem!$A$10:$A$509,0))="",INDEX(Origem!$AB$10:$AB$509,MATCH($A29,Origem!$A$10:$A$509,0))="—"),"Origem: sem classificação","Origem: "&INDEX(Origem!$AB$10:$AB$509,MATCH($A29,Origem!$A$10:$A$509,0))&IF(INDEX(Origem!$AC$10:$AC$509,MATCH($A29,Origem!$A$10:$A$509,0))=""," (sem pontuação)"," • "&INDEX(Origem!$AC$10:$AC$509,MATCH($A29,Origem!$A$10:$A$509,0))&" pontos")),"Origem: sem classificação")) | F29: =IF((ROW()-9+($J$8-1)*50)>COUNTIFS(Processos!$X$10:$X$509,1,Processos!$Y$10:$Y$509,1),"",IF(INDEX(Processos!$AQ$10:$AQ$509,MATCH((ROW()-9+($J$8-1)*50),Processos!$AJ$10:$AJ$509,0))="","",INDEX(Processos!$AQ$10:$AQ$509,MATCH((ROW()-9+($J$8-1)*50),Processos!$AJ$10:$AJ$509,0)))) | G29: =IF((ROW()-9+($J$8-1)*50)>COUNTIFS(Processos!$X$10:$X$509,1,Processos!$Y$10:$Y$509,1),"",IFERROR(HYPERLINK("#'Ficha'!C6","Selecionar na Ficha"),"Selecionar na Ficha"))
A30: =IF((ROW()-9+($J$8-1)*50)>COUNTIFS(Processos!$X$10:$X$509,1,Processos!$Y$10:$Y$509,1),"",IF(INDEX(Processos!$A$10:$A$509,MATCH((ROW()-9+($J$8-1)*50),Processos!$AJ$10:$AJ$509,0))="","",INDEX(Processos!$A$10:$A$509,MATCH((ROW()-9+($J$8-1)*50),Processos!$AJ$10:$AJ$509,0)))) | B30: =IF((ROW()-9+($J$8-1)*50)>COUNTIFS(Processos!$X$10:$X$509,1,Processos!$Y$10:$Y$509,1),"",IF(INDEX(Processos!$D$10:$D$509,MATCH((ROW()-9+($J$8-1)*50),Processos!$AJ$10:$AJ$509,0))="","",INDEX(Processos!$D$10:$D$509,MATCH((ROW()-9+($J$8-1)*50),Processos!$AJ$10:$AJ$509,0)))) | C30: =IF(LEN(SUBSTITUTE(SUBSTITUTE(IF((ROW()-9+($J$8-1)*50)>COUNTIFS(Processos!$X$10:$X$509,1,Processos!$Y$10:$Y$509,1),"",IF(INDEX(Processos!$H$10:$H$509,MATCH((ROW()-9+($J$8-1)*50),Processos!$AJ$10:$AJ$509,0))&" × "&INDEX(Processos!$I$10:$I$509,MATCH((ROW()-9+($J$8-1)*50),Processos!$AJ$10:$AJ$509,0))="","",INDEX(Processos!$H$10:$H$509,MATCH((ROW()-9+($J$8-1)*50),Processos!$AJ$10:$AJ$509,0))&" × "&INDEX(Processos!$I$10:$I$509,MATCH((ROW()-9+($J$8-1)*50),Processos!$AJ$10:$AJ$509,0)))),CHAR(10)," "),CHAR(13)," "))>150,LEFT(SUBSTITUTE(SUBSTITUTE(IF((ROW()-9+($J$8-1)*50)>COUNTIFS(Processos!$X$10:$X$509,1,Processos!$Y$10:$Y$509,1),"",IF(INDEX(Processos!$H$10:$H$509,MATCH((ROW()-9+($J$8-1)*50),Processos!$AJ$10:$AJ$509,0))&" × "&INDEX(Processos!$I$10:$I$509,MATCH((ROW()-9+($J$8-1)*50),Processos!$AJ$10:$AJ$509,0))="","",INDEX(Processos!$H$10:$H$509,MATCH((ROW()-9+($J$8-1)*50),Processos!$AJ$10:$AJ$509,0))&" × "&INDEX(Processos!$I$10:$I$509,MATCH((ROW()-9+($J$8-1)*50),Processos!$AJ$10:$AJ$509,0)))),CHAR(10)," "),CHAR(13)," "),150)&" [...]",SUBSTITUTE(SUBSTITUTE(IF((ROW()-9+($J$8-1)*50)>COUNTIFS(Processos!$X$10:$X$509,1,Processos!$Y$10:$Y$509,1),"",IF(INDEX(Processos!$H$10:$H$509,MATCH((ROW()-9+($J$8-1)*50),Processos!$AJ$10:$AJ$509,0))&" × "&INDEX(Processos!$I$10:$I$509,MATCH((ROW()-9+($J$8-1)*50),Processos!$AJ$10:$AJ$509,0))="","",INDEX(Processos!$H$10:$H$509,MATCH((ROW()-9+($J$8-1)*50),Processos!$AJ$10:$AJ$509,0))&" × "&INDEX(Processos!$I$10:$I$509,MATCH((ROW()-9+($J$8-1)*50),Processos!$AJ$10:$AJ$509,0)))),CHAR(10)," "),CHAR(13)," ")) | D30: =SUBSTITUTE(SUBSTITUTE(IF((ROW()-9+($J$8-1)*50)>COUNTIFS(Processos!$X$10:$X$509,1,Processos!$Y$10:$Y$509,1),"",IF(INDEX(Processos!$M$10:$M$509,MATCH((ROW()-9+($J$8-1)*50),Processos!$AJ$10:$AJ$509,0))="","",INDEX(Processos!$M$10:$M$509,MATCH((ROW()-9+($J$8-1)*50),Processos!$AJ$10:$AJ$509,0)))),CHAR(10)," "),CHAR(13)," ") | E30: =IF($A30="","",IFERROR(INDEX(Processos!$AR$10:$AR$509,MATCH($A30,Processos!$A$10:$A$509,0)),"")&CHAR(10)&IFERROR(IF(OR(INDEX(Origem!$AB$10:$AB$509,MATCH($A30,Origem!$A$10:$A$509,0))="",INDEX(Origem!$AB$10:$AB$509,MATCH($A30,Origem!$A$10:$A$509,0))="—"),"Origem: sem classificação","Origem: "&INDEX(Origem!$AB$10:$AB$509,MATCH($A30,Origem!$A$10:$A$509,0))&IF(INDEX(Origem!$AC$10:$AC$509,MATCH($A30,Origem!$A$10:$A$509,0))=""," (sem pontuação)"," • "&INDEX(Origem!$AC$10:$AC$509,MATCH($A30,Origem!$A$10:$A$509,0))&" pontos")),"Origem: sem classificação")) | F30: =IF((ROW()-9+($J$8-1)*50)>COUNTIFS(Processos!$X$10:$X$509,1,Processos!$Y$10:$Y$509,1),"",IF(INDEX(Processos!$AQ$10:$AQ$509,MATCH((ROW()-9+($J$8-1)*50),Processos!$AJ$10:$AJ$509,0))="","",INDEX(Processos!$AQ$10:$AQ$509,MATCH((ROW()-9+($J$8-1)*50),Processos!$AJ$10:$AJ$509,0)))) | G30: =IF((ROW()-9+($J$8-1)*50)>COUNTIFS(Processos!$X$10:$X$509,1,Processos!$Y$10:$Y$509,1),"",IFERROR(HYPERLINK("#'Ficha'!C6","Selecionar na Ficha"),"Selecionar na Ficha"))
A31: =IF((ROW()-9+($J$8-1)*50)>COUNTIFS(Processos!$X$10:$X$509,1,Processos!$Y$10:$Y$509,1),"",IF(INDEX(Processos!$A$10:$A$509,MATCH((ROW()-9+($J$8-1)*50),Processos!$AJ$10:$AJ$509,0))="","",INDEX(Processos!$A$10:$A$509,MATCH((ROW()-9+($J$8-1)*50),Processos!$AJ$10:$AJ$509,0)))) | B31: =IF((ROW()-9+($J$8-1)*50)>COUNTIFS(Processos!$X$10:$X$509,1,Processos!$Y$10:$Y$509,1),"",IF(INDEX(Processos!$D$10:$D$509,MATCH((ROW()-9+($J$8-1)*50),Processos!$AJ$10:$AJ$509,0))="","",INDEX(Processos!$D$10:$D$509,MATCH((ROW()-9+($J$8-1)*50),Processos!$AJ$10:$AJ$509,0)))) | C31: =IF(LEN(SUBSTITUTE(SUBSTITUTE(IF((ROW()-9+($J$8-1)*50)>COUNTIFS(Processos!$X$10:$X$509,1,Processos!$Y$10:$Y$509,1),"",IF(INDEX(Processos!$H$10:$H$509,MATCH((ROW()-9+($J$8-1)*50),Processos!$AJ$10:$AJ$509,0))&" × "&INDEX(Processos!$I$10:$I$509,MATCH((ROW()-9+($J$8-1)*50),Processos!$AJ$10:$AJ$509,0))="","",INDEX(Processos!$H$10:$H$509,MATCH((ROW()-9+($J$8-1)*50),Processos!$AJ$10:$AJ$509,0))&" × "&INDEX(Processos!$I$10:$I$509,MATCH((ROW()-9+($J$8-1)*50),Processos!$AJ$10:$AJ$509,0)))),CHAR(10)," "),CHAR(13)," "))>150,LEFT(SUBSTITUTE(SUBSTITUTE(IF((ROW()-9+($J$8-1)*50)>COUNTIFS(Processos!$X$10:$X$509,1,Processos!$Y$10:$Y$509,1),"",IF(INDEX(Processos!$H$10:$H$509,MATCH((ROW()-9+($J$8-1)*50),Processos!$AJ$10:$AJ$509,0))&" × "&INDEX(Processos!$I$10:$I$509,MATCH((ROW()-9+($J$8-1)*50),Processos!$AJ$10:$AJ$509,0))="","",INDEX(Processos!$H$10:$H$509,MATCH((ROW()-9+($J$8-1)*50),Processos!$AJ$10:$AJ$509,0))&" × "&INDEX(Processos!$I$10:$I$509,MATCH((ROW()-9+($J$8-1)*50),Processos!$AJ$10:$AJ$509,0)))),CHAR(10)," "),CHAR(13)," "),150)&" [...]",SUBSTITUTE(SUBSTITUTE(IF((ROW()-9+($J$8-1)*50)>COUNTIFS(Processos!$X$10:$X$509,1,Processos!$Y$10:$Y$509,1),"",IF(INDEX(Processos!$H$10:$H$509,MATCH((ROW()-9+($J$8-1)*50),Processos!$AJ$10:$AJ$509,0))&" × "&INDEX(Processos!$I$10:$I$509,MATCH((ROW()-9+($J$8-1)*50),Processos!$AJ$10:$AJ$509,0))="","",INDEX(Processos!$H$10:$H$509,MATCH((ROW()-9+($J$8-1)*50),Processos!$AJ$10:$AJ$509,0))&" × "&INDEX(Processos!$I$10:$I$509,MATCH((ROW()-9+($J$8-1)*50),Processos!$AJ$10:$AJ$509,0)))),CHAR(10)," "),CHAR(13)," ")) | D31: =SUBSTITUTE(SUBSTITUTE(IF((ROW()-9+($J$8-1)*50)>COUNTIFS(Processos!$X$10:$X$509,1,Processos!$Y$10:$Y$509,1),"",IF(INDEX(Processos!$M$10:$M$509,MATCH((ROW()-9+($J$8-1)*50),Processos!$AJ$10:$AJ$509,0))="","",INDEX(Processos!$M$10:$M$509,MATCH((ROW()-9+($J$8-1)*50),Processos!$AJ$10:$AJ$509,0)))),CHAR(10)," "),CHAR(13)," ") | E31: =IF($A31="","",IFERROR(INDEX(Processos!$AR$10:$AR$509,MATCH($A31,Processos!$A$10:$A$509,0)),"")&CHAR(10)&IFERROR(IF(OR(INDEX(Origem!$AB$10:$AB$509,MATCH($A31,Origem!$A$10:$A$509,0))="",INDEX(Origem!$AB$10:$AB$509,MATCH($A31,Origem!$A$10:$A$509,0))="—"),"Origem: sem classificação","Origem: "&INDEX(Origem!$AB$10:$AB$509,MATCH($A31,Origem!$A$10:$A$509,0))&IF(INDEX(Origem!$AC$10:$AC$509,MATCH($A31,Origem!$A$10:$A$509,0))=""," (sem pontuação)"," • "&INDEX(Origem!$AC$10:$AC$509,MATCH($A31,Origem!$A$10:$A$509,0))&" pontos")),"Origem: sem classificação")) | F31: =IF((ROW()-9+($J$8-1)*50)>COUNTIFS(Processos!$X$10:$X$509,1,Processos!$Y$10:$Y$509,1),"",IF(INDEX(Processos!$AQ$10:$AQ$509,MATCH((ROW()-9+($J$8-1)*50),Processos!$AJ$10:$AJ$509,0))="","",INDEX(Processos!$AQ$10:$AQ$509,MATCH((ROW()-9+($J$8-1)*50),Processos!$AJ$10:$AJ$509,0)))) | G31: =IF((ROW()-9+($J$8-1)*50)>COUNTIFS(Processos!$X$10:$X$509,1,Processos!$Y$10:$Y$509,1),"",IFERROR(HYPERLINK("#'Ficha'!C6","Selecionar na Ficha"),"Selecionar na Ficha"))
A32: =IF((ROW()-9+($J$8-1)*50)>COUNTIFS(Processos!$X$10:$X$509,1,Processos!$Y$10:$Y$509,1),"",IF(INDEX(Processos!$A$10:$A$509,MATCH((ROW()-9+($J$8-1)*50),Processos!$AJ$10:$AJ$509,0))="","",INDEX(Processos!$A$10:$A$509,MATCH((ROW()-9+($J$8-1)*50),Processos!$AJ$10:$AJ$509,0)))) | B32: =IF((ROW()-9+($J$8-1)*50)>COUNTIFS(Processos!$X$10:$X$509,1,Processos!$Y$10:$Y$509,1),"",IF(INDEX(Processos!$D$10:$D$509,MATCH((ROW()-9+($J$8-1)*50),Processos!$AJ$10:$AJ$509,0))="","",INDEX(Processos!$D$10:$D$509,MATCH((ROW()-9+($J$8-1)*50),Processos!$AJ$10:$AJ$509,0)))) | C32: =IF(LEN(SUBSTITUTE(SUBSTITUTE(IF((ROW()-9+($J$8-1)*50)>COUNTIFS(Processos!$X$10:$X$509,1,Processos!$Y$10:$Y$509,1),"",IF(INDEX(Processos!$H$10:$H$509,MATCH((ROW()-9+($J$8-1)*50),Processos!$AJ$10:$AJ$509,0))&" × "&INDEX(Processos!$I$10:$I$509,MATCH((ROW()-9+($J$8-1)*50),Processos!$AJ$10:$AJ$509,0))="","",INDEX(Processos!$H$10:$H$509,MATCH((ROW()-9+($J$8-1)*50),Processos!$AJ$10:$AJ$509,0))&" × "&INDEX(Processos!$I$10:$I$509,MATCH((ROW()-9+($J$8-1)*50),Processos!$AJ$10:$AJ$509,0)))),CHAR(10)," "),CHAR(13)," "))>150,LEFT(SUBSTITUTE(SUBSTITUTE(IF((ROW()-9+($J$8-1)*50)>COUNTIFS(Processos!$X$10:$X$509,1,Processos!$Y$10:$Y$509,1),"",IF(INDEX(Processos!$H$10:$H$509,MATCH((ROW()-9+($J$8-1)*50),Processos!$AJ$10:$AJ$509,0))&" × "&INDEX(Processos!$I$10:$I$509,MATCH((ROW()-9+($J$8-1)*50),Processos!$AJ$10:$AJ$509,0))="","",INDEX(Processos!$H$10:$H$509,MATCH((ROW()-9+($J$8-1)*50),Processos!$AJ$10:$AJ$509,0))&" × "&INDEX(Processos!$I$10:$I$509,MATCH((ROW()-9+($J$8-1)*50),Processos!$AJ$10:$AJ$509,0)))),CHAR(10)," "),CHAR(13)," "),150)&" [...]",SUBSTITUTE(SUBSTITUTE(IF((ROW()-9+($J$8-1)*50)>COUNTIFS(Processos!$X$10:$X$509,1,Processos!$Y$10:$Y$509,1),"",IF(INDEX(Processos!$H$10:$H$509,MATCH((ROW()-9+($J$8-1)*50),Processos!$AJ$10:$AJ$509,0))&" × "&INDEX(Processos!$I$10:$I$509,MATCH((ROW()-9+($J$8-1)*50),Processos!$AJ$10:$AJ$509,0))="","",INDEX(Processos!$H$10:$H$509,MATCH((ROW()-9+($J$8-1)*50),Processos!$AJ$10:$AJ$509,0))&" × "&INDEX(Processos!$I$10:$I$509,MATCH((ROW()-9+($J$8-1)*50),Processos!$AJ$10:$AJ$509,0)))),CHAR(10)," "),CHAR(13)," ")) | D32: =SUBSTITUTE(SUBSTITUTE(IF((ROW()-9+($J$8-1)*50)>COUNTIFS(Processos!$X$10:$X$509,1,Processos!$Y$10:$Y$509,1),"",IF(INDEX(Processos!$M$10:$M$509,MATCH((ROW()-9+($J$8-1)*50),Processos!$AJ$10:$AJ$509,0))="","",INDEX(Processos!$M$10:$M$509,MATCH((ROW()-9+($J$8-1)*50),Processos!$AJ$10:$AJ$509,0)))),CHAR(10)," "),CHAR(13)," ") | E32: =IF($A32="","",IFERROR(INDEX(Processos!$AR$10:$AR$509,MATCH($A32,Processos!$A$10:$A$509,0)),"")&CHAR(10)&IFERROR(IF(OR(INDEX(Origem!$AB$10:$AB$509,MATCH($A32,Origem!$A$10:$A$509,0))="",INDEX(Origem!$AB$10:$AB$509,MATCH($A32,Origem!$A$10:$A$509,0))="—"),"Origem: sem classificação","Origem: "&INDEX(Origem!$AB$10:$AB$509,MATCH($A32,Origem!$A$10:$A$509,0))&IF(INDEX(Origem!$AC$10:$AC$509,MATCH($A32,Origem!$A$10:$A$509,0))=""," (sem pontuação)"," • "&INDEX(Origem!$AC$10:$AC$509,MATCH($A32,Origem!$A$10:$A$509,0))&" pontos")),"Origem: sem classificação")) | F32: =IF((ROW()-9+($J$8-1)*50)>COUNTIFS(Processos!$X$10:$X$509,1,Processos!$Y$10:$Y$509,1),"",IF(INDEX(Processos!$AQ$10:$AQ$509,MATCH((ROW()-9+($J$8-1)*50),Processos!$AJ$10:$AJ$509,0))="","",INDEX(Processos!$AQ$10:$AQ$509,MATCH((ROW()-9+($J$8-1)*50),Processos!$AJ$10:$AJ$509,0)))) | G32: =IF((ROW()-9+($J$8-1)*50)>COUNTIFS(Processos!$X$10:$X$509,1,Processos!$Y$10:$Y$509,1),"",IFERROR(HYPERLINK("#'Ficha'!C6","Selecionar na Ficha"),"Selecionar na Ficha"))
A33: =IF((ROW()-9+($J$8-1)*50)>COUNTIFS(Processos!$X$10:$X$509,1,Processos!$Y$10:$Y$509,1),"",IF(INDEX(Processos!$A$10:$A$509,MATCH((ROW()-9+($J$8-1)*50),Processos!$AJ$10:$AJ$509,0))="","",INDEX(Processos!$A$10:$A$509,MATCH((ROW()-9+($J$8-1)*50),Processos!$AJ$10:$AJ$509,0)))) | B33: =IF((ROW()-9+($J$8-1)*50)>COUNTIFS(Processos!$X$10:$X$509,1,Processos!$Y$10:$Y$509,1),"",IF(INDEX(Processos!$D$10:$D$509,MATCH((ROW()-9+($J$8-1)*50),Processos!$AJ$10:$AJ$509,0))="","",INDEX(Processos!$D$10:$D$509,MATCH((ROW()-9+($J$8-1)*50),Processos!$AJ$10:$AJ$509,0)))) | C33: =IF(LEN(SUBSTITUTE(SUBSTITUTE(IF((ROW()-9+($J$8-1)*50)>COUNTIFS(Processos!$X$10:$X$509,1,Processos!$Y$10:$Y$509,1),"",IF(INDEX(Processos!$H$10:$H$509,MATCH((ROW()-9+($J$8-1)*50),Processos!$AJ$10:$AJ$509,0))&" × "&INDEX(Processos!$I$10:$I$509,MATCH((ROW()-9+($J$8-1)*50),Processos!$AJ$10:$AJ$509,0))="","",INDEX(Processos!$H$10:$H$509,MATCH((ROW()-9+($J$8-1)*50),Processos!$AJ$10:$AJ$509,0))&" × "&INDEX(Processos!$I$10:$I$509,MATCH((ROW()-9+($J$8-1)*50),Processos!$AJ$10:$AJ$509,0)))),CHAR(10)," "),CHAR(13)," "))>150,LEFT(SUBSTITUTE(SUBSTITUTE(IF((ROW()-9+($J$8-1)*50)>COUNTIFS(Processos!$X$10:$X$509,1,Processos!$Y$10:$Y$509,1),"",IF(INDEX(Processos!$H$10:$H$509,MATCH((ROW()-9+($J$8-1)*50),Processos!$AJ$10:$AJ$509,0))&" × "&INDEX(Processos!$I$10:$I$509,MATCH((ROW()-9+($J$8-1)*50),Processos!$AJ$10:$AJ$509,0))="","",INDEX(Processos!$H$10:$H$509,MATCH((ROW()-9+($J$8-1)*50),Processos!$AJ$10:$AJ$509,0))&" × "&INDEX(Processos!$I$10:$I$509,MATCH((ROW()-9+($J$8-1)*50),Processos!$AJ$10:$AJ$509,0)))),CHAR(10)," "),CHAR(13)," "),150)&" [...]",SUBSTITUTE(SUBSTITUTE(IF((ROW()-9+($J$8-1)*50)>COUNTIFS(Processos!$X$10:$X$509,1,Processos!$Y$10:$Y$509,1),"",IF(INDEX(Processos!$H$10:$H$509,MATCH((ROW()-9+($J$8-1)*50),Processos!$AJ$10:$AJ$509,0))&" × "&INDEX(Processos!$I$10:$I$509,MATCH((ROW()-9+($J$8-1)*50),Processos!$AJ$10:$AJ$509,0))="","",INDEX(Processos!$H$10:$H$509,MATCH((ROW()-9+($J$8-1)*50),Processos!$AJ$10:$AJ$509,0))&" × "&INDEX(Processos!$I$10:$I$509,MATCH((ROW()-9+($J$8-1)*50),Processos!$AJ$10:$AJ$509,0)))),CHAR(10)," "),CHAR(13)," ")) | D33: =SUBSTITUTE(SUBSTITUTE(IF((ROW()-9+($J$8-1)*50)>COUNTIFS(Processos!$X$10:$X$509,1,Processos!$Y$10:$Y$509,1),"",IF(INDEX(Processos!$M$10:$M$509,MATCH((ROW()-9+($J$8-1)*50),Processos!$AJ$10:$AJ$509,0))="","",INDEX(Processos!$M$10:$M$509,MATCH((ROW()-9+($J$8-1)*50),Processos!$AJ$10:$AJ$509,0)))),CHAR(10)," "),CHAR(13)," ") | E33: =IF($A33="","",IFERROR(INDEX(Processos!$AR$10:$AR$509,MATCH($A33,Processos!$A$10:$A$509,0)),"")&CHAR(10)&IFERROR(IF(OR(INDEX(Origem!$AB$10:$AB$509,MATCH($A33,Origem!$A$10:$A$509,0))="",INDEX(Origem!$AB$10:$AB$509,MATCH($A33,Origem!$A$10:$A$509,0))="—"),"Origem: sem classificação","Origem: "&INDEX(Origem!$AB$10:$AB$509,MATCH($A33,Origem!$A$10:$A$509,0))&IF(INDEX(Origem!$AC$10:$AC$509,MATCH($A33,Origem!$A$10:$A$509,0))=""," (sem pontuação)"," • "&INDEX(Origem!$AC$10:$AC$509,MATCH($A33,Origem!$A$10:$A$509,0))&" pontos")),"Origem: sem classificação")) | F33: =IF((ROW()-9+($J$8-1)*50)>COUNTIFS(Processos!$X$10:$X$509,1,Processos!$Y$10:$Y$509,1),"",IF(INDEX(Processos!$AQ$10:$AQ$509,MATCH((ROW()-9+($J$8-1)*50),Processos!$AJ$10:$AJ$509,0))="","",INDEX(Processos!$AQ$10:$AQ$509,MATCH((ROW()-9+($J$8-1)*50),Processos!$AJ$10:$AJ$509,0)))) | G33: =IF((ROW()-9+($J$8-1)*50)>COUNTIFS(Processos!$X$10:$X$509,1,Processos!$Y$10:$Y$509,1),"",IFERROR(HYPERLINK("#'Ficha'!C6","Selecionar na Ficha"),"Selecionar na Ficha"))
A34: =IF((ROW()-9+($J$8-1)*50)>COUNTIFS(Processos!$X$10:$X$509,1,Processos!$Y$10:$Y$509,1),"",IF(INDEX(Processos!$A$10:$A$509,MATCH((ROW()-9+($J$8-1)*50),Processos!$AJ$10:$AJ$509,0))="","",INDEX(Processos!$A$10:$A$509,MATCH((ROW()-9+($J$8-1)*50),Processos!$AJ$10:$AJ$509,0)))) | B34: =IF((ROW()-9+($J$8-1)*50)>COUNTIFS(Processos!$X$10:$X$509,1,Processos!$Y$10:$Y$509,1),"",IF(INDEX(Processos!$D$10:$D$509,MATCH((ROW()-9+($J$8-1)*50),Processos!$AJ$10:$AJ$509,0))="","",INDEX(Processos!$D$10:$D$509,MATCH((ROW()-9+($J$8-1)*50),Processos!$AJ$10:$AJ$509,0)))) | C34: =IF(LEN(SUBSTITUTE(SUBSTITUTE(IF((ROW()-9+($J$8-1)*50)>COUNTIFS(Processos!$X$10:$X$509,1,Processos!$Y$10:$Y$509,1),"",IF(INDEX(Processos!$H$10:$H$509,MATCH((ROW()-9+($J$8-1)*50),Processos!$AJ$10:$AJ$509,0))&" × "&INDEX(Processos!$I$10:$I$509,MATCH((ROW()-9+($J$8-1)*50),Processos!$AJ$10:$AJ$509,0))="","",INDEX(Processos!$H$10:$H$509,MATCH((ROW()-9+($J$8-1)*50),Processos!$AJ$10:$AJ$509,0))&" × "&INDEX(Processos!$I$10:$I$509,MATCH((ROW()-9+($J$8-1)*50),Processos!$AJ$10:$AJ$509,0)))),CHAR(10)," "),CHAR(13)," "))>150,LEFT(SUBSTITUTE(SUBSTITUTE(IF((ROW()-9+($J$8-1)*50)>COUNTIFS(Processos!$X$10:$X$509,1,Processos!$Y$10:$Y$509,1),"",IF(INDEX(Processos!$H$10:$H$509,MATCH((ROW()-9+($J$8-1)*50),Processos!$AJ$10:$AJ$509,0))&" × "&INDEX(Processos!$I$10:$I$509,MATCH((ROW()-9+($J$8-1)*50),Processos!$AJ$10:$AJ$509,0))="","",INDEX(Processos!$H$10:$H$509,MATCH((ROW()-9+($J$8-1)*50),Processos!$AJ$10:$AJ$509,0))&" × "&INDEX(Processos!$I$10:$I$509,MATCH((ROW()-9+($J$8-1)*50),Processos!$AJ$10:$AJ$509,0)))),CHAR(10)," "),CHAR(13)," "),150)&" [...]",SUBSTITUTE(SUBSTITUTE(IF((ROW()-9+($J$8-1)*50)>COUNTIFS(Processos!$X$10:$X$509,1,Processos!$Y$10:$Y$509,1),"",IF(INDEX(Processos!$H$10:$H$509,MATCH((ROW()-9+($J$8-1)*50),Processos!$AJ$10:$AJ$509,0))&" × "&INDEX(Processos!$I$10:$I$509,MATCH((ROW()-9+($J$8-1)*50),Processos!$AJ$10:$AJ$509,0))="","",INDEX(Processos!$H$10:$H$509,MATCH((ROW()-9+($J$8-1)*50),Processos!$AJ$10:$AJ$509,0))&" × "&INDEX(Processos!$I$10:$I$509,MATCH((ROW()-9+($J$8-1)*50),Processos!$AJ$10:$AJ$509,0)))),CHAR(10)," "),CHAR(13)," ")) | D34: =SUBSTITUTE(SUBSTITUTE(IF((ROW()-9+($J$8-1)*50)>COUNTIFS(Processos!$X$10:$X$509,1,Processos!$Y$10:$Y$509,1),"",IF(INDEX(Processos!$M$10:$M$509,MATCH((ROW()-9+($J$8-1)*50),Processos!$AJ$10:$AJ$509,0))="","",INDEX(Processos!$M$10:$M$509,MATCH((ROW()-9+($J$8-1)*50),Processos!$AJ$10:$AJ$509,0)))),CHAR(10)," "),CHAR(13)," ") | E34: =IF($A34="","",IFERROR(INDEX(Processos!$AR$10:$AR$509,MATCH($A34,Processos!$A$10:$A$509,0)),"")&CHAR(10)&IFERROR(IF(OR(INDEX(Origem!$AB$10:$AB$509,MATCH($A34,Origem!$A$10:$A$509,0))="",INDEX(Origem!$AB$10:$AB$509,MATCH($A34,Origem!$A$10:$A$509,0))="—"),"Origem: sem classificação","Origem: "&INDEX(Origem!$AB$10:$AB$509,MATCH($A34,Origem!$A$10:$A$509,0))&IF(INDEX(Origem!$AC$10:$AC$509,MATCH($A34,Origem!$A$10:$A$509,0))=""," (sem pontuação)"," • "&INDEX(Origem!$AC$10:$AC$509,MATCH($A34,Origem!$A$10:$A$509,0))&" pontos")),"Origem: sem classificação")) | F34: =IF((ROW()-9+($J$8-1)*50)>COUNTIFS(Processos!$X$10:$X$509,1,Processos!$Y$10:$Y$509,1),"",IF(INDEX(Processos!$AQ$10:$AQ$509,MATCH((ROW()-9+($J$8-1)*50),Processos!$AJ$10:$AJ$509,0))="","",INDEX(Processos!$AQ$10:$AQ$509,MATCH((ROW()-9+($J$8-1)*50),Processos!$AJ$10:$AJ$509,0)))) | G34: =IF((ROW()-9+($J$8-1)*50)>COUNTIFS(Processos!$X$10:$X$509,1,Processos!$Y$10:$Y$509,1),"",IFERROR(HYPERLINK("#'Ficha'!C6","Selecionar na Ficha"),"Selecionar na Ficha"))
A35: =IF((ROW()-9+($J$8-1)*50)>COUNTIFS(Processos!$X$10:$X$509,1,Processos!$Y$10:$Y$509,1),"",IF(INDEX(Processos!$A$10:$A$509,MATCH((ROW()-9+($J$8-1)*50),Processos!$AJ$10:$AJ$509,0))="","",INDEX(Processos!$A$10:$A$509,MATCH((ROW()-9+($J$8-1)*50),Processos!$AJ$10:$AJ$509,0)))) | B35: =IF((ROW()-9+($J$8-1)*50)>COUNTIFS(Processos!$X$10:$X$509,1,Processos!$Y$10:$Y$509,1),"",IF(INDEX(Processos!$D$10:$D$509,MATCH((ROW()-9+($J$8-1)*50),Processos!$AJ$10:$AJ$509,0))="","",INDEX(Processos!$D$10:$D$509,MATCH((ROW()-9+($J$8-1)*50),Processos!$AJ$10:$AJ$509,0)))) | C35: =IF(LEN(SUBSTITUTE(SUBSTITUTE(IF((ROW()-9+($J$8-1)*50)>COUNTIFS(Processos!$X$10:$X$509,1,Processos!$Y$10:$Y$509,1),"",IF(INDEX(Processos!$H$10:$H$509,MATCH((ROW()-9+($J$8-1)*50),Processos!$AJ$10:$AJ$509,0))&" × "&INDEX(Processos!$I$10:$I$509,MATCH((ROW()-9+($J$8-1)*50),Processos!$AJ$10:$AJ$509,0))="","",INDEX(Processos!$H$10:$H$509,MATCH((ROW()-9+($J$8-1)*50),Processos!$AJ$10:$AJ$509,0))&" × "&INDEX(Processos!$I$10:$I$509,MATCH((ROW()-9+($J$8-1)*50),Processos!$AJ$10:$AJ$509,0)))),CHAR(10)," "),CHAR(13)," "))>150,LEFT(SUBSTITUTE(SUBSTITUTE(IF((ROW()-9+($J$8-1)*50)>COUNTIFS(Processos!$X$10:$X$509,1,Processos!$Y$10:$Y$509,1),"",IF(INDEX(Processos!$H$10:$H$509,MATCH((ROW()-9+($J$8-1)*50),Processos!$AJ$10:$AJ$509,0))&" × "&INDEX(Processos!$I$10:$I$509,MATCH((ROW()-9+($J$8-1)*50),Processos!$AJ$10:$AJ$509,0))="","",INDEX(Processos!$H$10:$H$509,MATCH((ROW()-9+($J$8-1)*50),Processos!$AJ$10:$AJ$509,0))&" × "&INDEX(Processos!$I$10:$I$509,MATCH((ROW()-9+($J$8-1)*50),Processos!$AJ$10:$AJ$509,0)))),CHAR(10)," "),CHAR(13)," "),150)&" [...]",SUBSTITUTE(SUBSTITUTE(IF((ROW()-9+($J$8-1)*50)>COUNTIFS(Processos!$X$10:$X$509,1,Processos!$Y$10:$Y$509,1),"",IF(INDEX(Processos!$H$10:$H$509,MATCH((ROW()-9+($J$8-1)*50),Processos!$AJ$10:$AJ$509,0))&" × "&INDEX(Processos!$I$10:$I$509,MATCH((ROW()-9+($J$8-1)*50),Processos!$AJ$10:$AJ$509,0))="","",INDEX(Processos!$H$10:$H$509,MATCH((ROW()-9+($J$8-1)*50),Processos!$AJ$10:$AJ$509,0))&" × "&INDEX(Processos!$I$10:$I$509,MATCH((ROW()-9+($J$8-1)*50),Processos!$AJ$10:$AJ$509,0)))),CHAR(10)," "),CHAR(13)," ")) | D35: =SUBSTITUTE(SUBSTITUTE(IF((ROW()-9+($J$8-1)*50)>COUNTIFS(Processos!$X$10:$X$509,1,Processos!$Y$10:$Y$509,1),"",IF(INDEX(Processos!$M$10:$M$509,MATCH((ROW()-9+($J$8-1)*50),Processos!$AJ$10:$AJ$509,0))="","",INDEX(Processos!$M$10:$M$509,MATCH((ROW()-9+($J$8-1)*50),Processos!$AJ$10:$AJ$509,0)))),CHAR(10)," "),CHAR(13)," ") | E35: =IF($A35="","",IFERROR(INDEX(Processos!$AR$10:$AR$509,MATCH($A35,Processos!$A$10:$A$509,0)),"")&CHAR(10)&IFERROR(IF(OR(INDEX(Origem!$AB$10:$AB$509,MATCH($A35,Origem!$A$10:$A$509,0))="",INDEX(Origem!$AB$10:$AB$509,MATCH($A35,Origem!$A$10:$A$509,0))="—"),"Origem: sem classificação","Origem: "&INDEX(Origem!$AB$10:$AB$509,MATCH($A35,Origem!$A$10:$A$509,0))&IF(INDEX(Origem!$AC$10:$AC$509,MATCH($A35,Origem!$A$10:$A$509,0))=""," (sem pontuação)"," • "&INDEX(Origem!$AC$10:$AC$509,MATCH($A35,Origem!$A$10:$A$509,0))&" pontos")),"Origem: sem classificação")) | F35: =IF((ROW()-9+($J$8-1)*50)>COUNTIFS(Processos!$X$10:$X$509,1,Processos!$Y$10:$Y$509,1),"",IF(INDEX(Processos!$AQ$10:$AQ$509,MATCH((ROW()-9+($J$8-1)*50),Processos!$AJ$10:$AJ$509,0))="","",INDEX(Processos!$AQ$10:$AQ$509,MATCH((ROW()-9+($J$8-1)*50),Processos!$AJ$10:$AJ$509,0)))) | G35: =IF((ROW()-9+($J$8-1)*50)>COUNTIFS(Processos!$X$10:$X$509,1,Processos!$Y$10:$Y$509,1),"",IFERROR(HYPERLINK("#'Ficha'!C6","Selecionar na Ficha"),"Selecionar na Ficha"))
A36: =IF((ROW()-9+($J$8-1)*50)>COUNTIFS(Processos!$X$10:$X$509,1,Processos!$Y$10:$Y$509,1),"",IF(INDEX(Processos!$A$10:$A$509,MATCH((ROW()-9+($J$8-1)*50),Processos!$AJ$10:$AJ$509,0))="","",INDEX(Processos!$A$10:$A$509,MATCH((ROW()-9+($J$8-1)*50),Processos!$AJ$10:$AJ$509,0)))) | B36: =IF((ROW()-9+($J$8-1)*50)>COUNTIFS(Processos!$X$10:$X$509,1,Processos!$Y$10:$Y$509,1),"",IF(INDEX(Processos!$D$10:$D$509,MATCH((ROW()-9+($J$8-1)*50),Processos!$AJ$10:$AJ$509,0))="","",INDEX(Processos!$D$10:$D$509,MATCH((ROW()-9+($J$8-1)*50),Processos!$AJ$10:$AJ$509,0)))) | C36: =IF(LEN(SUBSTITUTE(SUBSTITUTE(IF((ROW()-9+($J$8-1)*50)>COUNTIFS(Processos!$X$10:$X$509,1,Processos!$Y$10:$Y$509,1),"",IF(INDEX(Processos!$H$10:$H$509,MATCH((ROW()-9+($J$8-1)*50),Processos!$AJ$10:$AJ$509,0))&" × "&INDEX(Processos!$I$10:$I$509,MATCH((ROW()-9+($J$8-1)*50),Processos!$AJ$10:$AJ$509,0))="","",INDEX(Processos!$H$10:$H$509,MATCH((ROW()-9+($J$8-1)*50),Processos!$AJ$10:$AJ$509,0))&" × "&INDEX(Processos!$I$10:$I$509,MATCH((ROW()-9+($J$8-1)*50),Processos!$AJ$10:$AJ$509,0)))),CHAR(10)," "),CHAR(13)," "))>150,LEFT(SUBSTITUTE(SUBSTITUTE(IF((ROW()-9+($J$8-1)*50)>COUNTIFS(Processos!$X$10:$X$509,1,Processos!$Y$10:$Y$509,1),"",IF(INDEX(Processos!$H$10:$H$509,MATCH((ROW()-9+($J$8-1)*50),Processos!$AJ$10:$AJ$509,0))&" × "&INDEX(Processos!$I$10:$I$509,MATCH((ROW()-9+($J$8-1)*50),Processos!$AJ$10:$AJ$509,0))="","",INDEX(Processos!$H$10:$H$509,MATCH((ROW()-9+($J$8-1)*50),Processos!$AJ$10:$AJ$509,0))&" × "&INDEX(Processos!$I$10:$I$509,MATCH((ROW()-9+($J$8-1)*50),Processos!$AJ$10:$AJ$509,0)))),CHAR(10)," "),CHAR(13)," "),150)&" [...]",SUBSTITUTE(SUBSTITUTE(IF((ROW()-9+($J$8-1)*50)>COUNTIFS(Processos!$X$10:$X$509,1,Processos!$Y$10:$Y$509,1),"",IF(INDEX(Processos!$H$10:$H$509,MATCH((ROW()-9+($J$8-1)*50),Processos!$AJ$10:$AJ$509,0))&" × "&INDEX(Processos!$I$10:$I$509,MATCH((ROW()-9+($J$8-1)*50),Processos!$AJ$10:$AJ$509,0))="","",INDEX(Processos!$H$10:$H$509,MATCH((ROW()-9+($J$8-1)*50),Processos!$AJ$10:$AJ$509,0))&" × "&INDEX(Processos!$I$10:$I$509,MATCH((ROW()-9+($J$8-1)*50),Processos!$AJ$10:$AJ$509,0)))),CHAR(10)," "),CHAR(13)," ")) | D36: =SUBSTITUTE(SUBSTITUTE(IF((ROW()-9+($J$8-1)*50)>COUNTIFS(Processos!$X$10:$X$509,1,Processos!$Y$10:$Y$509,1),"",IF(INDEX(Processos!$M$10:$M$509,MATCH((ROW()-9+($J$8-1)*50),Processos!$AJ$10:$AJ$509,0))="","",INDEX(Processos!$M$10:$M$509,MATCH((ROW()-9+($J$8-1)*50),Processos!$AJ$10:$AJ$509,0)))),CHAR(10)," "),CHAR(13)," ") | E36: =IF($A36="","",IFERROR(INDEX(Processos!$AR$10:$AR$509,MATCH($A36,Processos!$A$10:$A$509,0)),"")&CHAR(10)&IFERROR(IF(OR(INDEX(Origem!$AB$10:$AB$509,MATCH($A36,Origem!$A$10:$A$509,0))="",INDEX(Origem!$AB$10:$AB$509,MATCH($A36,Origem!$A$10:$A$509,0))="—"),"Origem: sem classificação","Origem: "&INDEX(Origem!$AB$10:$AB$509,MATCH($A36,Origem!$A$10:$A$509,0))&IF(INDEX(Origem!$AC$10:$AC$509,MATCH($A36,Origem!$A$10:$A$509,0))=""," (sem pontuação)"," • "&INDEX(Origem!$AC$10:$AC$509,MATCH($A36,Origem!$A$10:$A$509,0))&" pontos")),"Origem: sem classificação")) | F36: =IF((ROW()-9+($J$8-1)*50)>COUNTIFS(Processos!$X$10:$X$509,1,Processos!$Y$10:$Y$509,1),"",IF(INDEX(Processos!$AQ$10:$AQ$509,MATCH((ROW()-9+($J$8-1)*50),Processos!$AJ$10:$AJ$509,0))="","",INDEX(Processos!$AQ$10:$AQ$509,MATCH((ROW()-9+($J$8-1)*50),Processos!$AJ$10:$AJ$509,0)))) | G36: =IF((ROW()-9+($J$8-1)*50)>COUNTIFS(Processos!$X$10:$X$509,1,Processos!$Y$10:$Y$509,1),"",IFERROR(HYPERLINK("#'Ficha'!C6","Selecionar na Ficha"),"Selecionar na Ficha"))
A37: =IF((ROW()-9+($J$8-1)*50)>COUNTIFS(Processos!$X$10:$X$509,1,Processos!$Y$10:$Y$509,1),"",IF(INDEX(Processos!$A$10:$A$509,MATCH((ROW()-9+($J$8-1)*50),Processos!$AJ$10:$AJ$509,0))="","",INDEX(Processos!$A$10:$A$509,MATCH((ROW()-9+($J$8-1)*50),Processos!$AJ$10:$AJ$509,0)))) | B37: =IF((ROW()-9+($J$8-1)*50)>COUNTIFS(Processos!$X$10:$X$509,1,Processos!$Y$10:$Y$509,1),"",IF(INDEX(Processos!$D$10:$D$509,MATCH((ROW()-9+($J$8-1)*50),Processos!$AJ$10:$AJ$509,0))="","",INDEX(Processos!$D$10:$D$509,MATCH((ROW()-9+($J$8-1)*50),Processos!$AJ$10:$AJ$509,0)))) | C37: =IF(LEN(SUBSTITUTE(SUBSTITUTE(IF((ROW()-9+($J$8-1)*50)>COUNTIFS(Processos!$X$10:$X$509,1,Processos!$Y$10:$Y$509,1),"",IF(INDEX(Processos!$H$10:$H$509,MATCH((ROW()-9+($J$8-1)*50),Processos!$AJ$10:$AJ$509,0))&" × "&INDEX(Processos!$I$10:$I$509,MATCH((ROW()-9+($J$8-1)*50),Processos!$AJ$10:$AJ$509,0))="","",INDEX(Processos!$H$10:$H$509,MATCH((ROW()-9+($J$8-1)*50),Processos!$AJ$10:$AJ$509,0))&" × "&INDEX(Processos!$I$10:$I$509,MATCH((ROW()-9+($J$8-1)*50),Processos!$AJ$10:$AJ$509,0)))),CHAR(10)," "),CHAR(13)," "))>150,LEFT(SUBSTITUTE(SUBSTITUTE(IF((ROW()-9+($J$8-1)*50)>COUNTIFS(Processos!$X$10:$X$509,1,Processos!$Y$10:$Y$509,1),"",IF(INDEX(Processos!$H$10:$H$509,MATCH((ROW()-9+($J$8-1)*50),Processos!$AJ$10:$AJ$509,0))&" × "&INDEX(Processos!$I$10:$I$509,MATCH((ROW()-9+($J$8-1)*50),Processos!$AJ$10:$AJ$509,0))="","",INDEX(Processos!$H$10:$H$509,MATCH((ROW()-9+($J$8-1)*50),Processos!$AJ$10:$AJ$509,0))&" × "&INDEX(Processos!$I$10:$I$509,MATCH((ROW()-9+($J$8-1)*50),Processos!$AJ$10:$AJ$509,0)))),CHAR(10)," "),CHAR(13)," "),150)&" [...]",SUBSTITUTE(SUBSTITUTE(IF((ROW()-9+($J$8-1)*50)>COUNTIFS(Processos!$X$10:$X$509,1,Processos!$Y$10:$Y$509,1),"",IF(INDEX(Processos!$H$10:$H$509,MATCH((ROW()-9+($J$8-1)*50),Processos!$AJ$10:$AJ$509,0))&" × "&INDEX(Processos!$I$10:$I$509,MATCH((ROW()-9+($J$8-1)*50),Processos!$AJ$10:$AJ$509,0))="","",INDEX(Processos!$H$10:$H$509,MATCH((ROW()-9+($J$8-1)*50),Processos!$AJ$10:$AJ$509,0))&" × "&INDEX(Processos!$I$10:$I$509,MATCH((ROW()-9+($J$8-1)*50),Processos!$AJ$10:$AJ$509,0)))),CHAR(10)," "),CHAR(13)," ")) | D37: =SUBSTITUTE(SUBSTITUTE(IF((ROW()-9+($J$8-1)*50)>COUNTIFS(Processos!$X$10:$X$509,1,Processos!$Y$10:$Y$509,1),"",IF(INDEX(Processos!$M$10:$M$509,MATCH((ROW()-9+($J$8-1)*50),Processos!$AJ$10:$AJ$509,0))="","",INDEX(Processos!$M$10:$M$509,MATCH((ROW()-9+($J$8-1)*50),Processos!$AJ$10:$AJ$509,0)))),CHAR(10)," "),CHAR(13)," ") | E37: =IF($A37="","",IFERROR(INDEX(Processos!$AR$10:$AR$509,MATCH($A37,Processos!$A$10:$A$509,0)),"")&CHAR(10)&IFERROR(IF(OR(INDEX(Origem!$AB$10:$AB$509,MATCH($A37,Origem!$A$10:$A$509,0))="",INDEX(Origem!$AB$10:$AB$509,MATCH($A37,Origem!$A$10:$A$509,0))="—"),"Origem: sem classificação","Origem: "&INDEX(Origem!$AB$10:$AB$509,MATCH($A37,Origem!$A$10:$A$509,0))&IF(INDEX(Origem!$AC$10:$AC$509,MATCH($A37,Origem!$A$10:$A$509,0))=""," (sem pontuação)"," • "&INDEX(Origem!$AC$10:$AC$509,MATCH($A37,Origem!$A$10:$A$509,0))&" pontos")),"Origem: sem classificação")) | F37: =IF((ROW()-9+($J$8-1)*50)>COUNTIFS(Processos!$X$10:$X$509,1,Processos!$Y$10:$Y$509,1),"",IF(INDEX(Processos!$AQ$10:$AQ$509,MATCH((ROW()-9+($J$8-1)*50),Processos!$AJ$10:$AJ$509,0))="","",INDEX(Processos!$AQ$10:$AQ$509,MATCH((ROW()-9+($J$8-1)*50),Processos!$AJ$10:$AJ$509,0)))) | G37: =IF((ROW()-9+($J$8-1)*50)>COUNTIFS(Processos!$X$10:$X$509,1,Processos!$Y$10:$Y$509,1),"",IFERROR(HYPERLINK("#'Ficha'!C6","Selecionar na Ficha"),"Selecionar na Ficha"))
A38: =IF((ROW()-9+($J$8-1)*50)>COUNTIFS(Processos!$X$10:$X$509,1,Processos!$Y$10:$Y$509,1),"",IF(INDEX(Processos!$A$10:$A$509,MATCH((ROW()-9+($J$8-1)*50),Processos!$AJ$10:$AJ$509,0))="","",INDEX(Processos!$A$10:$A$509,MATCH((ROW()-9+($J$8-1)*50),Processos!$AJ$10:$AJ$509,0)))) | B38: =IF((ROW()-9+($J$8-1)*50)>COUNTIFS(Processos!$X$10:$X$509,1,Processos!$Y$10:$Y$509,1),"",IF(INDEX(Processos!$D$10:$D$509,MATCH((ROW()-9+($J$8-1)*50),Processos!$AJ$10:$AJ$509,0))="","",INDEX(Processos!$D$10:$D$509,MATCH((ROW()-9+($J$8-1)*50),Processos!$AJ$10:$AJ$509,0)))) | C38: =IF(LEN(SUBSTITUTE(SUBSTITUTE(IF((ROW()-9+($J$8-1)*50)>COUNTIFS(Processos!$X$10:$X$509,1,Processos!$Y$10:$Y$509,1),"",IF(INDEX(Processos!$H$10:$H$509,MATCH((ROW()-9+($J$8-1)*50),Processos!$AJ$10:$AJ$509,0))&" × "&INDEX(Processos!$I$10:$I$509,MATCH((ROW()-9+($J$8-1)*50),Processos!$AJ$10:$AJ$509,0))="","",INDEX(Processos!$H$10:$H$509,MATCH((ROW()-9+($J$8-1)*50),Processos!$AJ$10:$AJ$509,0))&" × "&INDEX(Processos!$I$10:$I$509,MATCH((ROW()-9+($J$8-1)*50),Processos!$AJ$10:$AJ$509,0)))),CHAR(10)," "),CHAR(13)," "))>150,LEFT(SUBSTITUTE(SUBSTITUTE(IF((ROW()-9+($J$8-1)*50)>COUNTIFS(Processos!$X$10:$X$509,1,Processos!$Y$10:$Y$509,1),"",IF(INDEX(Processos!$H$10:$H$509,MATCH((ROW()-9+($J$8-1)*50),Processos!$AJ$10:$AJ$509,0))&" × "&INDEX(Processos!$I$10:$I$509,MATCH((ROW()-9+($J$8-1)*50),Processos!$AJ$10:$AJ$509,0))="","",INDEX(Processos!$H$10:$H$509,MATCH((ROW()-9+($J$8-1)*50),Processos!$AJ$10:$AJ$509,0))&" × "&INDEX(Processos!$I$10:$I$509,MATCH((ROW()-9+($J$8-1)*50),Processos!$AJ$10:$AJ$509,0)))),CHAR(10)," "),CHAR(13)," "),150)&" [...]",SUBSTITUTE(SUBSTITUTE(IF((ROW()-9+($J$8-1)*50)>COUNTIFS(Processos!$X$10:$X$509,1,Processos!$Y$10:$Y$509,1),"",IF(INDEX(Processos!$H$10:$H$509,MATCH((ROW()-9+($J$8-1)*50),Processos!$AJ$10:$AJ$509,0))&" × "&INDEX(Processos!$I$10:$I$509,MATCH((ROW()-9+($J$8-1)*50),Processos!$AJ$10:$AJ$509,0))="","",INDEX(Processos!$H$10:$H$509,MATCH((ROW()-9+($J$8-1)*50),Processos!$AJ$10:$AJ$509,0))&" × "&INDEX(Processos!$I$10:$I$509,MATCH((ROW()-9+($J$8-1)*50),Processos!$AJ$10:$AJ$509,0)))),CHAR(10)," "),CHAR(13)," ")) | D38: =SUBSTITUTE(SUBSTITUTE(IF((ROW()-9+($J$8-1)*50)>COUNTIFS(Processos!$X$10:$X$509,1,Processos!$Y$10:$Y$509,1),"",IF(INDEX(Processos!$M$10:$M$509,MATCH((ROW()-9+($J$8-1)*50),Processos!$AJ$10:$AJ$509,0))="","",INDEX(Processos!$M$10:$M$509,MATCH((ROW()-9+($J$8-1)*50),Processos!$AJ$10:$AJ$509,0)))),CHAR(10)," "),CHAR(13)," ") | E38: =IF($A38="","",IFERROR(INDEX(Processos!$AR$10:$AR$509,MATCH($A38,Processos!$A$10:$A$509,0)),"")&CHAR(10)&IFERROR(IF(OR(INDEX(Origem!$AB$10:$AB$509,MATCH($A38,Origem!$A$10:$A$509,0))="",INDEX(Origem!$AB$10:$AB$509,MATCH($A38,Origem!$A$10:$A$509,0))="—"),"Origem: sem classificação","Origem: "&INDEX(Origem!$AB$10:$AB$509,MATCH($A38,Origem!$A$10:$A$509,0))&IF(INDEX(Origem!$AC$10:$AC$509,MATCH($A38,Origem!$A$10:$A$509,0))=""," (sem pontuação)"," • "&INDEX(Origem!$AC$10:$AC$509,MATCH($A38,Origem!$A$10:$A$509,0))&" pontos")),"Origem: sem classificação")) | F38: =IF((ROW()-9+($J$8-1)*50)>COUNTIFS(Processos!$X$10:$X$509,1,Processos!$Y$10:$Y$509,1),"",IF(INDEX(Processos!$AQ$10:$AQ$509,MATCH((ROW()-9+($J$8-1)*50),Processos!$AJ$10:$AJ$509,0))="","",INDEX(Processos!$AQ$10:$AQ$509,MATCH((ROW()-9+($J$8-1)*50),Processos!$AJ$10:$AJ$509,0)))) | G38: =IF((ROW()-9+($J$8-1)*50)>COUNTIFS(Processos!$X$10:$X$509,1,Processos!$Y$10:$Y$509,1),"",IFERROR(HYPERLINK("#'Ficha'!C6","Selecionar na Ficha"),"Selecionar na Ficha"))
A39: =IF((ROW()-9+($J$8-1)*50)>COUNTIFS(Processos!$X$10:$X$509,1,Processos!$Y$10:$Y$509,1),"",IF(INDEX(Processos!$A$10:$A$509,MATCH((ROW()-9+($J$8-1)*50),Processos!$AJ$10:$AJ$509,0))="","",INDEX(Processos!$A$10:$A$509,MATCH((ROW()-9+($J$8-1)*50),Processos!$AJ$10:$AJ$509,0)))) | B39: =IF((ROW()-9+($J$8-1)*50)>COUNTIFS(Processos!$X$10:$X$509,1,Processos!$Y$10:$Y$509,1),"",IF(INDEX(Processos!$D$10:$D$509,MATCH((ROW()-9+($J$8-1)*50),Processos!$AJ$10:$AJ$509,0))="","",INDEX(Processos!$D$10:$D$509,MATCH((ROW()-9+($J$8-1)*50),Processos!$AJ$10:$AJ$509,0)))) | C39: =IF(LEN(SUBSTITUTE(SUBSTITUTE(IF((ROW()-9+($J$8-1)*50)>COUNTIFS(Processos!$X$10:$X$509,1,Processos!$Y$10:$Y$509,1),"",IF(INDEX(Processos!$H$10:$H$509,MATCH((ROW()-9+($J$8-1)*50),Processos!$AJ$10:$AJ$509,0))&" × "&INDEX(Processos!$I$10:$I$509,MATCH((ROW()-9+($J$8-1)*50),Processos!$AJ$10:$AJ$509,0))="","",INDEX(Processos!$H$10:$H$509,MATCH((ROW()-9+($J$8-1)*50),Processos!$AJ$10:$AJ$509,0))&" × "&INDEX(Processos!$I$10:$I$509,MATCH((ROW()-9+($J$8-1)*50),Processos!$AJ$10:$AJ$509,0)))),CHAR(10)," "),CHAR(13)," "))>150,LEFT(SUBSTITUTE(SUBSTITUTE(IF((ROW()-9+($J$8-1)*50)>COUNTIFS(Processos!$X$10:$X$509,1,Processos!$Y$10:$Y$509,1),"",IF(INDEX(Processos!$H$10:$H$509,MATCH((ROW()-9+($J$8-1)*50),Processos!$AJ$10:$AJ$509,0))&" × "&INDEX(Processos!$I$10:$I$509,MATCH((ROW()-9+($J$8-1)*50),Processos!$AJ$10:$AJ$509,0))="","",INDEX(Processos!$H$10:$H$509,MATCH((ROW()-9+($J$8-1)*50),Processos!$AJ$10:$AJ$509,0))&" × "&INDEX(Processos!$I$10:$I$509,MATCH((ROW()-9+($J$8-1)*50),Processos!$AJ$10:$AJ$509,0)))),CHAR(10)," "),CHAR(13)," "),150)&" [...]",SUBSTITUTE(SUBSTITUTE(IF((ROW()-9+($J$8-1)*50)>COUNTIFS(Processos!$X$10:$X$509,1,Processos!$Y$10:$Y$509,1),"",IF(INDEX(Processos!$H$10:$H$509,MATCH((ROW()-9+($J$8-1)*50),Processos!$AJ$10:$AJ$509,0))&" × "&INDEX(Processos!$I$10:$I$509,MATCH((ROW()-9+($J$8-1)*50),Processos!$AJ$10:$AJ$509,0))="","",INDEX(Processos!$H$10:$H$509,MATCH((ROW()-9+($J$8-1)*50),Processos!$AJ$10:$AJ$509,0))&" × "&INDEX(Processos!$I$10:$I$509,MATCH((ROW()-9+($J$8-1)*50),Processos!$AJ$10:$AJ$509,0)))),CHAR(10)," "),CHAR(13)," ")) | D39: =SUBSTITUTE(SUBSTITUTE(IF((ROW()-9+($J$8-1)*50)>COUNTIFS(Processos!$X$10:$X$509,1,Processos!$Y$10:$Y$509,1),"",IF(INDEX(Processos!$M$10:$M$509,MATCH((ROW()-9+($J$8-1)*50),Processos!$AJ$10:$AJ$509,0))="","",INDEX(Processos!$M$10:$M$509,MATCH((ROW()-9+($J$8-1)*50),Processos!$AJ$10:$AJ$509,0)))),CHAR(10)," "),CHAR(13)," ") | E39: =IF($A39="","",IFERROR(INDEX(Processos!$AR$10:$AR$509,MATCH($A39,Processos!$A$10:$A$509,0)),"")&CHAR(10)&IFERROR(IF(OR(INDEX(Origem!$AB$10:$AB$509,MATCH($A39,Origem!$A$10:$A$509,0))="",INDEX(Origem!$AB$10:$AB$509,MATCH($A39,Origem!$A$10:$A$509,0))="—"),"Origem: sem classificação","Origem: "&INDEX(Origem!$AB$10:$AB$509,MATCH($A39,Origem!$A$10:$A$509,0))&IF(INDEX(Origem!$AC$10:$AC$509,MATCH($A39,Origem!$A$10:$A$509,0))=""," (sem pontuação)"," • "&INDEX(Origem!$AC$10:$AC$509,MATCH($A39,Origem!$A$10:$A$509,0))&" pontos")),"Origem: sem classificação")) | F39: =IF((ROW()-9+($J$8-1)*50)>COUNTIFS(Processos!$X$10:$X$509,1,Processos!$Y$10:$Y$509,1),"",IF(INDEX(Processos!$AQ$10:$AQ$509,MATCH((ROW()-9+($J$8-1)*50),Processos!$AJ$10:$AJ$509,0))="","",INDEX(Processos!$AQ$10:$AQ$509,MATCH((ROW()-9+($J$8-1)*50),Processos!$AJ$10:$AJ$509,0)))) | G39: =IF((ROW()-9+($J$8-1)*50)>COUNTIFS(Processos!$X$10:$X$509,1,Processos!$Y$10:$Y$509,1),"",IFERROR(HYPERLINK("#'Ficha'!C6","Selecionar na Ficha"),"Selecionar na Ficha"))
A40: =IF((ROW()-9+($J$8-1)*50)>COUNTIFS(Processos!$X$10:$X$509,1,Processos!$Y$10:$Y$509,1),"",IF(INDEX(Processos!$A$10:$A$509,MATCH((ROW()-9+($J$8-1)*50),Processos!$AJ$10:$AJ$509,0))="","",INDEX(Processos!$A$10:$A$509,MATCH((ROW()-9+($J$8-1)*50),Processos!$AJ$10:$AJ$509,0)))) | B40: =IF((ROW()-9+($J$8-1)*50)>COUNTIFS(Processos!$X$10:$X$509,1,Processos!$Y$10:$Y$509,1),"",IF(INDEX(Processos!$D$10:$D$509,MATCH((ROW()-9+($J$8-1)*50),Processos!$AJ$10:$AJ$509,0))="","",INDEX(Processos!$D$10:$D$509,MATCH((ROW()-9+($J$8-1)*50),Processos!$AJ$10:$AJ$509,0)))) | C40: =IF(LEN(SUBSTITUTE(SUBSTITUTE(IF((ROW()-9+($J$8-1)*50)>COUNTIFS(Processos!$X$10:$X$509,1,Processos!$Y$10:$Y$509,1),"",IF(INDEX(Processos!$H$10:$H$509,MATCH((ROW()-9+($J$8-1)*50),Processos!$AJ$10:$AJ$509,0))&" × "&INDEX(Processos!$I$10:$I$509,MATCH((ROW()-9+($J$8-1)*50),Processos!$AJ$10:$AJ$509,0))="","",INDEX(Processos!$H$10:$H$509,MATCH((ROW()-9+($J$8-1)*50),Processos!$AJ$10:$AJ$509,0))&" × "&INDEX(Processos!$I$10:$I$509,MATCH((ROW()-9+($J$8-1)*50),Processos!$AJ$10:$AJ$509,0)))),CHAR(10)," "),CHAR(13)," "))>150,LEFT(SUBSTITUTE(SUBSTITUTE(IF((ROW()-9+($J$8-1)*50)>COUNTIFS(Processos!$X$10:$X$509,1,Processos!$Y$10:$Y$509,1),"",IF(INDEX(Processos!$H$10:$H$509,MATCH((ROW()-9+($J$8-1)*50),Processos!$AJ$10:$AJ$509,0))&" × "&INDEX(Processos!$I$10:$I$509,MATCH((ROW()-9+($J$8-1)*50),Processos!$AJ$10:$AJ$509,0))="","",INDEX(Processos!$H$10:$H$509,MATCH((ROW()-9+($J$8-1)*50),Processos!$AJ$10:$AJ$509,0))&" × "&INDEX(Processos!$I$10:$I$509,MATCH((ROW()-9+($J$8-1)*50),Processos!$AJ$10:$AJ$509,0)))),CHAR(10)," "),CHAR(13)," "),150)&" [...]",SUBSTITUTE(SUBSTITUTE(IF((ROW()-9+($J$8-1)*50)>COUNTIFS(Processos!$X$10:$X$509,1,Processos!$Y$10:$Y$509,1),"",IF(INDEX(Processos!$H$10:$H$509,MATCH((ROW()-9+($J$8-1)*50),Processos!$AJ$10:$AJ$509,0))&" × "&INDEX(Processos!$I$10:$I$509,MATCH((ROW()-9+($J$8-1)*50),Processos!$AJ$10:$AJ$509,0))="","",INDEX(Processos!$H$10:$H$509,MATCH((ROW()-9+($J$8-1)*50),Processos!$AJ$10:$AJ$509,0))&" × "&INDEX(Processos!$I$10:$I$509,MATCH((ROW()-9+($J$8-1)*50),Processos!$AJ$10:$AJ$509,0)))),CHAR(10)," "),CHAR(13)," ")) | D40: =SUBSTITUTE(SUBSTITUTE(IF((ROW()-9+($J$8-1)*50)>COUNTIFS(Processos!$X$10:$X$509,1,Processos!$Y$10:$Y$509,1),"",IF(INDEX(Processos!$M$10:$M$509,MATCH((ROW()-9+($J$8-1)*50),Processos!$AJ$10:$AJ$509,0))="","",INDEX(Processos!$M$10:$M$509,MATCH((ROW()-9+($J$8-1)*50),Processos!$AJ$10:$AJ$509,0)))),CHAR(10)," "),CHAR(13)," ") | E40: =IF($A40="","",IFERROR(INDEX(Processos!$AR$10:$AR$509,MATCH($A40,Processos!$A$10:$A$509,0)),"")&CHAR(10)&IFERROR(IF(OR(INDEX(Origem!$AB$10:$AB$509,MATCH($A40,Origem!$A$10:$A$509,0))="",INDEX(Origem!$AB$10:$AB$509,MATCH($A40,Origem!$A$10:$A$509,0))="—"),"Origem: sem classificação","Origem: "&INDEX(Origem!$AB$10:$AB$509,MATCH($A40,Origem!$A$10:$A$509,0))&IF(INDEX(Origem!$AC$10:$AC$509,MATCH($A40,Origem!$A$10:$A$509,0))=""," (sem pontuação)"," • "&INDEX(Origem!$AC$10:$AC$509,MATCH($A40,Origem!$A$10:$A$509,0))&" pontos")),"Origem: sem classificação")) | F40: =IF((ROW()-9+($J$8-1)*50)>COUNTIFS(Processos!$X$10:$X$509,1,Processos!$Y$10:$Y$509,1),"",IF(INDEX(Processos!$AQ$10:$AQ$509,MATCH((ROW()-9+($J$8-1)*50),Processos!$AJ$10:$AJ$509,0))="","",INDEX(Processos!$AQ$10:$AQ$509,MATCH((ROW()-9+($J$8-1)*50),Processos!$AJ$10:$AJ$509,0)))) | G40: =IF((ROW()-9+($J$8-1)*50)>COUNTIFS(Processos!$X$10:$X$509,1,Processos!$Y$10:$Y$509,1),"",IFERROR(HYPERLINK("#'Ficha'!C6","Selecionar na Ficha"),"Selecionar na Ficha"))
A41: =IF((ROW()-9+($J$8-1)*50)>COUNTIFS(Processos!$X$10:$X$509,1,Processos!$Y$10:$Y$509,1),"",IF(INDEX(Processos!$A$10:$A$509,MATCH((ROW()-9+($J$8-1)*50),Processos!$AJ$10:$AJ$509,0))="","",INDEX(Processos!$A$10:$A$509,MATCH((ROW()-9+($J$8-1)*50),Processos!$AJ$10:$AJ$509,0)))) | B41: =IF((ROW()-9+($J$8-1)*50)>COUNTIFS(Processos!$X$10:$X$509,1,Processos!$Y$10:$Y$509,1),"",IF(INDEX(Processos!$D$10:$D$509,MATCH((ROW()-9+($J$8-1)*50),Processos!$AJ$10:$AJ$509,0))="","",INDEX(Processos!$D$10:$D$509,MATCH((ROW()-9+($J$8-1)*50),Processos!$AJ$10:$AJ$509,0)))) | C41: =IF(LEN(SUBSTITUTE(SUBSTITUTE(IF((ROW()-9+($J$8-1)*50)>COUNTIFS(Processos!$X$10:$X$509,1,Processos!$Y$10:$Y$509,1),"",IF(INDEX(Processos!$H$10:$H$509,MATCH((ROW()-9+($J$8-1)*50),Processos!$AJ$10:$AJ$509,0))&" × "&INDEX(Processos!$I$10:$I$509,MATCH((ROW()-9+($J$8-1)*50),Processos!$AJ$10:$AJ$509,0))="","",INDEX(Processos!$H$10:$H$509,MATCH((ROW()-9+($J$8-1)*50),Processos!$AJ$10:$AJ$509,0))&" × "&INDEX(Processos!$I$10:$I$509,MATCH((ROW()-9+($J$8-1)*50),Processos!$AJ$10:$AJ$509,0)))),CHAR(10)," "),CHAR(13)," "))>150,LEFT(SUBSTITUTE(SUBSTITUTE(IF((ROW()-9+($J$8-1)*50)>COUNTIFS(Processos!$X$10:$X$509,1,Processos!$Y$10:$Y$509,1),"",IF(INDEX(Processos!$H$10:$H$509,MATCH((ROW()-9+($J$8-1)*50),Processos!$AJ$10:$AJ$509,0))&" × "&INDEX(Processos!$I$10:$I$509,MATCH((ROW()-9+($J$8-1)*50),Processos!$AJ$10:$AJ$509,0))="","",INDEX(Processos!$H$10:$H$509,MATCH((ROW()-9+($J$8-1)*50),Processos!$AJ$10:$AJ$509,0))&" × "&INDEX(Processos!$I$10:$I$509,MATCH((ROW()-9+($J$8-1)*50),Processos!$AJ$10:$AJ$509,0)))),CHAR(10)," "),CHAR(13)," "),150)&" [...]",SUBSTITUTE(SUBSTITUTE(IF((ROW()-9+($J$8-1)*50)>COUNTIFS(Processos!$X$10:$X$509,1,Processos!$Y$10:$Y$509,1),"",IF(INDEX(Processos!$H$10:$H$509,MATCH((ROW()-9+($J$8-1)*50),Processos!$AJ$10:$AJ$509,0))&" × "&INDEX(Processos!$I$10:$I$509,MATCH((ROW()-9+($J$8-1)*50),Processos!$AJ$10:$AJ$509,0))="","",INDEX(Processos!$H$10:$H$509,MATCH((ROW()-9+($J$8-1)*50),Processos!$AJ$10:$AJ$509,0))&" × "&INDEX(Processos!$I$10:$I$509,MATCH((ROW()-9+($J$8-1)*50),Processos!$AJ$10:$AJ$509,0)))),CHAR(10)," "),CHAR(13)," ")) | D41: =SUBSTITUTE(SUBSTITUTE(IF((ROW()-9+($J$8-1)*50)>COUNTIFS(Processos!$X$10:$X$509,1,Processos!$Y$10:$Y$509,1),"",IF(INDEX(Processos!$M$10:$M$509,MATCH((ROW()-9+($J$8-1)*50),Processos!$AJ$10:$AJ$509,0))="","",INDEX(Processos!$M$10:$M$509,MATCH((ROW()-9+($J$8-1)*50),Processos!$AJ$10:$AJ$509,0)))),CHAR(10)," "),CHAR(13)," ") | E41: =IF($A41="","",IFERROR(INDEX(Processos!$AR$10:$AR$509,MATCH($A41,Processos!$A$10:$A$509,0)),"")&CHAR(10)&IFERROR(IF(OR(INDEX(Origem!$AB$10:$AB$509,MATCH($A41,Origem!$A$10:$A$509,0))="",INDEX(Origem!$AB$10:$AB$509,MATCH($A41,Origem!$A$10:$A$509,0))="—"),"Origem: sem classificação","Origem: "&INDEX(Origem!$AB$10:$AB$509,MATCH($A41,Origem!$A$10:$A$509,0))&IF(INDEX(Origem!$AC$10:$AC$509,MATCH($A41,Origem!$A$10:$A$509,0))=""," (sem pontuação)"," • "&INDEX(Origem!$AC$10:$AC$509,MATCH($A41,Origem!$A$10:$A$509,0))&" pontos")),"Origem: sem classificação")) | F41: =IF((ROW()-9+($J$8-1)*50)>COUNTIFS(Processos!$X$10:$X$509,1,Processos!$Y$10:$Y$509,1),"",IF(INDEX(Processos!$AQ$10:$AQ$509,MATCH((ROW()-9+($J$8-1)*50),Processos!$AJ$10:$AJ$509,0))="","",INDEX(Processos!$AQ$10:$AQ$509,MATCH((ROW()-9+($J$8-1)*50),Processos!$AJ$10:$AJ$509,0)))) | G41: =IF((ROW()-9+($J$8-1)*50)>COUNTIFS(Processos!$X$10:$X$509,1,Processos!$Y$10:$Y$509,1),"",IFERROR(HYPERLINK("#'Ficha'!C6","Selecionar na Ficha"),"Selecionar na Ficha"))
... A59: =IF((ROW()-9+($J$8-1)*50)>COUNTIFS(Processos!$X$10:$X$509,1,Processos!$Y$10:$Y$509,1),"",IF(INDEX(Processos!$A$10:$A$509,MATCH((ROW()-9+($J$8-1)*50),Processos!$AJ$10:$AJ$509,0))="","",INDEX(Processos!$A$10:$A$509,MATCH((ROW()-9+($J$8-1)*50),Processos!$AJ$10:$AJ$509,0)))) | B59: =IF((ROW()-9+($J$8-1)*50)>COUNTIFS(Processos!$X$10:$X$509,1,Processos!$Y$10:$Y$509,1),"",IF(INDEX(Processos!$D$10:$D$509,MATCH((ROW()-9+($J$8-1)*50),Processos!$AJ$10:$AJ$509,0))="","",INDEX(Processos!$D$10:$D$509,MATCH((ROW()-9+($J$8-1)*50),Processos!$AJ$10:$AJ$509,0)))) | C59: =IF(LEN(SUBSTITUTE(SUBSTITUTE(IF((ROW()-9+($J$8-1)*50)>COUNTIFS(Processos!$X$10:$X$509,1,Processos!$Y$10:$Y$509,1),"",IF(INDEX(Processos!$H$10:$H$509,MATCH((ROW()-9+($J$8-1)*50),Processos!$AJ$10:$AJ$509,0))&" × "&INDEX(Processos!$I$10:$I$509,MATCH((ROW()-9+($J$8-1)*50),Processos!$AJ$10:$AJ$509,0))="","",INDEX(Processos!$H$10:$H$509,MATCH((ROW()-9+($J$8-1)*50),Processos!$AJ$10:$AJ$509,0))&" × "&INDEX(Processos!$I$10:$I$509,MATCH((ROW()-9+($J$8-1)*50),Processos!$AJ$10:$AJ$509,0)))),CHAR(10)," "),CHAR(13)," "))>150,LEFT(SUBSTITUTE(SUBSTITUTE(IF((ROW()-9+($J$8-1)*50)>COUNTIFS(Processos!$X$10:$X$509,1,Processos!$Y$10:$Y$509,1),"",IF(INDEX(Processos!$H$10:$H$509,MATCH((ROW()-9+($J$8-1)*50),Processos!$AJ$10:$AJ$509,0))&" × "&INDEX(Processos!$I$10:$I$509,MATCH((ROW()-9+($J$8-1)*50),Processos!$AJ$10:$AJ$509,0))="","",INDEX(Processos!$H$10:$H$509,MATCH((ROW()-9+($J$8-1)*50),Processos!$AJ$10:$AJ$509,0))&" × "&INDEX(Processos!$I$10:$I$509,MATCH((ROW()-9+($J$8-1)*50),Processos!$AJ$10:$AJ$509,0)))),CHAR(10)," "),CHAR(13)," "),150)&" [...]",SUBSTITUTE(SUBSTITUTE(IF((ROW()-9+($J$8-1)*50)>COUNTIFS(Processos!$X$10:$X$509,1,Processos!$Y$10:$Y$509,1),"",IF(INDEX(Processos!$H$10:$H$509,MATCH((ROW()-9+($J$8-1)*50),Processos!$AJ$10:$AJ$509,0))&" × "&INDEX(Processos!$I$10:$I$509,MATCH((ROW()-9+($J$8-1)*50),Processos!$AJ$10:$AJ$509,0))="","",INDEX(Processos!$H$10:$H$509,MATCH((ROW()-9+($J$8-1)*50),Processos!$AJ$10:$AJ$509,0))&" × "&INDEX(Processos!$I$10:$I$509,MATCH((ROW()-9+($J$8-1)*50),Processos!$AJ$10:$AJ$509,0)))),CHAR(10)," "),CHAR(13)," ")) | D59: =SUBSTITUTE(SUBSTITUTE(IF((ROW()-9+($J$8-1)*50)>COUNTIFS(Processos!$X$10:$X$509,1,Processos!$Y$10:$Y$509,1),"",IF(INDEX(Processos!$M$10:$M$509,MATCH((ROW()-9+($J$8-1)*50),Processos!$AJ$10:$AJ$509,0))="","",INDEX(Processos!$M$10:$M$509,MATCH((ROW()-9+($J$8-1)*50),Processos!$AJ$10:$AJ$509,0)))),CHAR(10)," "),CHAR(13)," ") | E59: =IF($A59="","",IFERROR(INDEX(Processos!$AR$10:$AR$509,MATCH($A59,Processos!$A$10:$A$509,0)),"")&CHAR(10)&IFERROR(IF(OR(INDEX(Origem!$AB$10:$AB$509,MATCH($A59,Origem!$A$10:$A$509,0))="",INDEX(Origem!$AB$10:$AB$509,MATCH($A59,Origem!$A$10:$A$509,0))="—"),"Origem: sem classificação","Origem: "&INDEX(Origem!$AB$10:$AB$509,MATCH($A59,Origem!$A$10:$A$509,0))&IF(INDEX(Origem!$AC$10:$AC$509,MATCH($A59,Origem!$A$10:$A$509,0))=""," (sem pontuação)"," • "&INDEX(Origem!$AC$10:$AC$509,MATCH($A59,Origem!$A$10:$A$509,0))&" pontos")),"Origem: sem classificação")) | F59: =IF((ROW()-9+($J$8-1)*50)>COUNTIFS(Processos!$X$10:$X$509,1,Processos!$Y$10:$Y$509,1),"",IF(INDEX(Processos!$AQ$10:$AQ$509,MATCH((ROW()-9+($J$8-1)*50),Processos!$AJ$10:$AJ$509,0))="","",INDEX(Processos!$AQ$10:$AQ$509,MATCH((ROW()-9+($J$8-1)*50),Processos!$AJ$10:$AJ$509,0)))) | G59: =IF((ROW()-9+($J$8-1)*50)>COUNTIFS(Processos!$X$10:$X$509,1,Processos!$Y$10:$Y$509,1),"",IFERROR(HYPERLINK("#'Ficha'!C6","Selecionar na Ficha"),"Selecionar na Ficha"))
E60: =IF($A60="","",IFERROR(INDEX(Processos!$AR$10:$AR$509,MATCH($A60,Processos!$A$10:$A$509,0)),"")&CHAR(10)&IFERROR(IF(OR(INDEX(Origem!$AB$10:$AB$509,MATCH($A60,Origem!$A$10:$A$509,0))="",INDEX(Origem!$AB$10:$AB$509,MATCH($A60,Origem!$A$10:$A$509,0))="—"),"Origem: sem classificação","Origem: "&INDEX(Origem!$AB$10:$AB$509,MATCH($A60,Origem!$A$10:$A$509,0))&IF(INDEX(Origem!$AC$10:$AC$509,MATCH($A60,Origem!$A$10:$A$509,0))=""," (sem pontuação)"," • "&INDEX(Origem!$AC$10:$AC$509,MATCH($A60,Origem!$A$10:$A$509,0))&" pontos")),"Origem: sem classificação"))
E61: =IF($A61="","",IFERROR(INDEX(Processos!$AR$10:$AR$509,MATCH($A61,Processos!$A$10:$A$509,0)),"")&CHAR(10)&IFERROR(IF(OR(INDEX(Origem!$AB$10:$AB$509,MATCH($A61,Origem!$A$10:$A$509,0))="",INDEX(Origem!$AB$10:$AB$509,MATCH($A61,Origem!$A$10:$A$509,0))="—"),"Origem: sem classificação","Origem: "&INDEX(Origem!$AB$10:$AB$509,MATCH($A61,Origem!$A$10:$A$509,0))&IF(INDEX(Origem!$AC$10:$AC$509,MATCH($A61,Origem!$A$10:$A$509,0))=""," (sem pontuação)"," • "&INDEX(Origem!$AC$10:$AC$509,MATCH($A61,Origem!$A$10:$A$509,0))&" pontos")),"Origem: sem classificação"))
E62: =IF($A62="","",IFERROR(INDEX(Processos!$AR$10:$AR$509,MATCH($A62,Processos!$A$10:$A$509,0)),"")&CHAR(10)&IFERROR(IF(OR(INDEX(Origem!$AB$10:$AB$509,MATCH($A62,Origem!$A$10:$A$509,0))="",INDEX(Origem!$AB$10:$AB$509,MATCH($A62,Origem!$A$10:$A$509,0))="—"),"Origem: sem classificação","Origem: "&INDEX(Origem!$AB$10:$AB$509,MATCH($A62,Origem!$A$10:$A$509,0))&IF(INDEX(Origem!$AC$10:$AC$509,MATCH($A62,Origem!$A$10:$A$509,0))=""," (sem pontuação)"," • "&INDEX(Origem!$AC$10:$AC$509,MATCH($A62,Origem!$A$10:$A$509,0))&" pontos")),"Origem: sem classificação"))
E63: =IF($A63="","",IFERROR(INDEX(Processos!$AR$10:$AR$509,MATCH($A63,Processos!$A$10:$A$509,0)),"")&CHAR(10)&IFERROR(IF(OR(INDEX(Origem!$AB$10:$AB$509,MATCH($A63,Origem!$A$10:$A$509,0))="",INDEX(Origem!$AB$10:$AB$509,MATCH($A63,Origem!$A$10:$A$509,0))="—"),"Origem: sem classificação","Origem: "&INDEX(Origem!$AB$10:$AB$509,MATCH($A63,Origem!$A$10:$A$509,0))&IF(INDEX(Origem!$AC$10:$AC$509,MATCH($A63,Origem!$A$10:$A$509,0))=""," (sem pontuação)"," • "&INDEX(Origem!$AC$10:$AC$509,MATCH($A63,Origem!$A$10:$A$509,0))&" pontos")),"Origem: sem classificação"))
E64: =IF($A64="","",IFERROR(INDEX(Processos!$AR$10:$AR$509,MATCH($A64,Processos!$A$10:$A$509,0)),"")&CHAR(10)&IFERROR(IF(OR(INDEX(Origem!$AB$10:$AB$509,MATCH($A64,Origem!$A$10:$A$509,0))="",INDEX(Origem!$AB$10:$AB$509,MATCH($A64,Origem!$A$10:$A$509,0))="—"),"Origem: sem classificação","Origem: "&INDEX(Origem!$AB$10:$AB$509,MATCH($A64,Origem!$A$10:$A$509,0))&IF(INDEX(Origem!$AC$10:$AC$509,MATCH($A64,Origem!$A$10:$A$509,0))=""," (sem pontuação)"," • "&INDEX(Origem!$AC$10:$AC$509,MATCH($A64,Origem!$A$10:$A$509,0))&" pontos")),"Origem: sem classificação"))
E65: =IF($A65="","",IFERROR(INDEX(Processos!$AR$10:$AR$509,MATCH($A65,Processos!$A$10:$A$509,0)),"")&CHAR(10)&IFERROR(IF(OR(INDEX(Origem!$AB$10:$AB$509,MATCH($A65,Origem!$A$10:$A$509,0))="",INDEX(Origem!$AB$10:$AB$509,MATCH($A65,Origem!$A$10:$A$509,0))="—"),"Origem: sem classificação","Origem: "&INDEX(Origem!$AB$10:$AB$509,MATCH($A65,Origem!$A$10:$A$509,0))&IF(INDEX(Origem!$AC$10:$AC$509,MATCH($A65,Origem!$A$10:$A$509,0))=""," (sem pontuação)"," • "&INDEX(Origem!$AC$10:$AC$509,MATCH($A65,Origem!$A$10:$A$509,0))&" pontos")),"Origem: sem classificação"))
E66: =IF($A66="","",IFERROR(INDEX(Processos!$AR$10:$AR$509,MATCH($A66,Processos!$A$10:$A$509,0)),"")&CHAR(10)&IFERROR(IF(OR(INDEX(Origem!$AB$10:$AB$509,MATCH($A66,Origem!$A$10:$A$509,0))="",INDEX(Origem!$AB$10:$AB$509,MATCH($A66,Origem!$A$10:$A$509,0))="—"),"Origem: sem classificação","Origem: "&INDEX(Origem!$AB$10:$AB$509,MATCH($A66,Origem!$A$10:$A$509,0))&IF(INDEX(Origem!$AC$10:$AC$509,MATCH($A66,Origem!$A$10:$A$509,0))=""," (sem pontuação)"," • "&INDEX(Origem!$AC$10:$AC$509,MATCH($A66,Origem!$A$10:$A$509,0))&" pontos")),"Origem: sem classificação"))
E67: =IF($A67="","",IFERROR(INDEX(Processos!$AR$10:$AR$509,MATCH($A67,Processos!$A$10:$A$509,0)),"")&CHAR(10)&IFERROR(IF(OR(INDEX(Origem!$AB$10:$AB$509,MATCH($A67,Origem!$A$10:$A$509,0))="",INDEX(Origem!$AB$10:$AB$509,MATCH($A67,Origem!$A$10:$A$509,0))="—"),"Origem: sem classificação","Origem: "&INDEX(Origem!$AB$10:$AB$509,MATCH($A67,Origem!$A$10:$A$509,0))&IF(INDEX(Origem!$AC$10:$AC$509,MATCH($A67,Origem!$A$10:$A$509,0))=""," (sem pontuação)"," • "&INDEX(Origem!$AC$10:$AC$509,MATCH($A67,Origem!$A$10:$A$509,0))&" pontos")),"Origem: sem classificação"))
E68: =IF($A68="","",IFERROR(INDEX(Processos!$AR$10:$AR$509,MATCH($A68,Processos!$A$10:$A$509,0)),"")&CHAR(10)&IFERROR(IF(OR(INDEX(Origem!$AB$10:$AB$509,MATCH($A68,Origem!$A$10:$A$509,0))="",INDEX(Origem!$AB$10:$AB$509,MATCH($A68,Origem!$A$10:$A$509,0))="—"),"Origem: sem classificação","Origem: "&INDEX(Origem!$AB$10:$AB$509,MATCH($A68,Origem!$A$10:$A$509,0))&IF(INDEX(Origem!$AC$10:$AC$509,MATCH($A68,Origem!$A$10:$A$509,0))=""," (sem pontuação)"," • "&INDEX(Origem!$AC$10:$AC$509,MATCH($A68,Origem!$A$10:$A$509,0))&" pontos")),"Origem: sem classificação"))
E69: =IF($A69="","",IFERROR(INDEX(Processos!$AR$10:$AR$509,MATCH($A69,Processos!$A$10:$A$509,0)),"")&CHAR(10)&IFERROR(IF(OR(INDEX(Origem!$AB$10:$AB$509,MATCH($A69,Origem!$A$10:$A$509,0))="",INDEX(Origem!$AB$10:$AB$509,MATCH($A69,Origem!$A$10:$A$509,0))="—"),"Origem: sem classificação","Origem: "&INDEX(Origem!$AB$10:$AB$509,MATCH($A69,Origem!$A$10:$A$509,0))&IF(INDEX(Origem!$AC$10:$AC$509,MATCH($A69,Origem!$A$10:$A$509,0))=""," (sem pontuação)"," • "&INDEX(Origem!$AC$10:$AC$509,MATCH($A69,Origem!$A$10:$A$509,0))&" pontos")),"Origem: sem classificação"))
E70: =IF($A70="","",IFERROR(INDEX(Processos!$AR$10:$AR$509,MATCH($A70,Processos!$A$10:$A$509,0)),"")&CHAR(10)&IFERROR(IF(OR(INDEX(Origem!$AB$10:$AB$509,MATCH($A70,Origem!$A$10:$A$509,0))="",INDEX(Origem!$AB$10:$AB$509,MATCH($A70,Origem!$A$10:$A$509,0))="—"),"Origem: sem classificação","Origem: "&INDEX(Origem!$AB$10:$AB$509,MATCH($A70,Origem!$A$10:$A$509,0))&IF(INDEX(Origem!$AC$10:$AC$509,MATCH($A70,Origem!$A$10:$A$509,0))=""," (sem pontuação)"," • "&INDEX(Origem!$AC$10:$AC$509,MATCH($A70,Origem!$A$10:$A$509,0))&" pontos")),"Origem: sem classificação"))
E71: =IF($A71="","",IFERROR(INDEX(Processos!$AR$10:$AR$509,MATCH($A71,Processos!$A$10:$A$509,0)),"")&CHAR(10)&IFERROR(IF(OR(INDEX(Origem!$AB$10:$AB$509,MATCH($A71,Origem!$A$10:$A$509,0))="",INDEX(Origem!$AB$10:$AB$509,MATCH($A71,Origem!$A$10:$A$509,0))="—"),"Origem: sem classificação","Origem: "&INDEX(Origem!$AB$10:$AB$509,MATCH($A71,Origem!$A$10:$A$509,0))&IF(INDEX(Origem!$AC$10:$AC$509,MATCH($A71,Origem!$A$10:$A$509,0))=""," (sem pontuação)"," • "&INDEX(Origem!$AC$10:$AC$509,MATCH($A71,Origem!$A$10:$A$509,0))&" pontos")),"Origem: sem classificação"))
... E509: =IF($A509="","",IFERROR(INDEX(Processos!$AR$10:$AR$509,MATCH($A509,Processos!$A$10:$A$509,0)),"")&CHAR(10)&IFERROR(IF(OR(INDEX(Origem!$AB$10:$AB$509,MATCH($A509,Origem!$A$10:$A$509,0))="",INDEX(Origem!$AB$10:$AB$509,MATCH($A509,Origem!$A$10:$A$509,0))="—"),"Origem: sem classificação","Origem: "&INDEX(Origem!$AB$10:$AB$509,MATCH($A509,Origem!$A$10:$A$509,0))&IF(INDEX(Origem!$AC$10:$AC$509,MATCH($A509,Origem!$A$10:$A$509,0))=""," (sem pontuação)"," • "&INDEX(Origem!$AC$10:$AC$509,MATCH($A509,Origem!$A$10:$A$509,0))&" pontos")),"Origem: sem classificação"))

Sheet Escritórios
A2: Acompanhamento dos escritórios
A3: Comparação por escritório e carteira filtrada. Os controles ficam no Painel.
A4: =IFERROR(HYPERLINK("#'Painel'!A1","Painel"),"Painel") -> Painel | D4: =IFERROR(HYPERLINK("#'Ficha'!C6","Ficha do processo"),"Ficha do processo") -> Ficha do processo | G4: =IFERROR(HYPERLINK("#'Central IA'!C6","Atualizar com IA"),"Atualizar com IA") -> Atualizar com IA
A5: As listas seguem os filtros escolhidos no Painel.
A6: ="Escritório escolhido: "&Painel!C6&" Empresa: "&Painel!L6&" Consórcio: "&Painel!C8&" Tema: "&Painel!L8 -> Escritório escolhido: Todos Empresa: Todas Consórcio: Todos Tema: Todos
A7: A comparação considera empresa, consórcio, tema e busca. A lista de processos também considera o escritório escolhido.
A9: Escritório | B9: Total | C9: Críticos | D9: Cobrar atualização | E9: Valor da causa | F9: Depósitos judiciais | G9: Benefício estimado
A10: =IF(OR(Configurar!A10="",COUNTIFS(Configurar!$A$10:A10,Configurar!A10)>1),"",Configurar!A10) -> BMM Advogados | B10: =IF(A10="","",COUNTIFS(Processos!$D$10:$D$509,A10,Processos!$AL$10:$AL$509,1)) -> 103 | C10: =IF(A10="","",COUNTIFS(Processos!$D$10:$D$509,A10,Processos!$AL$10:$AL$509,1,Processos!$Y$10:$Y$509,1)) -> 6 | D10: =IF(A10="","",COUNTIFS(Processos!$D$10:$D$509,A10,Processos!$AL$10:$AL$509,1,Processos!$AD$10:$AD$509,1)) -> 57 | E10: =IF(A10="","",IF(COUNTIFS(Valores!$P$10:$P$509,A10,Valores!$Q$10:$Q$509,1,Valores!$B$10:$B$509,">0")+COUNTIFS(Valores!$P$10:$P$509,A10,Valores!$Q$10:$Q$509,1,Valores!$B$10:$B$509,"=0",Valores!$B$10:$B$509,"<>")=0,"Não informado",SUMIFS(Valores!$B$10:$B$509,Valores!$P$10:$P$509,A10,Valores!$Q$10:$Q$509,1))) -> 19619029 | F10: =IF(A10="","",IF(COUNTIFS(Valores!$P$10:$P$509,A10,Valores!$Q$10:$Q$509,1,Valores!$D$10:$D$509,">0")+COUNTIFS(Valores!$P$10:$P$509,A10,Valores!$Q$10:$Q$509,1,Valores!$D$10:$D$509,"=0",Valores!$D$10:$D$509,"<>")=0,"Não informado",SUMIFS(Valores!$D$10:$D$509,Valores!$P$10:$P$509,A10,Valores!$Q$10:$Q$509,1))) -> 137749.46 | G10: =IF(A10="","",IF(COUNTIFS(Valores!$P$10:$P$509,A10,Valores!$Q$10:$Q$509,1,Valores!$G$10:$G$509,">0")+COUNTIFS(Valores!$P$10:$P$509,A10,Valores!$Q$10:$Q$509,1,Valores!$G$10:$G$509,"=0",Valores!$G$10:$G$509,"<>")=0,"Não informado",SUMIFS(Valores!$G$10:$G$509,Valores!$P$10:$P$509,A10,Valores!$Q$10:$Q$509,1))) -> Não informado
A11: =IF(OR(Configurar!A11="",COUNTIFS(Configurar!$A$10:A11,Configurar!A11)>1),"",Configurar!A11) -> SMP Advogados | B11: =IF(A11="","",COUNTIFS(Processos!$D$10:$D$509,A11,Processos!$AL$10:$AL$509,1)) -> 15 | C11: =IF(A11="","",COUNTIFS(Processos!$D$10:$D$509,A11,Processos!$AL$10:$AL$509,1,Processos!$Y$10:$Y$509,1)) -> 0 | D11: =IF(A11="","",COUNTIFS(Processos!$D$10:$D$509,A11,Processos!$AL$10:$AL$509,1,Processos!$AD$10:$AD$509,1)) -> 10 | E11: =IF(A11="","",IF(COUNTIFS(Valores!$P$10:$P$509,A11,Valores!$Q$10:$Q$509,1,Valores!$B$10:$B$509,">0")+COUNTIFS(Valores!$P$10:$P$509,A11,Valores!$Q$10:$Q$509,1,Valores!$B$10:$B$509,"=0",Valores!$B$10:$B$509,"<>")=0,"Não informado",SUMIFS(Valores!$B$10:$B$509,Valores!$P$10:$P$509,A11,Valores!$Q$10:$Q$509,1))) -> 9819315 | F11: =IF(A11="","",IF(COUNTIFS(Valores!$P$10:$P$509,A11,Valores!$Q$10:$Q$509,1,Valores!$D$10:$D$509,">0")+COUNTIFS(Valores!$P$10:$P$509,A11,Valores!$Q$10:$Q$509,1,Valores!$D$10:$D$509,"=0",Valores!$D$10:$D$509,"<>")=0,"Não informado",SUMIFS(Valores!$D$10:$D$509,Valores!$P$10:$P$509,A11,Valores!$Q$10:$Q$509,1))) -> Não informado | G11: =IF(A11="","",IF(COUNTIFS(Valores!$P$10:$P$509,A11,Valores!$Q$10:$Q$509,1,Valores!$G$10:$G$509,">0")+COUNTIFS(Valores!$P$10:$P$509,A11,Valores!$Q$10:$Q$509,1,Valores!$G$10:$G$509,"=0",Valores!$G$10:$G$509,"<>")=0,"Não informado",SUMIFS(Valores!$G$10:$G$509,Valores!$P$10:$P$509,A11,Valores!$Q$10:$Q$509,1))) -> Não informado
A12: =IF(OR(Configurar!A12="",COUNTIFS(Configurar!$A$10:A12,Configurar!A12)>1),"",Configurar!A12) -> Liporace | B12: =IF(A12="","",COUNTIFS(Processos!$D$10:$D$509,A12,Processos!$AL$10:$AL$509,1)) -> 9 | C12: =IF(A12="","",COUNTIFS(Processos!$D$10:$D$509,A12,Processos!$AL$10:$AL$509,1,Processos!$Y$10:$Y$509,1)) -> 0 | D12: =IF(A12="","",COUNTIFS(Processos!$D$10:$D$509,A12,Processos!$AL$10:$AL$509,1,Processos!$AD$10:$AD$509,1)) -> 5 | E12: =IF(A12="","",IF(COUNTIFS(Valores!$P$10:$P$509,A12,Valores!$Q$10:$Q$509,1,Valores!$B$10:$B$509,">0")+COUNTIFS(Valores!$P$10:$P$509,A12,Valores!$Q$10:$Q$509,1,Valores!$B$10:$B$509,"=0",Valores!$B$10:$B$509,"<>")=0,"Não informado",SUMIFS(Valores!$B$10:$B$509,Valores!$P$10:$P$509,A12,Valores!$Q$10:$Q$509,1))) -> 104350000 | F12: =IF(A12="","",IF(COUNTIFS(Valores!$P$10:$P$509,A12,Valores!$Q$10:$Q$509,1,Valores!$D$10:$D$509,">0")+COUNTIFS(Valores!$P$10:$P$509,A12,Valores!$Q$10:$Q$509,1,Valores!$D$10:$D$509,"=0",Valores!$D$10:$D$509,"<>")=0,"Não informado",SUMIFS(Valores!$D$10:$D$509,Valores!$P$10:$P$509,A12,Valores!$Q$10:$Q$509,1))) -> Não informado | G12: =IF(A12="","",IF(COUNTIFS(Valores!$P$10:$P$509,A12,Valores!$Q$10:$Q$509,1,Valores!$G$10:$G$509,">0")+COUNTIFS(Valores!$P$10:$P$509,A12,Valores!$Q$10:$Q$509,1,Valores!$G$10:$G$509,"=0",Valores!$G$10:$G$509,"<>")=0,"Não informado",SUMIFS(Valores!$G$10:$G$509,Valores!$P$10:$P$509,A12,Valores!$Q$10:$Q$509,1))) -> Não informado
A13: =IF(OR(Configurar!A13="",COUNTIFS(Configurar!$A$10:A13,Configurar!A13)>1),"",Configurar!A13) -> Enver | B13: =IF(A13="","",COUNTIFS(Processos!$D$10:$D$509,A13,Processos!$AL$10:$AL$509,1)) -> 1 | C13: =IF(A13="","",COUNTIFS(Processos!$D$10:$D$509,A13,Processos!$AL$10:$AL$509,1,Processos!$Y$10:$Y$509,1)) -> 0 | D13: =IF(A13="","",COUNTIFS(Processos!$D$10:$D$509,A13,Processos!$AL$10:$AL$509,1,Processos!$AD$10:$AD$509,1)) -> 0 | E13: =IF(A13="","",IF(COUNTIFS(Valores!$P$10:$P$509,A13,Valores!$Q$10:$Q$509,1,Valores!$B$10:$B$509,">0")+COUNTIFS(Valores!$P$10:$P$509,A13,Valores!$Q$10:$Q$509,1,Valores!$B$10:$B$509,"=0",Valores!$B$10:$B$509,"<>")=0,"Não informado",SUMIFS(Valores!$B$10:$B$509,Valores!$P$10:$P$509,A13,Valores!$Q$10:$Q$509,1))) -> Não informado | F13: =IF(A13="","",IF(COUNTIFS(Valores!$P$10:$P$509,A13,Valores!$Q$10:$Q$509,1,Valores!$D$10:$D$509,">0")+COUNTIFS(Valores!$P$10:$P$509,A13,Valores!$Q$10:$Q$509,1,Valores!$D$10:$D$509,"=0",Valores!$D$10:$D$509,"<>")=0,"Não informado",SUMIFS(Valores!$D$10:$D$509,Valores!$P$10:$P$509,A13,Valores!$Q$10:$Q$509,1))) -> Não informado | G13: =IF(A13="","",IF(COUNTIFS(Valores!$P$10:$P$509,A13,Valores!$Q$10:$Q$509,1,Valores!$G$10:$G$509,">0")+COUNTIFS(Valores!$P$10:$P$509,A13,Valores!$Q$10:$Q$509,1,Valores!$G$10:$G$509,"=0",Valores!$G$10:$G$509,"<>")=0,"Não informado",SUMIFS(Valores!$G$10:$G$509,Valores!$P$10:$P$509,A13,Valores!$Q$10:$Q$509,1))) -> Não informado
A14: =IF(OR(Configurar!A14="",COUNTIFS(Configurar!$A$10:A14,Configurar!A14)>1),"",Configurar!A14) -> Pedro Calmon | B14: =IF(A14="","",COUNTIFS(Processos!$D$10:$D$509,A14,Processos!$AL$10:$AL$509,1)) -> 1 | C14: =IF(A14="","",COUNTIFS(Processos!$D$10:$D$509,A14,Processos!$AL$10:$AL$509,1,Processos!$Y$10:$Y$509,1)) -> 0 | D14: =IF(A14="","",COUNTIFS(Processos!$D$10:$D$509,A14,Processos!$AL$10:$AL$509,1,Processos!$AD$10:$AD$509,1)) -> 1 | E14: =IF(A14="","",IF(COUNTIFS(Valores!$P$10:$P$509,A14,Valores!$Q$10:$Q$509,1,Valores!$B$10:$B$509,">0")+COUNTIFS(Valores!$P$10:$P$509,A14,Valores!$Q$10:$Q$509,1,Valores!$B$10:$B$509,"=0",Valores!$B$10:$B$509,"<>")=0,"Não informado",SUMIFS(Valores!$B$10:$B$509,Valores!$P$10:$P$509,A14,Valores!$Q$10:$Q$509,1))) -> Não informado | F14: =IF(A14="","",IF(COUNTIFS(Valores!$P$10:$P$509,A14,Valores!$Q$10:$Q$509,1,Valores!$D$10:$D$509,">0")+COUNTIFS(Valores!$P$10:$P$509,A14,Valores!$Q$10:$Q$509,1,Valores!$D$10:$D$509,"=0",Valores!$D$10:$D$509,"<>")=0,"Não informado",SUMIFS(Valores!$D$10:$D$509,Valores!$P$10:$P$509,A14,Valores!$Q$10:$Q$509,1))) -> Não informado | G14: =IF(A14="","",IF(COUNTIFS(Valores!$P$10:$P$509,A14,Valores!$Q$10:$Q$509,1,Valores!$G$10:$G$509,">0")+COUNTIFS(Valores!$P$10:$P$509,A14,Valores!$Q$10:$Q$509,1,Valores!$G$10:$G$509,"=0",Valores!$G$10:$G$509,"<>")=0,"Não informado",SUMIFS(Valores!$G$10:$G$509,Valores!$P$10:$P$509,A14,Valores!$Q$10:$Q$509,1))) -> Não informado
A15: =IF(OR(Configurar!A15="",COUNTIFS(Configurar!$A$10:A15,Configurar!A15)>1),"",Configurar!A15) -> Brandão | B15: =IF(A15="","",COUNTIFS(Processos!$D$10:$D$509,A15,Processos!$AL$10:$AL$509,1)) -> 2 | C15: =IF(A15="","",COUNTIFS(Processos!$D$10:$D$509,A15,Processos!$AL$10:$AL$509,1,Processos!$Y$10:$Y$509,1)) -> 0 | D15: =IF(A15="","",COUNTIFS(Processos!$D$10:$D$509,A15,Processos!$AL$10:$AL$509,1,Processos!$AD$10:$AD$509,1)) -> 2 | E15: =IF(A15="","",IF(COUNTIFS(Valores!$P$10:$P$509,A15,Valores!$Q$10:$Q$509,1,Valores!$B$10:$B$509,">0")+COUNTIFS(Valores!$P$10:$P$509,A15,Valores!$Q$10:$Q$509,1,Valores!$B$10:$B$509,"=0",Valores!$B$10:$B$509,"<>")=0,"Não informado",SUMIFS(Valores!$B$10:$B$509,Valores!$P$10:$P$509,A15,Valores!$Q$10:$Q$509,1))) -> Não informado | F15: =IF(A15="","",IF(COUNTIFS(Valores!$P$10:$P$509,A15,Valores!$Q$10:$Q$509,1,Valores!$D$10:$D$509,">0")+COUNTIFS(Valores!$P$10:$P$509,A15,Valores!$Q$10:$Q$509,1,Valores!$D$10:$D$509,"=0",Valores!$D$10:$D$509,"<>")=0,"Não informado",SUMIFS(Valores!$D$10:$D$509,Valores!$P$10:$P$509,A15,Valores!$Q$10:$Q$509,1))) -> Não informado | G15: =IF(A15="","",IF(COUNTIFS(Valores!$P$10:$P$509,A15,Valores!$Q$10:$Q$509,1,Valores!$G$10:$G$509,">0")+COUNTIFS(Valores!$P$10:$P$509,A15,Valores!$Q$10:$Q$509,1,Valores!$G$10:$G$509,"=0",Valores!$G$10:$G$509,"<>")=0,"Não informado",SUMIFS(Valores!$G$10:$G$509,Valores!$P$10:$P$509,A15,Valores!$Q$10:$Q$509,1))) -> Não informado
A16: =IF(OR(Configurar!A16="",COUNTIFS(Configurar!$A$10:A16,Configurar!A16)>1),"",Configurar!A16) -> Cavalcanti | B16: =IF(A16="","",COUNTIFS(Processos!$D$10:$D$509,A16,Processos!$AL$10:$AL$509,1)) -> 3 | C16: =IF(A16="","",COUNTIFS(Processos!$D$10:$D$509,A16,Processos!$AL$10:$AL$509,1,Processos!$Y$10:$Y$509,1)) -> 0 | D16: =IF(A16="","",COUNTIFS(Processos!$D$10:$D$509,A16,Processos!$AL$10:$AL$509,1,Processos!$AD$10:$AD$509,1)) -> 2 | E16: =IF(A16="","",IF(COUNTIFS(Valores!$P$10:$P$509,A16,Valores!$Q$10:$Q$509,1,Valores!$B$10:$B$509,">0")+COUNTIFS(Valores!$P$10:$P$509,A16,Valores!$Q$10:$Q$509,1,Valores!$B$10:$B$509,"=0",Valores!$B$10:$B$509,"<>")=0,"Não informado",SUMIFS(Valores!$B$10:$B$509,Valores!$P$10:$P$509,A16,Valores!$Q$10:$Q$509,1))) -> Não informado | F16: =IF(A16="","",IF(COUNTIFS(Valores!$P$10:$P$509,A16,Valores!$Q$10:$Q$509,1,Valores!$D$10:$D$509,">0")+COUNTIFS(Valores!$P$10:$P$509,A16,Valores!$Q$10:$Q$509,1,Valores!$D$10:$D$509,"=0",Valores!$D$10:$D$509,"<>")=0,"Não informado",SUMIFS(Valores!$D$10:$D$509,Valores!$P$10:$P$509,A16,Valores!$Q$10:$Q$509,1))) -> Não informado | G16: =IF(A16="","",IF(COUNTIFS(Valores!$P$10:$P$509,A16,Valores!$Q$10:$Q$509,1,Valores!$G$10:$G$509,">0")+COUNTIFS(Valores!$P$10:$P$509,A16,Valores!$Q$10:$Q$509,1,Valores!$G$10:$G$509,"=0",Valores!$G$10:$G$509,"<>")=0,"Não informado",SUMIFS(Valores!$G$10:$G$509,Valores!$P$10:$P$509,A16,Valores!$Q$10:$Q$509,1))) -> Não informado
A17: =IF(OR(Configurar!A17="",COUNTIFS(Configurar!$A$10:A17,Configurar!A17)>1),"",Configurar!A17) -> Joaquim Carvalho | B17: =IF(A17="","",COUNTIFS(Processos!$D$10:$D$509,A17,Processos!$AL$10:$AL$509,1)) -> 1 | C17: =IF(A17="","",COUNTIFS(Processos!$D$10:$D$509,A17,Processos!$AL$10:$AL$509,1,Processos!$Y$10:$Y$509,1)) -> 0 | D17: =IF(A17="","",COUNTIFS(Processos!$D$10:$D$509,A17,Processos!$AL$10:$AL$509,1,Processos!$AD$10:$AD$509,1)) -> 1 | E17: =IF(A17="","",IF(COUNTIFS(Valores!$P$10:$P$509,A17,Valores!$Q$10:$Q$509,1,Valores!$B$10:$B$509,">0")+COUNTIFS(Valores!$P$10:$P$509,A17,Valores!$Q$10:$Q$509,1,Valores!$B$10:$B$509,"=0",Valores!$B$10:$B$509,"<>")=0,"Não informado",SUMIFS(Valores!$B$10:$B$509,Valores!$P$10:$P$509,A17,Valores!$Q$10:$Q$509,1))) -> Não informado | F17: =IF(A17="","",IF(COUNTIFS(Valores!$P$10:$P$509,A17,Valores!$Q$10:$Q$509,1,Valores!$D$10:$D$509,">0")+COUNTIFS(Valores!$P$10:$P$509,A17,Valores!$Q$10:$Q$509,1,Valores!$D$10:$D$509,"=0",Valores!$D$10:$D$509,"<>")=0,"Não informado",SUMIFS(Valores!$D$10:$D$509,Valores!$P$10:$P$509,A17,Valores!$Q$10:$Q$509,1))) -> Não informado | G17: =IF(A17="","",IF(COUNTIFS(Valores!$P$10:$P$509,A17,Valores!$Q$10:$Q$509,1,Valores!$G$10:$G$509,">0")+COUNTIFS(Valores!$P$10:$P$509,A17,Valores!$Q$10:$Q$509,1,Valores!$G$10:$G$509,"=0",Valores!$G$10:$G$509,"<>")=0,"Não informado",SUMIFS(Valores!$G$10:$G$509,Valores!$P$10:$P$509,A17,Valores!$Q$10:$Q$509,1))) -> Não informado
A18: =IF(OR(Configurar!A18="",COUNTIFS(Configurar!$A$10:A18,Configurar!A18)>1),"",Configurar!A18) -> Sacha Calmon | B18: =IF(A18="","",COUNTIFS(Processos!$D$10:$D$509,A18,Processos!$AL$10:$AL$509,1)) -> 2 | C18: =IF(A18="","",COUNTIFS(Processos!$D$10:$D$509,A18,Processos!$AL$10:$AL$509,1,Processos!$Y$10:$Y$509,1)) -> 1 | D18: =IF(A18="","",COUNTIFS(Processos!$D$10:$D$509,A18,Processos!$AL$10:$AL$509,1,Processos!$AD$10:$AD$509,1)) -> 2 | E18: =IF(A18="","",IF(COUNTIFS(Valores!$P$10:$P$509,A18,Valores!$Q$10:$Q$509,1,Valores!$B$10:$B$509,">0")+COUNTIFS(Valores!$P$10:$P$509,A18,Valores!$Q$10:$Q$509,1,Valores!$B$10:$B$509,"=0",Valores!$B$10:$B$509,"<>")=0,"Não informado",SUMIFS(Valores!$B$10:$B$509,Valores!$P$10:$P$509,A18,Valores!$Q$10:$Q$509,1))) -> 28362468 | F18: =IF(A18="","",IF(COUNTIFS(Valores!$P$10:$P$509,A18,Valores!$Q$10:$Q$509,1,Valores!$D$10:$D$509,">0")+COUNTIFS(Valores!$P$10:$P$509,A18,Valores!$Q$10:$Q$509,1,Valores!$D$10:$D$509,"=0",Valores!$D$10:$D$509,"<>")=0,"Não informado",SUMIFS(Valores!$D$10:$D$509,Valores!$P$10:$P$509,A18,Valores!$Q$10:$Q$509,1))) -> Não informado | G18: =IF(A18="","",IF(COUNTIFS(Valores!$P$10:$P$509,A18,Valores!$Q$10:$Q$509,1,Valores!$G$10:$G$509,">0")+COUNTIFS(Valores!$P$10:$P$509,A18,Valores!$Q$10:$Q$509,1,Valores!$G$10:$G$509,"=0",Valores!$G$10:$G$509,"<>")=0,"Não informado",SUMIFS(Valores!$G$10:$G$509,Valores!$P$10:$P$509,A18,Valores!$Q$10:$Q$509,1))) -> Não informado
A19: =IF(OR(Configurar!A19="",COUNTIFS(Configurar!$A$10:A19,Configurar!A19)>1),"",Configurar!A19) -> Frois | B19: =IF(A19="","",COUNTIFS(Processos!$D$10:$D$509,A19,Processos!$AL$10:$AL$509,1)) -> 7 | C19: =IF(A19="","",COUNTIFS(Processos!$D$10:$D$509,A19,Processos!$AL$10:$AL$509,1,Processos!$Y$10:$Y$509,1)) -> 0 | D19: =IF(A19="","",COUNTIFS(Processos!$D$10:$D$509,A19,Processos!$AL$10:$AL$509,1,Processos!$AD$10:$AD$509,1)) -> 5 | E19: =IF(A19="","",IF(COUNTIFS(Valores!$P$10:$P$509,A19,Valores!$Q$10:$Q$509,1,Valores!$B$10:$B$509,">0")+COUNTIFS(Valores!$P$10:$P$509,A19,Valores!$Q$10:$Q$509,1,Valores!$B$10:$B$509,"=0",Valores!$B$10:$B$509,"<>")=0,"Não informado",SUMIFS(Valores!$B$10:$B$509,Valores!$P$10:$P$509,A19,Valores!$Q$10:$Q$509,1))) -> 25158.79 | F19: =IF(A19="","",IF(COUNTIFS(Valores!$P$10:$P$509,A19,Valores!$Q$10:$Q$509,1,Valores!$D$10:$D$509,">0")+COUNTIFS(Valores!$P$10:$P$509,A19,Valores!$Q$10:$Q$509,1,Valores!$D$10:$D$509,"=0",Valores!$D$10:$D$509,"<>")=0,"Não informado",SUMIFS(Valores!$D$10:$D$509,Valores!$P$10:$P$509,A19,Valores!$Q$10:$Q$509,1))) -> Não informado | G19: =IF(A19="","",IF(COUNTIFS(Valores!$P$10:$P$509,A19,Valores!$Q$10:$Q$509,1,Valores!$G$10:$G$509,">0")+COUNTIFS(Valores!$P$10:$P$509,A19,Valores!$Q$10:$Q$509,1,Valores!$G$10:$G$509,"=0",Valores!$G$10:$G$509,"<>")=0,"Não informado",SUMIFS(Valores!$G$10:$G$509,Valores!$P$10:$P$509,A19,Valores!$Q$10:$Q$509,1))) -> Não informado
A20: =IF(OR(Configurar!A20="",COUNTIFS(Configurar!$A$10:A20,Configurar!A20)>1),"",Configurar!A20) -> EHJC | B20: =IF(A20="","",COUNTIFS(Processos!$D$10:$D$509,A20,Processos!$AL$10:$AL$509,1)) -> 1 | C20: =IF(A20="","",COUNTIFS(Processos!$D$10:$D$509,A20,Processos!$AL$10:$AL$509,1,Processos!$Y$10:$Y$509,1)) -> 0 | D20: =IF(A20="","",COUNTIFS(Processos!$D$10:$D$509,A20,Processos!$AL$10:$AL$509,1,Processos!$AD$10:$AD$509,1)) -> 1 | E20: =IF(A20="","",IF(COUNTIFS(Valores!$P$10:$P$509,A20,Valores!$Q$10:$Q$509,1,Valores!$B$10:$B$509,">0")+COUNTIFS(Valores!$P$10:$P$509,A20,Valores!$Q$10:$Q$509,1,Valores!$B$10:$B$509,"=0",Valores!$B$10:$B$509,"<>")=0,"Não informado",SUMIFS(Valores!$B$10:$B$509,Valores!$P$10:$P$509,A20,Valores!$Q$10:$Q$509,1))) -> Não informado | F20: =IF(A20="","",IF(COUNTIFS(Valores!$P$10:$P$509,A20,Valores!$Q$10:$Q$509,1,Valores!$D$10:$D$509,">0")+COUNTIFS(Valores!$P$10:$P$509,A20,Valores!$Q$10:$Q$509,1,Valores!$D$10:$D$509,"=0",Valores!$D$10:$D$509,"<>")=0,"Não informado",SUMIFS(Valores!$D$10:$D$509,Valores!$P$10:$P$509,A20,Valores!$Q$10:$Q$509,1))) -> Não informado | G20: =IF(A20="","",IF(COUNTIFS(Valores!$P$10:$P$509,A20,Valores!$Q$10:$Q$509,1,Valores!$G$10:$G$509,">0")+COUNTIFS(Valores!$P$10:$P$509,A20,Valores!$Q$10:$Q$509,1,Valores!$G$10:$G$509,"=0",Valores!$G$10:$G$509,"<>")=0,"Não informado",SUMIFS(Valores!$G$10:$G$509,Valores!$P$10:$P$509,A20,Valores!$Q$10:$Q$509,1))) -> Não informado
A21: =IF(OR(Configurar!A21="",COUNTIFS(Configurar!$A$10:A21,Configurar!A21)>1),"",Configurar!A21) -> Romanhol | B21: =IF(A21="","",COUNTIFS(Processos!$D$10:$D$509,A21,Processos!$AL$10:$AL$509,1)) -> 1 | C21: =IF(A21="","",COUNTIFS(Processos!$D$10:$D$509,A21,Processos!$AL$10:$AL$509,1,Processos!$Y$10:$Y$509,1)) -> 0 | D21: =IF(A21="","",COUNTIFS(Processos!$D$10:$D$509,A21,Processos!$AL$10:$AL$509,1,Processos!$AD$10:$AD$509,1)) -> 1 | E21: =IF(A21="","",IF(COUNTIFS(Valores!$P$10:$P$509,A21,Valores!$Q$10:$Q$509,1,Valores!$B$10:$B$509,">0")+COUNTIFS(Valores!$P$10:$P$509,A21,Valores!$Q$10:$Q$509,1,Valores!$B$10:$B$509,"=0",Valores!$B$10:$B$509,"<>")=0,"Não informado",SUMIFS(Valores!$B$10:$B$509,Valores!$P$10:$P$509,A21,Valores!$Q$10:$Q$509,1))) -> Não informado | F21: =IF(A21="","",IF(COUNTIFS(Valores!$P$10:$P$509,A21,Valores!$Q$10:$Q$509,1,Valores!$D$10:$D$509,">0")+COUNTIFS(Valores!$P$10:$P$509,A21,Valores!$Q$10:$Q$509,1,Valores!$D$10:$D$509,"=0",Valores!$D$10:$D$509,"<>")=0,"Não informado",SUMIFS(Valores!$D$10:$D$509,Valores!$P$10:$P$509,A21,Valores!$Q$10:$Q$509,1))) -> Não informado | G21: =IF(A21="","",IF(COUNTIFS(Valores!$P$10:$P$509,A21,Valores!$Q$10:$Q$509,1,Valores!$G$10:$G$509,">0")+COUNTIFS(Valores!$P$10:$P$509,A21,Valores!$Q$10:$Q$509,1,Valores!$G$10:$G$509,"=0",Valores!$G$10:$G$509,"<>")=0,"Não informado",SUMIFS(Valores!$G$10:$G$509,Valores!$P$10:$P$509,A21,Valores!$Q$10:$Q$509,1))) -> Não informado
... A29: =IF(OR(Configurar!A29="",COUNTIFS(Configurar!$A$10:A29,Configurar!A29)>1),"",Configurar!A29) | B29: =IF(A29="","",COUNTIFS(Processos!$D$10:$D$509,A29,Processos!$AL$10:$AL$509,1)) | C29: =IF(A29="","",COUNTIFS(Processos!$D$10:$D$509,A29,Processos!$AL$10:$AL$509,1,Processos!$Y$10:$Y$509,1)) | D29: =IF(A29="","",COUNTIFS(Processos!$D$10:$D$509,A29,Processos!$AL$10:$AL$509,1,Processos!$AD$10:$AD$509,1)) | E29: =IF(A29="","",IF(COUNTIFS(Valores!$P$10:$P$509,A29,Valores!$Q$10:$Q$509,1,Valores!$B$10:$B$509,">0")+COUNTIFS(Valores!$P$10:$P$509,A29,Valores!$Q$10:$Q$509,1,Valores!$B$10:$B$509,"=0",Valores!$B$10:$B$509,"<>")=0,"Não informado",SUMIFS(Valores!$B$10:$B$509,Valores!$P$10:$P$509,A29,Valores!$Q$10:$Q$509,1))) | F29: =IF(A29="","",IF(COUNTIFS(Valores!$P$10:$P$509,A29,Valores!$Q$10:$Q$509,1,Valores!$D$10:$D$509,">0")+COUNTIFS(Valores!$P$10:$P$509,A29,Valores!$Q$10:$Q$509,1,Valores!$D$10:$D$509,"=0",Valores!$D$10:$D$509,"<>")=0,"Não informado",SUMIFS(Valores!$D$10:$D$509,Valores!$P$10:$P$509,A29,Valores!$Q$10:$Q$509,1))) | G29: =IF(A29="","",IF(COUNTIFS(Valores!$P$10:$P$509,A29,Valores!$Q$10:$Q$509,1,Valores!$G$10:$G$509,">0")+COUNTIFS(Valores!$P$10:$P$509,A29,Valores!$Q$10:$Q$509,1,Valores!$G$10:$G$509,"=0",Valores!$G$10:$G$509,"<>")=0,"Não informado",SUMIFS(Valores!$G$10:$G$509,Valores!$P$10:$P$509,A29,Valores!$Q$10:$Q$509,1)))
A31: Valores são parciais: registros marcados “Revisar” em Valores não entram nos totais.
A33: PROCESSOS NA SELEÇÃO
A34: 200 por página; escolha em D35. A lista segue os filtros do Painel.
C35: Página | D35: 1 | I35: =MAX(1,ROUNDUP(COUNTIFS(Processos!$X$10:$X$509,1)/200,0)) -> 1 | J35: =MAX(1,MIN(IFERROR(INT(D35),1),I35)) -> 1
A36: Processo | B36: Situação | C36: Autor × réu | D36: Valor da causa | E36: Atualização recebida | F36: Crítico | G36: Escritório
A37: =IF((ROW()-36+($J$35-1)*200)>COUNTIFS(Processos!$X$10:$X$509,1),"",IF(INDEX(Processos!$A$10:$A$509,MATCH((ROW()-36+($J$35-1)*200),Processos!$AK$10:$AK$509,0))="","",INDEX(Processos!$A$10:$A$509,MATCH((ROW()-36+($J$35-1)*200),Processos!$AK$10:$AK$509,0)))) -> 0000365-30.2017.5.14.0071 | B37: =IF((ROW()-36+($J$35-1)*200)>COUNTIFS(Processos!$X$10:$X$509,1),"",IF(INDEX(Processos!$C$10:$C$509,MATCH((ROW()-36+($J$35-1)*200),Processos!$AK$10:$AK$509,0))="","",INDEX(Processos!$C$10:$C$509,MATCH((ROW()-36+($J$35-1)*200),Processos!$AK$10:$AK$509,0)))) -> Suspenso | C37: =IF(LEN(SUBSTITUTE(SUBSTITUTE(IF(LEN(IF((ROW()-36+($J$35-1)*200)>COUNTIFS(Processos!$X$10:$X$509,1),"",IF(INDEX(Processos!$H$10:$H$509,MATCH((ROW()-36+($J$35-1)*200),Processos!$AK$10:$AK$509,0))&" × "&INDEX(Processos!$I$10:$I$509,MATCH((ROW()-36+($J$35-1)*200),Processos!$AK$10:$AK$509,0))="","",INDEX(Processos!$H$10:$H$509,MATCH((ROW()-36+($J$35-1)*200),Processos!$AK$10:$AK$509,0))&" × "&INDEX(Processos!$I$10:$I$509,MATCH((ROW()-36+($J$35-1)*200),Processos!$AK$10:$AK$509,0)))))>190,LEFT(IF((ROW()-36+($J$35-1)*200)>COUNTIFS(Processos!$X$10:$X$509,1),"",IF(INDEX(Processos!$H$10:$H$509,MATCH((ROW()-36+($J$35-1)*200),Processos!$AK$10:$AK$509,0))&" × "&INDEX(Processos!$I$10:$I$509,MATCH((ROW()-36+($J$35-1)*200),Processos!$AK$10:$AK$509,0))="","",INDEX(Processos!$H$10:$H$509,MATCH((ROW()-36+($J$35-1)*200),Processos!$AK$10:$AK$509,0))&" × "&INDEX(Processos!$I$10:$I$509,MATCH((ROW()-36+($J$35-1)*200),Processos!$AK$10:$AK$509,0)))),190)&" [...]",IF((ROW()-36+($J$35-1)*200)>COUNTIFS(Processos!$X$10:$X$509,1),"",IF(INDEX(Processos!$H$10:$H$509,MATCH((ROW()-36+($J$35-1)*200),Processos!$AK$10:$AK$509,0))&" × "&INDEX(Processos!$I$10:$I$509,MATCH((ROW()-36+($J$35-1)*200),Processos!$AK$10:$AK$509,0))="","",INDEX(Processos!$H$10:$H$509,MATCH((ROW()-36+($J$35-1)*200),Processos!$AK$10:$AK$509,0))&" × "&INDEX(Processos!$I$10:$I$509,MATCH((ROW()-36+($J$35-1)*200),Processos!$AK$10:$AK$509,0))))),CHAR(10)," "),CHAR(13)," "))>100,LEFT(SUBSTITUTE(SUBSTITUTE(IF(LEN(IF((ROW()-36+($J$35-1)*200)>COUNTIFS(Processos!$X$10:$X$509,1),"",IF(INDEX(Processos!$H$10:$H$509,MATCH((ROW()-36+($J$35-1)*200),Processos!$AK$10:$AK$509,0))&" × "&INDEX(Processos!$I$10:$I$509,MATCH((ROW()-36+($J$35-1)*200),Processos!$AK$10:$AK$509,0))="","",INDEX(Processos!$H$10:$H$509,MATCH((ROW()-36+($J$35-1)*200),Processos!$AK$10:$AK$509,0))&" × "&INDEX(Processos!$I$10:$I$509,MATCH((ROW()-36+($J$35-1)*200),Processos!$AK$10:$AK$509,0)))))>190,LEFT(IF((ROW()-36+($J$35-1)*200)>COUNTIFS(Processos!$X$10:$X$509,1),"",IF(INDEX(Processos!$H$10:$H$509,MATCH((ROW()-36+($J$35-1)*200),Processos!$AK$10:$AK$509,0))&" × "&INDEX(Processos!$I$10:$I$509,MATCH((ROW()-36+($J$35-1)*200),Processos!$AK$10:$AK$509,0))="","",INDEX(Processos!$H$10:$H$509,MATCH((ROW()-36+($J$35-1)*200),Processos!$AK$10:$AK$509,0))&" × "&INDEX(Processos!$I$10:$I$509,MATCH((ROW()-36+($J$35-1)*200),Processos!$AK$10:$AK$509,0)))),190)&" [...]",IF((ROW()-36+($J$35-1)*200)>COUNTIFS(Processos!$X$10:$X$509,1),"",IF(INDEX(Processos!$H$10:$H$509,MATCH((ROW()-36+($J$35-1)*200),Processos!$AK$10:$AK$509,0))&" × "&INDEX(Processos!$I$10:$I$509,MATCH((ROW()-36+($J$35-1)*200),Processos!$AK$10:$AK$509,0))="","",INDEX(Processos!$H$10:$H$509,MATCH((ROW()-36+($J$35-1)*200),Processos!$AK$10:$AK$509,0))&" × "&INDEX(Processos!$I$10:$I$509,MATCH((ROW()-36+($J$35-1)*200),Processos!$AK$10:$AK$509,0))))),CHAR(10)," "),CHAR(13)," "),100)&" [...]",SUBSTITUTE(SUBSTITUTE(IF(LEN(IF((ROW()-36+($J$35-1)*200)>COUNTIFS(Processos!$X$10:$X$509,1),"",IF(INDEX(Processos!$H$10:$H$509,MATCH((ROW()-36+($J$35-1)*200),Processos!$AK$10:$AK$509,0))&" × "&INDEX(Processos!$I$10:$I$509,MATCH((ROW()-36+($J$35-1)*200),Processos!$AK$10:$AK$509,0))="","",INDEX(Processos!$H$10:$H$509,MATCH((ROW()-36+($J$35-1)*200),Processos!$AK$10:$AK$509,0))&" × "&INDEX(Processos!$I$10:$I$509,MATCH((ROW()-36+($J$35-1)*200),Processos!$AK$10:$AK$509,0)))))>190,LEFT(IF((ROW()-36+($J$35-1)*200)>COUNTIFS(Processos!$X$10:$X$509,1),"",IF(INDEX(Processos!$H$10:$H$509,MATCH((ROW()-36+($J$35-1)*200),Processos!$AK$10:$AK$509,0))&" × "&INDEX(Processos!$I$10:$I$509,MATCH((ROW()-36+($J$35-1)*200),Processos!$AK$10:$AK$509,0))="","",INDEX(Processos!$H$10:$H$509,MATCH((ROW()-36+($J$35-1)*200),Processos!$AK$10:$AK$509,0))&" × "&INDEX(Processos!$I$10:$I$509,MATCH((ROW()-36+($J$35-1)*200),Processos!$AK$10:$AK$509,0)))),190)&" [...]",IF((ROW()-36+($J$35-1)*200)>COUNTIFS(Processos!$X$10:$X$509,1),"",IF(INDEX(Processos!$H$10:$H$509,MATCH((ROW()-36+($J$35-1)*200),Processos!$AK$10:$AK$509,0))&" × "&INDEX(Processos!$I$10:$I$509,MATCH((ROW()-36+($J$35-1)*200),Processos!$AK$10:$AK$509,0))="","",INDEX(Processos!$H$10:$H$509,MATCH((ROW()-36+($J$35-1)*200),Processos!$AK$10:$AK$509,0))&" × "&INDEX(Processos!$I$10:$I$509,MATCH((ROW()-36+($J$35-1)*200),Processos!$AK$10:$AK$509,0))))),CHAR(10)," "),CHAR(13)," ")) -> ELEANDRO VIEIRA DE ARAUJO × ALTA | D37: =IF((ROW()-36+($J$35-1)*200)>COUNTIFS(Processos!$X$10:$X$509,1),"",IF(INDEX(Processos!$AQ$10:$AQ$509,MATCH((ROW()-36+($J$35-1)*200),Processos!$AK$10:$AK$509,0))="","",INDEX(Processos!$AQ$10:$AQ$509,MATCH((ROW()-36+($J$35-1)*200),Processos!$AK$10:$AK$509,0)))) -> 50000 | E37: =IF((ROW()-36+($J$35-1)*200)>COUNTIFS(Processos!$X$10:$X$509,1),"",IF(INDEX(Processos!$Z$10:$Z$509,MATCH((ROW()-36+($J$35-1)*200),Processos!$AK$10:$AK$509,0))="","",INDEX(Processos!$Z$10:$Z$509,MATCH((ROW()-36+($J$35-1)*200),Processos!$AK$10:$AK$509,0)))) -> 46055 | F37: =IF((ROW()-36+($J$35-1)*200)>COUNTIFS(Processos!$X$10:$X$509,1),"",IF(IF(INDEX(Processos!$Y$10:$Y$509,MATCH((ROW()-36+($J$35-1)*200),Processos!$AK$10:$AK$509,0))=1,"Sim","Não")="","",IF(INDEX(Processos!$Y$10:$Y$509,MATCH((ROW()-36+($J$35-1)*200),Processos!$AK$10:$AK$509,0))=1,"Sim","Não"))) -> Não | G37: =IF((ROW()-36+($J$35-1)*200)>COUNTIFS(Processos!$X$10:$X$509,1),"",IF(INDEX(Processos!$D$10:$D$509,MATCH((ROW()-36+($J$35-1)*200),Processos!$AK$10:$AK$509,0))="","",INDEX(Processos!$D$10:$D$509,MATCH((ROW()-36+($J$35-1)*200),Processos!$AK$10:$AK$509,0)))) -> BMM Advogados
A38: =IF((ROW()-36+($J$35-1)*200)>COUNTIFS(Processos!$X$10:$X$509,1),"",IF(INDEX(Processos!$A$10:$A$509,MATCH((ROW()-36+($J$35-1)*200),Processos!$AK$10:$AK$509,0))="","",INDEX(Processos!$A$10:$A$509,MATCH((ROW()-36+($J$35-1)*200),Processos!$AK$10:$AK$509,0)))) -> 0010045-55.2019.5.18.0201 | B38: =IF((ROW()-36+($J$35-1)*200)>COUNTIFS(Processos!$X$10:$X$509,1),"",IF(INDEX(Processos!$C$10:$C$509,MATCH((ROW()-36+($J$35-1)*200),Processos!$AK$10:$AK$509,0))="","",INDEX(Processos!$C$10:$C$509,MATCH((ROW()-36+($J$35-1)*200),Processos!$AK$10:$AK$509,0)))) -> Arquivado | C38: =IF(LEN(SUBSTITUTE(SUBSTITUTE(IF(LEN(IF((ROW()-36+($J$35-1)*200)>COUNTIFS(Processos!$X$10:$X$509,1),"",IF(INDEX(Processos!$H$10:$H$509,MATCH((ROW()-36+($J$35-1)*200),Processos!$AK$10:$AK$509,0))&" × "&INDEX(Processos!$I$10:$I$509,MATCH((ROW()-36+($J$35-1)*200),Processos!$AK$10:$AK$509,0))="","",INDEX(Processos!$H$10:$H$509,MATCH((ROW()-36+($J$35-1)*200),Processos!$AK$10:$AK$509,0))&" × "&INDEX(Processos!$I$10:$I$509,MATCH((ROW()-36+($J$35-1)*200),Processos!$AK$10:$AK$509,0)))))>190,LEFT(IF((ROW()-36+($J$35-1)*200)>COUNTIFS(Processos!$X$10:$X$509,1),"",IF(INDEX(Processos!$H$10:$H$509,MATCH((ROW()-36+($J$35-1)*200),Processos!$AK$10:$AK$509,0))&" × "&INDEX(Processos!$I$10:$I$509,MATCH((ROW()-36+($J$35-1)*200),Processos!$AK$10:$AK$509,0))="","",INDEX(Processos!$H$10:$H$509,MATCH((ROW()-36+($J$35-1)*200),Processos!$AK$10:$AK$509,0))&" × "&INDEX(Processos!$I$10:$I$509,MATCH((ROW()-36+($J$35-1)*200),Processos!$AK$10:$AK$509,0)))),190)&" [...]",IF((ROW()-36+($J$35-1)*200)>COUNTIFS(Processos!$X$10:$X$509,1),"",IF(INDEX(Processos!$H$10:$H$509,MATCH((ROW()-36+($J$35-1)*200),Processos!$AK$10:$AK$509,0))&" × "&INDEX(Processos!$I$10:$I$509,MATCH((ROW()-36+($J$35-1)*200),Processos!$AK$10:$AK$509,0))="","",INDEX(Processos!$H$10:$H$509,MATCH((ROW()-36+($J$35-1)*200),Processos!$AK$10:$AK$509,0))&" × "&INDEX(Processos!$I$10:$I$509,MATCH((ROW()-36+($J$35-1)*200),Processos!$AK$10:$AK$509,0))))),CHAR(10)," "),CHAR(13)," "))>100,LEFT(SUBSTITUTE(SUBSTITUTE(IF(LEN(IF((ROW()-36+($J$35-1)*200)>COUNTIFS(Processos!$X$10:$X$509,1),"",IF(INDEX(Processos!$H$10:$H$509,MATCH((ROW()-36+($J$35-1)*200),Processos!$AK$10:$AK$509,0))&" × "&INDEX(Processos!$I$10:$I$509,MATCH((ROW()-36+($J$35-1)*200),Processos!$AK$10:$AK$509,0))="","",INDEX(Processos!$H$10:$H$509,MATCH((ROW()-36+($J$35-1)*200),Processos!$AK$10:$AK$509,0))&" × "&INDEX(Processos!$I$10:$I$509,MATCH((ROW()-36+($J$35-1)*200),Processos!$AK$10:$AK$509,0)))))>190,LEFT(IF((ROW()-36+($J$35-1)*200)>COUNTIFS(Processos!$X$10:$X$509,1),"",IF(INDEX(Processos!$H$10:$H$509,MATCH((ROW()-36+($J$35-1)*200),Processos!$AK$10:$AK$509,0))&" × "&INDEX(Processos!$I$10:$I$509,MATCH((ROW()-36+($J$35-1)*200),Processos!$AK$10:$AK$509,0))="","",INDEX(Processos!$H$10:$H$509,MATCH((ROW()-36+($J$35-1)*200),Processos!$AK$10:$AK$509,0))&" × "&INDEX(Processos!$I$10:$I$509,MATCH((ROW()-36+($J$35-1)*200),Processos!$AK$10:$AK$509,0)))),190)&" [...]",IF((ROW()-36+($J$35-1)*200)>COUNTIFS(Processos!$X$10:$X$509,1),"",IF(INDEX(Processos!$H$10:$H$509,MATCH((ROW()-36+($J$35-1)*200),Processos!$AK$10:$AK$509,0))&" × "&INDEX(Processos!$I$10:$I$509,MATCH((ROW()-36+($J$35-1)*200),Processos!$AK$10:$AK$509,0))="","",INDEX(Processos!$H$10:$H$509,MATCH((ROW()-36+($J$35-1)*200),Processos!$AK$10:$AK$509,0))&" × "&INDEX(Processos!$I$10:$I$509,MATCH((ROW()-36+($J$35-1)*200),Processos!$AK$10:$AK$509,0))))),CHAR(10)," "),CHAR(13)," "),100)&" [...]",SUBSTITUTE(SUBSTITUTE(IF(LEN(IF((ROW()-36+($J$35-1)*200)>COUNTIFS(Processos!$X$10:$X$509,1),"",IF(INDEX(Processos!$H$10:$H$509,MATCH((ROW()-36+($J$35-1)*200),Processos!$AK$10:$AK$509,0))&" × "&INDEX(Processos!$I$10:$I$509,MATCH((ROW()-36+($J$35-1)*200),Processos!$AK$10:$AK$509,0))="","",INDEX(Processos!$H$10:$H$509,MATCH((ROW()-36+($J$35-1)*200),Processos!$AK$10:$AK$509,0))&" × "&INDEX(Processos!$I$10:$I$509,MATCH((ROW()-36+($J$35-1)*200),Processos!$AK$10:$AK$509,0)))))>190,LEFT(IF((ROW()-36+($J$35-1)*200)>COUNTIFS(Processos!$X$10:$X$509,1),"",IF(INDEX(Processos!$H$10:$H$509,MATCH((ROW()-36+($J$35-1)*200),Processos!$AK$10:$AK$509,0))&" × "&INDEX(Processos!$I$10:$I$509,MATCH((ROW()-36+($J$35-1)*200),Processos!$AK$10:$AK$509,0))="","",INDEX(Processos!$H$10:$H$509,MATCH((ROW()-36+($J$35-1)*200),Processos!$AK$10:$AK$509,0))&" × "&INDEX(Processos!$I$10:$I$509,MATCH((ROW()-36+($J$35-1)*200),Processos!$AK$10:$AK$509,0)))),190)&" [...]",IF((ROW()-36+($J$35-1)*200)>COUNTIFS(Processos!$X$10:$X$509,1),"",IF(INDEX(Processos!$H$10:$H$509,MATCH((ROW()-36+($J$35-1)*200),Processos!$AK$10:$AK$509,0))&" × "&INDEX(Processos!$I$10:$I$509,MATCH((ROW()-36+($J$35-1)*200),Processos!$AK$10:$AK$509,0))="","",INDEX(Processos!$H$10:$H$509,MATCH((ROW()-36+($J$35-1)*200),Processos!$AK$10:$AK$509,0))&" × "&INDEX(Processos!$I$10:$I$509,MATCH((ROW()-36+($J$35-1)*200),Processos!$AK$10:$AK$509,0))))),CHAR(10)," "),CHAR(13)," ")) -> PAULO CESAR DE FREITAS × 1 - Consórcio Trail-Spavias-Alta 2 - Trail Infraestrutura LTDA 3 - Spavias [...] | D38: =IF((ROW()-36+($J$35-1)*200)>COUNTIFS(Processos!$X$10:$X$509,1),"",IF(INDEX(Processos!$AQ$10:$AQ$509,MATCH((ROW()-36+($J$35-1)*200),Processos!$AK$10:$AK$509,0))="","",INDEX(Processos!$AQ$10:$AQ$509,MATCH((ROW()-36+($J$35-1)*200),Processos!$AK$10:$AK$509,0)))) -> 125064.62 | E38: =IF((ROW()-36+($J$35-1)*200)>COUNTIFS(Processos!$X$10:$X$509,1),"",IF(INDEX(Processos!$Z$10:$Z$509,MATCH((ROW()-36+($J$35-1)*200),Processos!$AK$10:$AK$509,0))="","",INDEX(Processos!$Z$10:$Z$509,MATCH((ROW()-36+($J$35-1)*200),Processos!$AK$10:$AK$509,0)))) -> 45512 | F38: =IF((ROW()-36+($J$35-1)*200)>COUNTIFS(Processos!$X$10:$X$509,1),"",IF(IF(INDEX(Processos!$Y$10:$Y$509,MATCH((ROW()-36+($J$35-1)*200),Processos!$AK$10:$AK$509,0))=1,"Sim","Não")="","",IF(INDEX(Processos!$Y$10:$Y$509,MATCH((ROW()-36+($J$35-1)*200),Processos!$AK$10:$AK$509,0))=1,"Sim","Não"))) -> Não | G38: =IF((ROW()-36+($J$35-1)*200)>COUNTIFS(Processos!$X$10:$X$509,1),"",IF(INDEX(Processos!$D$10:$D$509,MATCH((ROW()-36+($J$35-1)*200),Processos!$AK$10:$AK$509,0))="","",INDEX(Processos!$D$10:$D$509,MATCH((ROW()-36+($J$35-1)*200),Processos!$AK$10:$AK$509,0)))) -> BMM Advogados
